Workbook
Name Abs_Balance: [1]Data!$V$1:$V$5000
Name ABS_PL: [1]Data!$AD$1:$AD$5000
Name ABS_PL_30: [1]Data!$AG$1:$AG$5000
Name Asset_Liab: [1]Data!$W$1:$W$5000
Name ATF: '[2]Lookup - Tables_LM'!$B$8:$B$13
Name Bal_to_Conf: [1]Data!$D$1:$D$5000
Name BOS: [3]Notes!$B$34:$C$54
Name BOS_List: [3]Notes!$B$35:$B$52
Name CONF: [1]Data!$K$1:$K$5000
Name Contingent: '[2]Adj Factors'!$B$106:$B$108
Name Countries: 'Country List'!$A$2:$A$160
Name Cr_Recon: [1]Data!$AB$1:$AB$5000
Name Data_2: '[4]CH6 Data'!$A$1:$P$51
Name Data_2: '[5]CH6 Data'!$A$1:$P$51
Name Date: [1]Inputs!$C$3
Name Debt_2: '[2]Adj Factors'!$D$83:$D$85
Name Debt_LM: '[2]Adj Factors'!$B$112:$B$114
Name Dr_Recon: [1]Data!$AA$1:$AA$5000
Name GDP_1: '[2]Adj Factors'!$B$55:$B$57
Name GDP_2: '[2]Adj Factors'!$B$60:$B$61
Name GDP_3: '[2]Adj Factors'!$B$64:$B$66
Name GDP_5: '[2]Adj Factors'!$B$73:$B$74
Name GDP_6: '[2]Adj Factors'!$B$77:$B$79
Name GetChart: IF([4]CH7!$B$7=1,INDIRECT("CH7!$B$14"),INDIRECT("CH7!$B$19"))
Name GetChart: IF([5]CH7!$B$7=1,INDIRECT("CH7!$B$14"),INDIRECT("CH7!$B$19"))
Name Getdata: IF([4]CH7!$E$7="Sales",INDIRECT("Source!$C$26"),IF([6]Example!$B$6="COS",INDIRECT("Source!$C$27"),INDIRECT("Source!$C$28")))
Name Getdata: IF([5]CH7!$E$7="Sales",INDIRECT("Source!$C$26"),IF([6]Example!$B$6="COS",INDIRECT("Source!$C$27"),INDIRECT("Source!$C$28")))
Name Green_2: [4]CH6!$G$24
Name Green_2: [5]CH6!$G$24
Name H_Expenses2: [4]CH5!#REF!
Name H_Expenses2: [5]CH5!#REF!
Name HIGH: 'Country List'!$G$2:$G$79
Name KPI_List: [4]Inputs!$J$8:$J$12
Name KPI_List: [5]Inputs!$J$8:$J$12
Name KPI_Name: [4]Inputs!$J$8:$K$11
Name KPI_Name: [5]Inputs!$J$8:$K$11
Name LOW: 'Country List'!$F$2:$F$49
Name Min_2: [4]CH6!$F$20
Name Min_2: [5]CH6!$F$20
Name No_Recon: [1]Data!$AC$1:$AC$5000
Name No_SARS: [1]Data!$U$1:$U$5000
Name Nodata: 'Country List'!$H$2:$H$35
Name Non_submission: [1]Data!$Z$1:$Z$5000
Name Period: [4]Data!$A$1:$A$141
Name Period: [5]Data!$A$1:$A$141
Name Period_List: [4]Inputs!$H$8:$H$20
Name Period_List: [5]Inputs!$H$8:$H$20
Name Period_List2: [4]Inputs!$H$9:$H$20
Name Period_List2: [5]Inputs!$H$9:$H$20
Name PL_CR: [1]Data!$AE$1:$AE$5000
Name PL_CR_30: [1]Data!$AH$1:$AH$5000
Name PL_DR: [1]Data!$AF$1:$AF$5000
Name PL_DR_30: [1]Data!$AI$1:$AI$5000
Name Position_Range: [4]Inputs!$B$8:$B$15
Name Position_Range: [5]Inputs!$B$8:$B$15
Name PRE: '[2]Lookup - Tables_LM'!$B$16:$B$22
Name Prod: [4]CH7!$F$28:$F$32
Name Prod: [5]CH7!$F$28:$F$32
Name Prod_List: [4]Inputs!$F$8:$F$12
Name Prod_List: [5]Inputs!$F$8:$F$12

Sheet Home
C8: Country Model
B9: Select Country and then the applicable Segment | G9: Select Segment directly
B10: Countries | F10: OR | G10: Country Segments
B12: SOUTH AFRICA | G12: • | H12: High Segment Country Model
G13: • | H13: Low Segment Country Model
B14: • | C14: =IF(ISNUMBER(MATCH(B12,'Country List'!F2:F49,0)),HYPERLINK("#'Low Segment'!A1","Low Segment Country Model"),IF(ISNUMBER(MATCH(B12,'Country List'!G2:G79,0)),HYPERLINK("#'High Segment'!A1","High Segment Country Model"),HYPERLINK("#'No Data Segment'!A1","No Data Model"))) -> Low Segment Country Model | G14: • | H14: No Data Model

Sheet High Segment
I1: Low mapping
I2: Economic | J2: Currency | K2: Finance | L2: Political | M2: Bus Risk | N2: Risk | O2: Overall
I3: 0 | J3: 0 | K3: 0 | L3: 0 | M3: 0 | N3: 0 | O3: 0 | P3: Very Low Risk
B4: HIGH HUMAN DEVELOPMENT | I4: 20 | J4: 20 | K4: 20 | L4: 20 | M4: 20 | N4: 20 | O4: 20 | P4: Low Risk
I5: 40 | J5: 40 | K5: 40 | L5: 40 | M5: 40 | N5: 40 | O5: 40 | P5: Moderate Risk
B6: Country Name | D6: UNITED STATES | I6: 60 | J6: 60 | K6: 60 | L6: 60 | M6: 60 | N6: 60 | O6: 60 | P6: High Risk
B7: ISO Code | D7: =VLOOKUP(D6,'Country List'!$A:$D,2,FALSE) -> USA | I7: 80 | J7: 80 | K7: 80 | L7: 80 | M7: 80 | N7: 80 | O7: 80 | P7: Very High Risk
B8: HDI Segmentation | D8: =VLOOKUP(D7,'Country List'!$B:$D,2,FALSE) -> VERY HIGH HUMAN DEVELOPMENT | I8: 100 | J8: 100 | K8: 100 | L8: 100 | M8: 100 | N8: 100 | O8: 100 | P8: Default
B9: Region | D9: =VLOOKUP(D7,'Country List'!$B:$D,3,FALSE) -> DEVELOPED MARKET | I9: Model Drivers
I10: Inflation 5 year average | J10: dcpi_5_adj | K10: 0.36915 | L10: 0.17699423 | M10: =0.5*L10 -> 0.088497113 | N10: =SUM(M10:M14) -> 0.35360935 | O10: =SUM(N10:N18) -> 0.5
I11: Nominal Interest Rate Volatility | J11: nom_rir_vol | K11: 0.30992 | L11: 0.031468549 | M11: =0.5*L11 -> 0.015734274
I12: GDP per Capita | J12: GDP_CAPITA | K12: 0.48583 | L12: 0.29341459 | M12: =0.5*L12 -> 0.1467073
I13: Growth Volatility | J13: growth_vol | K13: 0.21098 | L13: 0.043085309 | M13: =0.5*L13 -> 0.021542654
I14: Macroeconomic | J14: macro_var | K14: 0.30523 | L14: 0.16225603 | M14: =0.5*L14 -> 0.081128016
I15: Access to Finance | J15: atf | K15: 0.16803 | L15: 0.060577427 | M15: =0.5*L15 -> 0.030288713 | N15: =SUM(M15:M17) -> 0.11080833
I16: Debt Trend | J16: DT | K16: 0.31148 | L16: 0.054668955 | M16: =0.5*L16 -> 0.027334477
I17: Foreign Debt to GDP 3 year average | J17: FDG_3yr | K17: 0.2757 | L17: 0.10637028 | M17: =0.5*L17 -> 0.05318514
I18: Cost of Funds | J18: cof | K18: 0.17338 | L18: 0.07116463 | M18: =0.5*L18 -> 0.035582315 | N18: =M18 -> 0.035582315
I19: Political Risk Environment | J19: pr | K19: 0.31528 | L19: 0.27089516 | M19: =0.5*L19 -> 0.13544758 | N19: =M19 -> 0.13544758 | O19: =SUM(N19:N22) -> 0.5
I20: Rule of Law | J20: rol | K20: 0.4947 | L20: 0.45860746 | M20: =0.5*L20 -> 0.22930373 | N20: =SUM(M20:M21) -> 0.29387428
I21: Doing Business | J21: db | K21: 0.17546 | L21: 0.12914111 | M21: =0.5*L21 -> 0.064570554
I22: Security Risk | J22: sr | K22: 0.18997 | L22: 0.14135627 | M22: =0.5*L22 -> 0.070678136 | N22: =M22 -> 0.070678136
I23: Quant | J23: yhat_Quant | K23: 0.33531 | L23: 0.29206231 | M23: 0.2921443 | N23: 0.29206231 | O23: =SUM(N23:N24) -> 1
I24: Qual | J24: yhat_qual | K24: 0.74942 | L24: 0.70793769 | M24: 0.7078557 | N24: 0.70793769
I25: Quant | J25: yhat_Quant | K25: 0.54747 | L25: 0.50000345 | M25: 0.50000345 | N25: =M25 -> 0.50000345 | O25: =SUM(N25:N26) -> 1
I26: Qual | J26: yhat_qual_ridge | K26: 0.54011 | L26: 0.49999655 | M26: 0.49999655 | N26: =M26 -> 0.49999655
J27: Intercept Quant | K27: 0.78489
J28: Intercept Qual_Ridge | K28: 0.08359
J29: Intercept Quant/Qual (Unrestricted) | K29: 0.04155
J30: Intercept Final (Restricted) | K30: 0.04295
B33: Base Model
C34: Factors | D34: Raw Value | E34: Weight | F34: Raw Fitted Value | G34: Bucket # | I34: Std Fitted Value
B35: Economic | C35: =I10 -> Inflation 5 year average | D35: =IF(VLOOKUP($D$7,High_Seg2!$C:$BX,6,FALSE)="","",VLOOKUP($D$7,High_Seg2!$C:$BX,6,FALSE)) -> 2.2206 | E35: =M10 -> 0.088497113 | F35: =IF($D35="",VLOOKUP(9999999999,Buckets!$E$9:$M$15,8,TRUE),VLOOKUP($D35,Buckets!$E$9:$M$15,8,TRUE)) -> 1.2928828 | G35: =IF($D35="",VLOOKUP(9999999999,Buckets!$E$9:$M$15,9,TRUE),VLOOKUP($D35,Buckets!$E$9:$M$15,9,TRUE)) -> 1 | I35: =IF($D35="",VLOOKUP(9999999999,Buckets!$E$9:$M$15,7,TRUE),VLOOKUP($D35,Buckets!$E$9:$M$15,7,TRUE)) -> -0.9733
C36: =I11 -> Nominal Interest Rate Volatility | D36: =IF(VLOOKUP($D$7,High_Seg2!$C:$BX,16,FALSE)="","",VLOOKUP($D$7,High_Seg2!$C:$BX,16,FALSE)) -> 24.787811 | E36: =M11 -> 0.015734274 | F36: =IF($D36="",VLOOKUP(9999999999,Buckets!$E$138:$M$143,8,TRUE),VLOOKUP($D36,Buckets!$E$138:$M$143,8,TRUE)) -> 8.0021865 | G36: =IF($D36="",VLOOKUP(9999999999,Buckets!$E$138:$M$143,9,TRUE),VLOOKUP($D36,Buckets!$E$138:$M$143,9,TRUE)) -> 5 | I36: =IF($D36="",VLOOKUP(9999999999,Buckets!$E$138:$M$143,7,TRUE),VLOOKUP($D36,Buckets!$E$138:$M$143,7,TRUE)) -> -0.591
C37: =I12 -> GDP per Capita | D37: =IF(VLOOKUP($D$7,High_Seg2!$C:$BX,7,FALSE)="","",VLOOKUP($D$7,High_Seg2!$C:$BX,7,FALSE)) -> 48170 | E37: =M12 -> 0.1467073 | F37: =IF($D37="",VLOOKUP(999999999,Buckets!$E$19:$M$24,8,TRUE),VLOOKUP($D37,Buckets!$E$19:$M$24,8,TRUE)) -> -14130.835 | G37: =IF($D37="",VLOOKUP(999999999,Buckets!$E$19:$M$24,9,TRUE),VLOOKUP($D37,Buckets!$E$19:$M$24,9,TRUE)) -> 6 | I37: =IF($D37="",VLOOKUP(999999999,Buckets!$E$19:$M$24,7,TRUE),VLOOKUP($D37,Buckets!$E$19:$M$24,7,TRUE)) -> -1.5742
C38: =I13 -> Growth Volatility | D38: =IF(VLOOKUP($D$7,High_Seg2!$C:$BX,15,FALSE)="","",VLOOKUP($D$7,High_Seg2!$C:$BX,15,FALSE)) -> 2.5693265 | E38: =M13 -> 0.021542654 | F38: =IF($D38="",VLOOKUP(999999999,Buckets!$E$129:$M$134,8,TRUE),VLOOKUP($D38,Buckets!$E$129:$M$134,8,TRUE)) -> 1.779107 | G38: =IF($D38="",VLOOKUP(999999999,Buckets!$E$129:$M$134,9,TRUE),VLOOKUP($D38,Buckets!$E$129:$M$134,9,TRUE)) -> 4 | I38: =IF($D38="",VLOOKUP(999999999,Buckets!$E$129:$M$134,7,TRUE),VLOOKUP($D38,Buckets!$E$129:$M$134,7,TRUE)) -> -0.4183
C39: =I14 -> Macroeconomic | D39: =IF(VLOOKUP($D$7,High_Seg2!$C:$BX,10,FALSE)="","",VLOOKUP($D$7,High_Seg2!$C:$BX,10,FALSE)) -> 2 | E39: =M14 -> 0.081128016 | F39: =IF($D39="",VLOOKUP(9999999999,Buckets!$E$73:$M$78,8,TRUE),VLOOKUP($D39,Buckets!$E$73:$M$78,8,TRUE)) -> 2.1614379 | G39: =IF($D39="",VLOOKUP(9999999999,Buckets!$E$73:$M$78,9,TRUE),VLOOKUP($D39,Buckets!$E$73:$M$78,9,TRUE)) -> 2 | I39: =IF($D39="",VLOOKUP(9999999999,Buckets!$E$73:$M$78,7,TRUE),VLOOKUP($D39,Buckets!$E$73:$M$78,7,TRUE)) -> -1.1529
C41: Category Assessment | D41: =(SUMPRODUCT(K10:K14,I35:I39)+$K$25*E41)*Standardisation_Parameters!$F$2+Standardisation_Parameters!$E$2 -> 18.698955 | E41: =SUM(E35:E39) -> 0.35360935 | F41: =VLOOKUP($D41,$I$3:$P$8,8,TRUE) -> Very Low Risk
B43: Currency | C43: =I15 -> Access to Finance | D43: =IF(VLOOKUP($D$7,High_Seg2!$C:$BX,2,FALSE)="","",VLOOKUP($D$7,High_Seg2!$C:$BX,2,FALSE)) -> 1 | E43: =M15 -> 0.030288713 | F43: =IF($D43="",VLOOKUP(9999999999,Buckets!$E$4:$M$6,8,TRUE),VLOOKUP($D43,Buckets!$E$4:$M$6,8,TRUE)) -> 1.190268 | G43: =IF($D43="",VLOOKUP(9999999999,Buckets!$E$4:$M$6,9,TRUE),VLOOKUP($D43,Buckets!$E$4:$M$6,9,TRUE)) -> 1 | I43: =IF($D43="",VLOOKUP(9999999999,Buckets!$E$4:$M$6,7,TRUE),VLOOKUP($D43,Buckets!$E$4:$M$6,7,TRUE)) -> -0.7287
C44: =I16 -> Debt Trend | D44: =IF(VLOOKUP($D$7,High_Seg2!$C:$BX,8,FALSE)="","",VLOOKUP($D$7,High_Seg2!$C:$BX,8,FALSE)) -> 0.82238578 | E44: =M16 -> 0.027334477 | F44: =IF($D44="",VLOOKUP(9999999999,Buckets!$E$37:$M$42,8,TRUE),VLOOKUP($D44,Buckets!$E$37:$M$42,8,TRUE)) -> -15.191739 | G44: =IF($D44="",VLOOKUP(9999999999,Buckets!$E$37:$M$42,9,TRUE),VLOOKUP($D44,Buckets!$E$37:$M$42,9,TRUE)) -> 3 | I44: =IF($D44="",VLOOKUP(9999999999,Buckets!$E$37:$M$42,7,TRUE),VLOOKUP($D44,Buckets!$E$37:$M$42,7,TRUE)) -> -0.4274
C45: =I17 -> Foreign Debt to GDP 3 year average | D45: =IF(VLOOKUP($D$7,High_Seg2!$C:$BX,9,FALSE)="","",VLOOKUP($D$7,High_Seg2!$C:$BX,9,FALSE)) -> 99.291191 | E45: =M17 -> 0.05318514 | F45: =IF($D45="",VLOOKUP(9999999999,Buckets!$E$55:$M$60,8,TRUE),VLOOKUP($D45,Buckets!$E$55:$M$60,8,TRUE)) -> -29.743831 | G45: =IF($D45="",VLOOKUP(9999999999,Buckets!$E$55:$M$60,9,TRUE),VLOOKUP($D45,Buckets!$E$55:$M$60,9,TRUE)) -> 5 | I45: =IF($D45="",VLOOKUP(9999999999,Buckets!$E$55:$M$60,7,TRUE),VLOOKUP($D45,Buckets!$E$55:$M$60,7,TRUE)) -> -0.8995
C47: Category Assessment | D47: =(SUMPRODUCT(K15:K17,I43:I45)+$K$25*E47)*Standardisation_Parameters!$F$2+Standardisation_Parameters!$E$2 -> 37.267939 | E47: =SUM(E43:E45) -> 0.11080833 | F47: =VLOOKUP($D47,$J$3:$P$8,7,TRUE) -> Low Risk
B49: Finance | C49: =I18 -> Cost of Funds | D49: =IF(VLOOKUP($D$7,High_Seg2!$C:$BX,5,FALSE)="","",VLOOKUP($D$7,High_Seg2!$C:$BX,5,FALSE)) -> 0.2 | E49: =M18 -> 0.035582315 | F49: =IF($D49="",VLOOKUP(9999999999,Buckets!$E$28:$M$33,8,TRUE),VLOOKUP($D49,Buckets!$E$28:$M$33,8,TRUE)) -> -0.30906646 | G49: =IF($D49="",VLOOKUP(9999999999,Buckets!$E$28:$M$33,9,TRUE),VLOOKUP($D49,Buckets!$E$28:$M$33,9,TRUE)) -> 1 | I49: =IF($D49="",VLOOKUP(9999999999,Buckets!$E$28:$M$33,7,TRUE),VLOOKUP($D49,Buckets!$E$28:$M$33,7,TRUE)) -> -1.2093
C51: Category Assessment | D51: =((I49*K18)+$K$25*E51)*Standardisation_Parameters!$F$2+Standardisation_Parameters!$E$2 -> 41.491995 | E51: =SUM(E49) -> 0.035582315 | F51: =VLOOKUP($D51,$K$3:$P$8,6,TRUE) -> Moderate Risk
B53: Political | C53: =I19 -> Political Risk Environment | D53: =IF(VLOOKUP($D$7,High_Seg2!$C:$BX,12,FALSE)="","",VLOOKUP($D$7,High_Seg2!$C:$BX,12,FALSE)) -> 2 | E53: =M19 -> 0.13544758 | F53: =IF($D53="",VLOOKUP(9999999999,Buckets!$E$90:$M$94,8,TRUE),VLOOKUP($D53,Buckets!$E$90:$M$94,8,TRUE)) -> 2.1092142 | G53: =IF($D53="",VLOOKUP(9999999999,Buckets!$E$90:$M$94,9,TRUE),VLOOKUP($D53,Buckets!$E$90:$M$94,9,TRUE)) -> 2 | I53: =IF($D53="",VLOOKUP(9999999999,Buckets!$E$90:$M$94,7,TRUE),VLOOKUP($D53,Buckets!$E$90:$M$94,7,TRUE)) -> -0.9315
C55: Category Assessment | D55: =((I53*K19)+$K$26*E55)*Standardisation_Parameters!$F$2+Standardisation_Parameters!$E$2 -> 40.984885 | E55: =SUM(E53) -> 0.13544758 | F55: =VLOOKUP($D55,$L$3:$P$8,5,TRUE) -> Moderate Risk
B57: Business Risk | C57: =I20 -> Rule of Law | D57: =IF(VLOOKUP($D$7,High_Seg2!$C:$BX,13,FALSE)="","",VLOOKUP($D$7,High_Seg2!$C:$BX,13,FALSE)) -> 1.594333 | E57: =M20 -> 0.22930373 | F57: =IF($D57="",VLOOKUP(9999999999,Buckets!$E$100:$M$105,8,TRUE),VLOOKUP($D57,Buckets!$E$100:$M$105,8,TRUE)) -> -1.1879613 | G57: =IF($D57="",VLOOKUP(9999999999,Buckets!$E$100:$M$105,9,TRUE),VLOOKUP($D57,Buckets!$E$100:$M$105,9,TRUE)) -> 5 | I57: =IF($D57="",VLOOKUP(9999999999,Buckets!$E$100:$M$105,7,TRUE),VLOOKUP($D57,Buckets!$E$100:$M$105,7,TRUE)) -> -1.2543
C58: =I21 -> Doing Business | D58: =IF(VLOOKUP($D$7,High_Seg2!$C:$BX,11,FALSE)="","",VLOOKUP($D$7,High_Seg2!$C:$BX,11,FALSE)) -> 2.1857923 | E58: =M21 -> 0.064570554 | F58: =IF($D58="",VLOOKUP(9999999999,Buckets!$E$81:$M$86,8,TRUE),VLOOKUP($D58,Buckets!$E$81:$M$86,8,TRUE)) -> 2.8096146 | G58: =IF($D58="",VLOOKUP(9999999999,Buckets!$E$81:$M$86,9,TRUE),VLOOKUP($D58,Buckets!$E$81:$M$86,9,TRUE)) -> 1 | I58: =IF($D58="",VLOOKUP(9999999999,Buckets!$E$81:$M$86,7,TRUE),VLOOKUP($D58,Buckets!$E$81:$M$86,7,TRUE)) -> -1.491
C60: Category Assessment | D60: =(SUMPRODUCT(K20:K21,I57:I58)+$K$26*E60)*Standardisation_Parameters!$F$2+Standardisation_Parameters!$E$2 -> 32.579524 | E60: =SUM(E56:E58) -> 0.29387428 | F60: =VLOOKUP($D60,$M$3:$P$8,4,TRUE) -> Low Risk
B62: Risk | C62: =I22 -> Security Risk | D62: =IF(VLOOKUP($D$7,High_Seg2!$C:$BX,14,FALSE)="","",VLOOKUP($D$7,High_Seg2!$C:$BX,14,FALSE)) -> 2.5 | E62: =M22 -> 0.070678136 | F62: =IF($D62="",VLOOKUP(9999999999,Buckets!$E$109:$M$114,8,TRUE),VLOOKUP($D62,Buckets!$E$109:$M$114,8,TRUE)) -> 2.2913351 | G62: =IF($D62="",VLOOKUP(9999999999,Buckets!$E$109:$M$114,9,TRUE),VLOOKUP($D62,Buckets!$E$109:$M$114,9,TRUE)) -> 4 | I62: =IF($D62="",VLOOKUP(9999999999,Buckets!$E$109:$M$114,7,TRUE),VLOOKUP($D62,Buckets!$E$109:$M$114,7,TRUE)) -> -0.4412
C64: Category Assessment | D64: =((I62*K22)+$K$26*E64)*Standardisation_Parameters!$F$2+Standardisation_Parameters!$E$2 -> 43.908112 | E64: =SUM(E62:E62) -> 0.070678136 | F64: =VLOOKUP(D64,$N$3:$P$8,3,TRUE) -> Moderate Risk
J65: Lookup Raw | K65: Lookup STD
B66: Overall | C66: Quantitative Score | D66: =((K10*I35+K11*I36+K12*I37+K13*I38+K14*I39+K15*I43+K16*I44+K17*I45+K18*I49)+K27)*Standardisation_Parameters!$F$2+Standardisation_Parameters!$E$2 -> 16.66087 | E66: =SUM(E41,E51,E47) -> 0.5 | F66: =VLOOKUP(D66,$O$3:$P$8,2,TRUE) -> Very Low Risk | I66: =(K10*I35+K11*I36+K12*I37+K13*I38+K14*I39+K15*I43+K16*I44+K17*I45+K18*I49)+K27 -> -1.6757432 | J66: =VLOOKUP($D$7,High_Raw!$D:$CD,75,FALSE)*Standardisation_Parameters!$F$2+Standardisation_Parameters!$E$2 -> 16.660582 | K66: =VLOOKUP($D$7,High_Raw!$D:$CD,75,FALSE) -> -1.6757604
C67: Qualititative Score | D67: =((K19*I53+K20*I57+K21*I58+K22*I62)+K28)*Standardisation_Parameters!$F$2+Standardisation_Parameters!$E$2 -> 25.013749 | E67: =SUM(E55,E64,E60) -> 0.5 | F67: =VLOOKUP(D67,$O$3:$P$8,2,TRUE) -> Low Risk | I67: =(K19*I53+K20*I57+K21*I58+K22*I62)+K28 -> -1.1760212 | J67: =VLOOKUP($D$7,High_Raw!$D:$CD,76,FALSE)*Standardisation_Parameters!$F$2+Standardisation_Parameters!$E$2 -> 25.013749 | K67: =VLOOKUP($D$7,High_Raw!$D:$CD,76,FALSE) -> -1.1760212
E68: Country Rating (CR) | F68: Risk
C69: Overall Country Score without Restriction | D69: =((I66*K25+I67*K26)+K29)*Standardisation_Parameters!$F$2+Standardisation_Parameters!$E$2 -> 19.413727 | E69: =ROUND(D69/4,0) -> 5 | F69: =VLOOKUP(D69,$O$3:$P$8,2,TRUE) -> Very Low Risk | I69: =(I66*K25+I67*K26)+K29 -> -1.5110499 | J69: =VLOOKUP($D$7,High_Raw!$D:$CD,77,FALSE)*Standardisation_Parameters!$F$2+Standardisation_Parameters!$E$2 -> 21.241824 | K69: =VLOOKUP($D$7,High_Raw!$D:$CD,77,FALSE) -> -1.4016816
C70: Overall Country Score with Restriction | D70: =((I66*K25+I67*K26)+K30)*Standardisation_Parameters!$F$2+Standardisation_Parameters!$E$2 -> 19.437128 | E70: =ROUND(D69/4,0) -> 5 | F70: =VLOOKUP(D70,$O$3:$P$8,2,TRUE) -> Very Low Risk | I70: =(I66*K26+I67*K27)+K30 -> -1.7851829 | J70: =VLOOKUP($D$7,High_Raw!$D:$CD,78,FALSE)*Standardisation_Parameters!$F$2+Standardisation_Parameters!$E$2 -> 19.436937 | K70: =VLOOKUP($D$7,High_Raw!$D:$CD,78,FALSE) -> -1.5096613
C71: External EIU Equivalent | D71: =IFERROR(VLOOKUP($D$7,High_Raw!$D:$CD,79,FALSE)*Standardisation_Parameters!$F$2+Standardisation_Parameters!$E$2,"No Dependent Variable") -> 23.333556 | E71: =IFERROR(ROUND(D71/4,0),"") -> 6 | F71: =IFERROR(VLOOKUP(D71,$O$3:$P$8,2,TRUE),"") -> Low Risk
C72: Risk Assesment | D72: =VLOOKUP(D70,$O$3:$P$8,2,TRUE) -> Very Low Risk
B93: Would you like to view the Overall Rating or Adjust the Rating?
B95: Overall | E95: Adjust
A98: ADJUSTMENT FACTORS
A100: Category Level Adjsutment Factors | B100: Economic | D100: Raw | E100: Risk Bucket | F100: Raw Fitted - Before | G100: Raw Fitted - After
C101: Inflation 5 year average | D101: =D35 -> 2.2206 | E101: =IF($D101="",VLOOKUP(9999999999,Buckets!$E$9:$M$15,9,TRUE),VLOOKUP($D101,Buckets!$E$9:$M$15,9,TRUE)) -> 1
C102: Inflation 5 year volatility | D102: =VLOOKUP($D$7,High_Raw!$D:$CD,34,FALSE) -> -0.1206 | E102: =VLOOKUP($D102,Buckets!$E$120:$N$125,9,TRUE) -> 4
C103: Peer average Inflation 5 year volatility | D103: =VLOOKUP(E102,Buckets!$M$120:$O$125,3,FALSE) -> 0.2554411
E104: =IF(D102<0,VLOOKUP(IF(D102<D103,IF(E101<6,E101+1,E101),E101),Buckets!$Z$4:$AB$9,1,FALSE),VLOOKUP(IF(D102>D103,IF(E101<6,E101+1,E101),E101),Buckets!$Z$4:$AB$9,1,FALSE)) -> 2 | F104: =VLOOKUP(E101,Buckets!$J$9:$M$15,3,FALSE) -> 1.2928828 | G104: =IF(E104>E101,VLOOKUP(E104,Buckets!$J$9:$M$15,3,FALSE),VLOOKUP(E101,Buckets!$J$9:$M$15,3,FALSE)) -> 3.5986415 | I104: =IF($E104="",VLOOKUP(9999999999,Buckets!$J$9:$M$15,2,TRUE),VLOOKUP($E104,Buckets!$J$9:$M$15,2,TRUE)) -> -0.5387
C105: Macroeconomic | D105: =D39 -> 2 | E105: =IF($D105="",VLOOKUP(9999999999,Buckets!$E$73:$M$78,9,TRUE),VLOOKUP($D105,Buckets!$E$73:$M$78,9,TRUE)) -> 2
C106: Export Concentration by Sector | D106: =IF(VLOOKUP($D$7,High_Raw!$D:$BX,7,FALSE)="","",VLOOKUP($D$7,High_Raw!$D:$BX,7,FALSE)) -> 34.938 | E106: =IF($D106="",VLOOKUP(9999999999,Buckets!$E$147:$M$152,9,TRUE),VLOOKUP($D106,Buckets!$E$147:$M$152,9,TRUE)) -> 3 | F106: =IF(D106="",1,PERCENTRANK(High_Raw!$J:$J,D106)) -> 0.52 | G106: =IF(F106>0.95,IF(E105<6,E105+1,6),E105) -> 2
C107: Export Concentration by Market | D107: =IF(VLOOKUP($D$7,High_Raw!$D:$BX,8,FALSE)="","",VLOOKUP($D$7,High_Raw!$D:$BX,8,FALSE)) -> 19.417 | E107: =IF($D107="",VLOOKUP(9999999999,Buckets!$E$156:$M$161,9,TRUE),VLOOKUP($D107,Buckets!$E$16:$M$156,9,TRUE)) -> 3 | F107: =IF(D107="",1,PERCENTRANK(High_Raw!$K:$K,D107)) -> 0.462 | G107: =IF(F107>0.95,IF(E105<6,E105+1,6),E105) -> 2
E108: =IF(E105<G106,E105+1,IF(E105<G107,E105+1,E105)) -> 2 | F108: =VLOOKUP(E105,Buckets!$J$73:$M$78,3,FALSE) -> 2.1614379 | G108: =IF(E108>E105,VLOOKUP(E108,Buckets!$J$73:$M$78,3,FALSE),VLOOKUP(E105,Buckets!$J$73:$M$78,3,FALSE)) -> 2.1614379 | I108: =IF($E108="",VLOOKUP(9999999999,Buckets!$J$73:$M$78,2,TRUE),VLOOKUP($E108,Buckets!$J$73:$M$78,2,TRUE)) -> -1.1529
G109: Notching | H109: Comment
C110: Is the overall inflation greater than 10.5? | F110: No | G110: =VLOOKUP(F110,Buckets!$AI$27:$AJ$28,2,FALSE) -> 0
C111: GDP per capita provides an incomplete picture of development in the country, given the high degree of income inequality (as measured by the GINI coefficient) | F111: Not Applicable | G111: =VLOOKUP(F111,Buckets!$AI$2:$AJ$3,2,FALSE) -> 0
C112: Exposure to an adverse export market (may either be one country or a grouping of countries) poses a significant concentration risk | F112: No concentration risk | G112: =VLOOKUP(F112,Buckets!$AI$7:$AJ$8,2,FALSE) -> 0
C113: Existence of a managed exchange rate regime or member of Common Monetary Area (CMA) | F113: No impact | G113: =VLOOKUP(F113,Buckets!$AI$12:$AJ$14,2,FALSE) -> 0 | I113: =SUM(G110:G113) -> 0
C114: Fitted Before Adjustment | D114: Fitted After AutoAdjusted Factors | F114: Fitted After Notching
C115: =(SUMPRODUCT(K10:K14,I35:I39)+$K$23*E41)*Standardisation_Parameters!$F$2+Standardisation_Parameters!$E$2 -> 17.444962 | D115: =((K10*I104+K11*I36+K12*I37+K13*I38+K14*I108)+$K$23*E41)*Standardisation_Parameters!$F$2+Standardisation_Parameters!$E$2 -> 20.126601 | F115: =-SUM(G110:G113)*5+D115 -> 20.126601 | I115: =(F115-Standardisation_Parameters!$E$2)/Standardisation_Parameters!$F$2 -> -1.4684013
B117: Currency | D117: Raw | E117: Risk Bucket | F117: Raw Fitted - Before | G117: Raw Fitted - After
C118: Debt Trend | D118: =E54 -> 0 | E118: =VLOOKUP($D118,Buckets!$E$37:$O$41,9,TRUE) -> 3
C119: Peer average Debt Trend Worst Bucket | D119: =VLOOKUP(6,Buckets!$AC$117:$AE$122,3,FALSE) -> 40.620428
E120: =IF(E118<6,IF(D118>(1.5*D119),6,E118),IF(D118>(1.5*D119),"1 Notch",E118)) -> 3 | F120: =VLOOKUP(E118,Buckets!$J$37:$O$42,2,FALSE)*Standardisation_Parameters!$F$13+Standardisation_Parameters!$E$13 -> -15.191739 | G120: =IF(E120="1 Notch","1 Notch",VLOOKUP(E120,Buckets!$J$37:$O$42,3,FALSE)) -> -15.191739 | I120: =IF(OR($E120="1 Notch", $E120=""),VLOOKUP(9999999999,Buckets!$J$37:$O$42,2,TRUE),VLOOKUP($E120,Buckets!$J$37:$O$42,2,TRUE)) -> -0.4274
G121: Notching | H121: Comment
C122: In addition to the nominal level of external debt, debt serviceability improves/impedes the rating. | F122: No impact | G122: =VLOOKUP(F122,Buckets!$AI$22:$AJ$24,2,FALSE) -> 0 | I122: =IF(G120="1 Notch",G122+1,G122) -> 0
C123: Fitted Before Adjustment | D123: Fitted After AutoAdjusted Factors | F123: Fitted After Notching
C124: =(SUMPRODUCT(K15:K17,I43:I45)+$K$23*E47)*Standardisation_Parameters!$F$2+Standardisation_Parameters!$E$2 -> 36.874984 | D124: =IF(G120="1 Notch",C124+5,((K15*I43+K16*I120+K17*I45)+$K$23*$E$47)*Standardisation_Parameters!$F$2+Standardisation_Parameters!$E$2) -> 36.874984 | F124: =-G122*5+D124 -> 36.874984
B126: Political | G126: Notching | H126: Comment
C127: There is a risk of war within the country territory, but the risk is not expected to materialise within the next 3 years | F127: Not Applicable | G127: =VLOOKUP(F127,Buckets!$AI$17:$AJ$19,2,FALSE) -> 0 | I127: =G127 -> 0
D128: Fitted Before Adjustment | F128: Fitted After Notching
D129: =((I53*K19)+$K$24*E55)*Standardisation_Parameters!$F$2+Standardisation_Parameters!$E$2 -> 41.458766 | F129: =-G127*5+D129 -> 41.458766
B131: Overall | C131: Quantitative Score | D131: =(((K10*I104+K11*I36+K12*I37+K13*I38+K14*I108+K15*I43+K16*I120+K17*I45+K18*I49)+K27)*Standardisation_Parameters!$F$2+Standardisation_Parameters!$E$2)+5*(I113+I122) -> 19.342509 | E131: =SUM($E$41,$E$47,$E$51) -> 0.5 | F131: =VLOOKUP($D131,$O$3:$P$8,2,TRUE) -> Very Low Risk | I131: =(D131-Standardisation_Parameters!$E$2)/Standardisation_Parameters!$F$2 -> -1.5153106
C132: Qualititative Score | D132: =(((K19*I53+K20*I57+K21*I58+K22*I62)+K28)*Standardisation_Parameters!$F$2+Standardisation_Parameters!$E$2)+5*I127 -> 25.013749 | E132: =SUM($E$55,$E$64,$E$60) -> 0.5 | F132: =VLOOKUP($D132,$O$3:$P$8,2,TRUE) -> Low Risk | I132: =(D132-Standardisation_Parameters!$E$2)/Standardisation_Parameters!$F$2 -> -1.1760212
E133: Country Rating (CR) | F133: Risk
C134: Overall Country Score without Restriction | D134: =((I131*K25+I132*K26)+K29)*Standardisation_Parameters!$F$2+Standardisation_Parameters!$E$2 -> 20.881843 | E134: =ROUND(D134/4,0) -> 5 | F134: =VLOOKUP(D134,$O$3:$P$8,2,TRUE) -> Low Risk
C135: Overall Country Score with Restriction | D135: =((I131*K26+I132*K27)+K30)*Standardisation_Parameters!$F$2+Standardisation_Parameters!$E$2 -> 16.27996 | E135: =ROUND(D135/4,0) -> 4 | F135: =VLOOKUP(D135,$O$3:$P$8,2,TRUE) -> Very Low Risk
C136: External EIU Equivalent | D136: =VLOOKUP($D$7,High_Raw!$D:$CD,79,FALSE)*Standardisation_Parameters!$F$2+Standardisation_Parameters!$E$2 -> 23.333556 | E136: =ROUND(D136/4,0) -> 6 | F136: =VLOOKUP(D136,$O$3:$P$8,2,TRUE) -> Low Risk
C137: Risk Assesment | D137: =VLOOKUP(D135,$O$3:$P$8,2,TRUE) -> Very Low Risk
C163: OVERALL RATING
C166: Quantitative Score | D166: =D131 -> 19.342509 | E166: =E131 -> 0.5 | F166: =VLOOKUP($D166,$O$3:$P$8,2,TRUE) -> Very Low Risk
C167: Qualititative Score | D167: =D132 -> 25.013749 | E167: =E132 -> 0.5 | F167: =VLOOKUP($D167,$O$3:$P$8,2,TRUE) -> Low Risk
...

Sheet Low Segment
I1: Low mapping
I2: Economic | J2: Currency | K2: Political | L2: Bus Risk | M2: Risk | N2: Overall
I3: 0 | J3: 0 | K3: 0 | L3: 0 | M3: 0 | N3: 0 | O3: Very Low Risk
B4: LOW HUMAN DEVELOPMENT | I4: 20 | J4: 20 | K4: 20 | L4: 20 | M4: 20 | N4: 20 | O4: Low Risk
I5: 40 | J5: 40 | K5: 40 | L5: 40 | M5: 40 | N5: 40 | O5: Moderate Risk
B6: Country Name | D6: SOUTH AFRICA | I6: 60 | J6: 60 | K6: 60 | L6: 60 | M6: 60 | N6: 60 | O6: High Risk
B7: ISO Code | D7: =VLOOKUP(D6,'Country List'!$A:$D,2,FALSE) -> ZAF | I7: 80 | J7: 80 | K7: 80 | L7: 80 | M7: 80 | N7: 80 | O7: Very High Risk
B8: HDI Segmentation | D8: =VLOOKUP(D7,'Country List'!$B:$D,2,FALSE) -> MEDIUM HUMAN DEVELOPMENT | I8: 100 | J8: 100 | K8: 100 | L8: 100 | M8: 100 | N8: 100 | O8: Default
B9: Region | D9: =VLOOKUP(D7,'Country List'!$B:$D,3,FALSE) -> AFRICA | I9: Model Drivers
I10: Inflation 5 year average | J10: dcpi_5_adj | K10: 0.43996 | L10: 0.16081591 | M10: =0.5*L10 -> 0.080407953 | N10: =SUM(M10:M12) -> 0.26381405 | O10: =SUM(N10:N15) -> 0.5
I11: Nominal Interest Rate | J11: nom_rir | K11: 0.30601 | L11: 0.082499404 | M11: =0.5*L11 -> 0.041249702
I12: Macroeconomic | J12: macro_var | K12: 0.63284 | L12: 0.28431279 | M12: =0.5*L12 -> 0.1421564
I13: Access to Finance | J13: atf | K13: 0.55294 | L13: 0.254189 | M13: =0.5*L13 -> 0.1270945 | N13: =SUM(M13:M15) -> 0.23618595
I14: Debt Trend | J14: DT | K14: 0.60889 | L14: 0.088012387 | M14: =0.5*L14 -> 0.044006193
I15: Debt Service Ratio 5 year average | J15: DSR_5year | K15: 1.11395 | L15: 0.13017051 | M15: =0.5*L15 -> 0.065085254
I16: Political Risk Environment | J16: pr | K16: 0.33987 | L16: 0.18188992 | M16: =0.5*L16 -> 0.090944962 | N16: =M16 -> 0.090944962 | O16: =SUM(N16:N19) -> 0.5
I17: Rule of Law | J17: rol | K17: 0.65754 | L17: 0.51294019 | M17: =0.5*L17 -> 0.25647009 | N17: =SUM(M17:M18) -> 0.34111244
I18: Doing Business | J18: db___rol_segmentation | K18: 0.33801 | L18: 0.16928469 | M18: =0.5*L18 -> 0.084642344
I19: Security Risk | J19: sr | K19: 0.23124 | L19: 0.1358852 | M19: =0.5*L19 -> 0.067942601 | N19: =M19 -> 0.067942601
I20: Quant | J20: yhat_quant | K20: 0.30517 | L20: 0.22605113 | M20: 0.22605113 | N20: 0.22605113 | O20: =SUM(N20:N21) -> 1
I21: Qual | J21: yhat_qualitative | K21: 0.83736 | L21: 0.77394887 | M21: 0.77394887 | N21: 0.77394887
I22: Quant | J22: yhat_quant with Restriction | K22: 0.675 | L22: 0.49999696 | M22: 0.49999696 | N22: =M22 -> 0.49999696 | O22: =SUM(N22:N23) -> 1
I23: Qual | J23: yhat_qualitative with Restriction | K23: 0.54096 | L23: 0.50000304 | M23: 0.50000304 | N23: =M23 -> 0.50000304
B24: Base Model | J24: Intercept Quant | K24: -1.9591
C25: Factors | D25: Raw Value | E25: Weight | F25: Raw Fitted Value | G25: Bucket # | I25: Std Fitted Value | J25: Intercept Qual | K25: -0.41692
B26: Economic | C26: =I10 -> Inflation 5 year average | D26: =IF(VLOOKUP($D$7,Low_Seg2!$C:$BE,2,FALSE)="","",VLOOKUP($D$7,Low_Seg2!$C:$BE,2,FALSE)) -> 6.5196 | E26: =M10 -> 0.080407953 | F26: =IF($D26="",VLOOKUP(9999999999,Buckets!$U$3:$AC$9,8,TRUE),VLOOKUP($D26,Buckets!$U$3:$AC$9,8,TRUE)) -> 10.600275 | G26: =IF($D26="",VLOOKUP(9999999999,Buckets!$U$3:$AC$9,9,TRUE),VLOOKUP($D26,Buckets!$U$3:$AC$9,9,TRUE)) -> 3 | I26: =IF($D26="",VLOOKUP(9999999999,Buckets!$U$3:$AC$9,7,TRUE),VLOOKUP($D26,Buckets!$U$3:$AC$9,7,TRUE)) -> 0.781 | J26: Intercept Quant/Qual (Unrestricted) | K26: -0.1046
C27: =I11 -> Nominal Interest Rate | D27: =IF(VLOOKUP($D$7,Low_Seg2!$C:$BE,4,FALSE)="","",VLOOKUP($D$7,Low_Seg2!$C:$BE,4,FALSE)) -> 9 | E27: =M11 -> 0.041249702 | F27: =IF($D27="",VLOOKUP(9999999999,Buckets!$U$30:$AC$35,8,TRUE),VLOOKUP($D27,Buckets!$U$30:$AC$35,8,TRUE)) -> 15.349915 | G27: =IF($D27="",VLOOKUP(9999999999,Buckets!$U$30:$AC$35,9,TRUE),VLOOKUP($D27,Buckets!$U$30:$AC$35,9,TRUE)) -> 1 | I27: =IF($D27="",VLOOKUP(9999999999,Buckets!$U$30:$AC$35,7,TRUE),VLOOKUP($D27,Buckets!$U$30:$AC$35,7,TRUE)) -> 0.4808 | J27: Intercept Final (Restricted) | K27: -0.15849
C28: =I12 -> Macroeconomic | D28: =IF(VLOOKUP($D$7,Low_Seg2!$C:$BE,3,FALSE)="","",VLOOKUP($D$7,Low_Seg2!$C:$BE,3,FALSE)) -> 4 | E28: =M12 -> 0.1421564 | F28: =IF($D28="",VLOOKUP(9999999999,Buckets!$U$13:$AC$18,8,TRUE),VLOOKUP($D28,Buckets!$U$13:$AC$18,8,TRUE)) -> 5.3660546 | G28: =IF($D28="",VLOOKUP(9999999999,Buckets!$U$13:$AC$18,9,TRUE),VLOOKUP($D28,Buckets!$U$13:$AC$18,9,TRUE)) -> 2 | I28: =IF($D28="",VLOOKUP(9999999999,Buckets!$U$13:$AC$18,7,TRUE),VLOOKUP($D28,Buckets!$U$13:$AC$18,7,TRUE)) -> 0.4707
C30: Category Assessment | D30: =(SUMPRODUCT(K10:K12,I26:I28)+$K$20*E30)*Standardisation_Parameters!$F$2+Standardisation_Parameters!$E$2 -> 59.198455 | E30: =SUM(E26:E28) -> 0.26381405 | F30: =VLOOKUP($D30,$I$3:$O$8,7,TRUE) -> Moderate Risk
B32: Currency | C32: =I13 -> Access to Finance | D32: =IF(VLOOKUP($D$7,Low_Seg2!$C:$BE,5,FALSE)="","",VLOOKUP($D$7,Low_Seg2!$C:$BE,5,FALSE)) -> 1 | E32: =M13 -> 0.1270945 | F32: =IF($D32="",VLOOKUP(9999999999,Buckets!$U$22:$AC$26,8,TRUE),VLOOKUP($D32,Buckets!$U$22:$AC$26,8,TRUE)) -> 2.7667357 | G32: =IF($D32="",VLOOKUP(9999999999,Buckets!$U$22:$AC$26,9,TRUE),VLOOKUP($D32,Buckets!$U$22:$AC$26,9,TRUE)) -> 1 | I32: =IF($D32="",VLOOKUP(9999999999,Buckets!$U$22:$AC$26,7,TRUE),VLOOKUP($D32,Buckets!$U$22:$AC$26,7,TRUE)) -> 0.332
C33: =I14 -> Debt Trend | D33: =IF(VLOOKUP($D$7,Low_Seg2!$C:$BE,11,FALSE)="","",VLOOKUP($D$7,Low_Seg2!$C:$BE,11,FALSE)) -> -21.24897 | E33: =M14 -> 0.044006193 | F33: =IF($D33="",VLOOKUP(9999999999,Buckets!$U$117:$AC$122,8,TRUE),VLOOKUP($D33,Buckets!$U$117:$AC$122,8,TRUE)) -> 28.939827 | G33: =IF($D33="",VLOOKUP(9999999999,Buckets!$U$117:$AC$122,9,TRUE),VLOOKUP($D33,Buckets!$U$117:$AC$122,9,TRUE)) -> 3 | I33: =IF($D33="",VLOOKUP(9999999999,Buckets!$U$117:$AC$122,7,TRUE),VLOOKUP($D33,Buckets!$U$117:$AC$122,7,TRUE)) -> 0.7245
C34: =I15 -> Debt Service Ratio 5 year average | D34: =IF(VLOOKUP($D$7,Low_Seg2!$C:$BE,6,FALSE)="","",VLOOKUP($D$7,Low_Seg2!$C:$BE,6,FALSE)) -> 5.1372 | E34: =M15 -> 0.065085254 | F34: =IF($D34="",VLOOKUP(9999999999,Buckets!$U$39:$AC$44,8,TRUE),VLOOKUP($D34,Buckets!$U$39:$AC$44,8,TRUE)) -> 17.520085 | G34: =IF($D34="",VLOOKUP(9999999999,Buckets!$U$39:$AC$44,9,TRUE),VLOOKUP($D34,Buckets!$U$39:$AC$44,9,TRUE)) -> 3 | I34: =IF($D34="",VLOOKUP(9999999999,Buckets!$U$39:$AC$44,7,TRUE),VLOOKUP($D34,Buckets!$U$39:$AC$44,7,TRUE)) -> 0.6933
C36: Category Assessment | D36: =(SUMPRODUCT(K13:K15,I32:I34)+$K$20*$E$36)*Standardisation_Parameters!$F$2+Standardisation_Parameters!$E$2 -> 69.227 | E36: =SUM(E32:E34) -> 0.23618595 | F36: =VLOOKUP($D36,$J$3:$O$8,6,TRUE) -> High Risk
B38: Political | C38: =I16 -> Political Risk Environment | D38: =IF(VLOOKUP($D$7,Low_Seg2!$C:$BE,7,FALSE)="","",VLOOKUP($D$7,Low_Seg2!$C:$BE,7,FALSE)) -> 3 | E38: =M16 -> 0.090944962 | F38: =IF($D38="",VLOOKUP(9999999999,Buckets!$U$50:$AC$54,8,TRUE),VLOOKUP($D38,Buckets!$U$50:$AC$54,8,TRUE)) -> 4.4199 | G38: =IF($D38="",VLOOKUP(9999999999,Buckets!$U$50:$AC$54,9,TRUE),VLOOKUP($D38,Buckets!$U$50:$AC$54,9,TRUE)) -> 1 | I38: =IF($D38="",VLOOKUP(9999999999,Buckets!$U$50:$AC$54,7,TRUE),VLOOKUP($D38,Buckets!$U$50:$AC$54,7,TRUE)) -> 0.296
C40: Category Assessment | D40: =((I38*K16)+$K$21*$E$40)*Standardisation_Parameters!$F$2+Standardisation_Parameters!$E$2 -> 47.625472 | E40: =SUM(E38) -> 0.090944962 | F40: =VLOOKUP($D40,$K$3:$O$8,5,TRUE) -> Moderate Risk
B42: Business Risk | C42: =I17 -> Rule of Law | D42: =IF(VLOOKUP($D$7,Low_Seg2!$C:$BE,8,FALSE)="","",VLOOKUP($D$7,Low_Seg2!$C:$BE,8,FALSE)) -> 0.10025151 | E42: =M17 -> 0.25647009 | F42: =IF($D42="",VLOOKUP(9999999999,Buckets!$U$58:$AC$63,8,TRUE),VLOOKUP($D42,Buckets!$U$58:$AC$63,8,TRUE)) -> 0.14792011 | G42: =IF($D42="",VLOOKUP(9999999999,Buckets!$U$58:$AC$63,9,TRUE),VLOOKUP($D42,Buckets!$U$58:$AC$63,9,TRUE)) -> 6 | I42: =IF($D42="",VLOOKUP(9999999999,Buckets!$U$58:$AC$63,7,TRUE),VLOOKUP($D42,Buckets!$U$58:$AC$63,7,TRUE)) -> 0.1036
C43: =I18 -> Doing Business | D43: =IF(VLOOKUP($D$7,Low_Seg2!$C:$BE,9,FALSE)="","",VLOOKUP($D$7,Low_Seg2!$C:$BE,9,FALSE)) -> 19.672131 | E43: =M18 -> 0.084642344 | F43: =IF($D43="",IF($D42<0,VLOOKUP(9999999999,Buckets!$S$76:$AC$78,10,TRUE),VLOOKUP(9999999999,Buckets!$S$84:$AC$86,10,TRUE)),IF($D42<0,VLOOKUP((($D43-Standardisation_Parameters!$E$15)/Standardisation_Parameters!$F$15),Buckets!$S$76:$AC$78,10,TRUE),VLOOKUP((($D43-Standardisation_Parameters!$E$15)/Standardisation_Parameters!$F$15),Buckets!$S$84:$AC$86,10,TRUE))) -> 37.062615 | G43: =IF($D43="",IF($D42<0,VLOOKUP(9999999999,Buckets!$S$76:$AC$78,11,TRUE),VLOOKUP(9999999999,Buckets!$S$84:$AC$86,11,TRUE)),IF($D42<0,VLOOKUP((($D43-Standardisation_Parameters!$E$15)/Standardisation_Parameters!$F$15),Buckets!$S$76:$AC$78,11,TRUE),VLOOKUP((($D43-Standardisation_Parameters!$E$15)/Standardisation_Parameters!$F$15),Buckets!$S$84:$AC$86,11,TRUE))) -> 1 | I43: =IF($D43="",IF($D42<0,VLOOKUP(9999999999,Buckets!$S$76:$AC$78,9,TRUE),VLOOKUP(9999999999,Buckets!$S$84:$AC$86,9,TRUE)),IF($D42<0,VLOOKUP((($D43-Standardisation_Parameters!$E$15)/Standardisation_Parameters!$F$15),Buckets!$S$76:$AC$78,9,TRUE),VLOOKUP((($D43-Standardisation_Parameters!$E$15)/Standardisation_Parameters!$F$15),Buckets!$S$84:$AC$86,9,TRUE))) -> -0.2519
C45: Category Assessment | D45: =(SUMPRODUCT(K17:K18,I42:I43)+$K$21*$E$45)*Standardisation_Parameters!$F$2+Standardisation_Parameters!$E$2 -> 49.160835 | E45: =SUM(E41:E43) -> 0.34111244 | F45: =VLOOKUP($D45,$L$3:$O$8,4,TRUE) -> Moderate Risk
B47: Risk | C47: =I19 -> Security Risk | D47: =IF(VLOOKUP($D$7,Low_Seg2!$C:$BE,10,FALSE)="","",VLOOKUP($D$7,Low_Seg2!$C:$BE,10,FALSE)) -> 3.25 | E47: =M19 -> 0.067942601 | F47: =IF($D47="",VLOOKUP(9999999999,Buckets!$U$67:$AC$72,8,TRUE),VLOOKUP($D47,Buckets!$U$67:$AC$72,8,TRUE)) -> 3.4408471 | G47: =IF($D47="",VLOOKUP(9999999999,Buckets!$U$67:$AC$72,9,TRUE),VLOOKUP($D47,Buckets!$U$67:$AC$72,9,TRUE)) -> 4 | I47: =IF($D47="",VLOOKUP(9999999999,Buckets!$U$67:$AC$72,7,TRUE),VLOOKUP($D47,Buckets!$U$67:$AC$72,7,TRUE)) -> 0.8224
C49: Category Assessment | D49: =((I47*K19)+$K$21*$E$49)*Standardisation_Parameters!$F$2+Standardisation_Parameters!$E$2 -> 48.80069 | E49: =SUM(E47:E47) -> 0.067942601 | F49: =VLOOKUP($D49,$M$3:$O$8,3,TRUE) -> Moderate Risk
J50: Lookuip Raw | K50: Lookup STD
B51: Overall | C51: Quantitative Score | D51: =((K10*I26+K11*I27+K12*I28+K13*I32+K14*I33+K15*I34)+K24)*Standardisation_Parameters!$F$2+Standardisation_Parameters!$E$2 -> 48.457537 | E51: =SUM($E$36,$E$30) -> 0.5 | F51: =VLOOKUP($D51,$N$3:$O$8,2,TRUE) -> Moderate Risk | I51: =(K10*I26+K11*I27+K12*I28+K13*I32+K14*I33+K15*I34)+K24 -> 0.22653458 | J51: =VLOOKUP($D$7,Low_Raw!$D:$CD,75,FALSE)*Standardisation_Parameters!$F$2+Standardisation_Parameters!$E$2 -> 48.457393 | K51: =VLOOKUP($D$7,Low_Raw!$D:$CD,75,FALSE) -> 0.22652597
C52: Qualititative Score | D52: =((K16*I38+K17*I42+K18*I43+K19*I47)+K25)*Standardisation_Parameters!$F$2+Standardisation_Parameters!$E$2 -> 42.277902 | E52: =SUM($E$40,$E$49,$E$45) -> 0.5 | F52: =VLOOKUP($D52,$N$3:$O$8,2,TRUE) -> Moderate Risk | I52: =(K16*I38+K17*I42+K18*I43+K19*I47)+K25 -> -0.14317028 | J52: =VLOOKUP($D$7,Low_Raw!$D:$CD,76,FALSE)*Standardisation_Parameters!$F$2+Standardisation_Parameters!$E$2 -> 42.277949 | K52: =VLOOKUP($D$7,Low_Raw!$D:$CD,76,FALSE) -> -0.14316747
E53: Country Rating (CR) | F53: Risk
C54: Overall Country Score without Restriction | D54: =(I51*K20+I52*K21+K26)*Standardisation_Parameters!$F$2+Standardisation_Parameters!$E$2 -> 42.074258 | E54: =ROUND(D54/4,0) -> 11 | F54: =VLOOKUP(D54,$N$3:$O$8,2,TRUE) -> Moderate Risk | I54: =I51*K20+I52*K21+K26 -> -0.15535351 | J54: =VLOOKUP($D$7,Low_Raw!$D:$CD,77,FALSE)*Standardisation_Parameters!$F$2+Standardisation_Parameters!$E$2 -> 42.074345 | K54: =VLOOKUP($D$7,Low_Raw!$D:$CD,77,FALSE) -> -0.15534834
C55: Overall Country Score with Restriction | D55: =(I51*K22+I52*K23+K27)*Standardisation_Parameters!$F$2+Standardisation_Parameters!$E$2 -> 43.283174 | E55: =ROUND(D55/4,0) -> 11 | F55: =VLOOKUP(D55,$N$3:$O$8,2,TRUE) -> Moderate Risk | I55: =I51*K22+I52*K23+K27 -> -0.083028555 | J55: =VLOOKUP($D$7,Low_Raw!$D:$CD,78,FALSE)*Standardisation_Parameters!$F$2+Standardisation_Parameters!$E$2 -> 43.283108 | K55: =VLOOKUP($D$7,Low_Raw!$D:$CD,78,FALSE) -> -0.083032511
C56: External EIU Equivalent | D56: =IFERROR(VLOOKUP($D$7,Low_Raw!$D:$CD,79,FALSE)*Standardisation_Parameters!$F$2+Standardisation_Parameters!$E$2,"No Dependent Variable") -> 45.555777 | E56: =IFERROR(ROUND(D56/4,0),"") -> 11 | F56: =IFERROR(VLOOKUP(D56,$N$3:$O$8,2,TRUE),"") -> Moderate Risk
C57: Risk Assesment | D57: =VLOOKUP(D55,$N$3:$O$8,2,TRUE) -> Moderate Risk
C72: Would you like to view the Overall Rating or Adjust the Rating?
C74: Overall | E74: Adjust
A77: ADJUSTMENT FACTORS
A79: Category Level Adjsutment Factors | B79: Economic | D79: Raw | E79: Risk Bucket | F79: Raw Fitted - Before | G79: Raw Fitted - After
C80: Inflation 5 year average | D80: =D26 -> 6.5196 | E80: =IF($D80="",VLOOKUP(9999999999,Buckets!$U$3:$AC$9,9,TRUE),VLOOKUP($D80,Buckets!$U$3:$AC$9,9,TRUE)) -> 3
C81: Inflation 5 year volatility | D81: =VLOOKUP($D$7,Low_Raw!$D:$BW,34,FALSE) -> -1.2196 | E81: =VLOOKUP($D81,Buckets!$U$90:$AC$95,9,TRUE) -> 3
C82: Peer average Inflation 5 year volatility | D82: =VLOOKUP(E81,Buckets!$AC$91:$AE$96,3,FALSE) -> -1.0891228
E83: =IF(D81<0,VLOOKUP(IF(D81<D82,IF(E80<6,E80+1,E80),E80),Buckets!$Z$4:$AB$9,1,FALSE),VLOOKUP(IF(D81>D82,IF(E80<6,E80+1,E80),E80),Buckets!$Z$4:$AB$9,1,FALSE)) -> 4 | F83: =VLOOKUP(E80,Buckets!$Z$4:$AB$9,3,FALSE) -> 10.600275 | G83: =IF(E83>E80,VLOOKUP(E83,Buckets!$Z$4:$AB$9,3,FALSE),VLOOKUP(E80,Buckets!$Z$4:$AB$9,3,FALSE)) -> 11.6428 | I83: =IF($E83="",VLOOKUP(9999999999,Buckets!$Z$3:$AC$9,2,TRUE),VLOOKUP($E83,Buckets!$Z$3:$AC$9,2,TRUE)) -> 0.9775
C84: Macroeconomic | D84: =D28 -> 4 | E84: =IF($D84="",VLOOKUP(9999999999,Buckets!$U$13:$AC$18,9,TRUE),VLOOKUP($D84,Buckets!$U$13:$AC$18,9,TRUE)) -> 2
C85: Export Concentration by Sector | D85: =IF(VLOOKUP($D$7,Low_Raw!$D:$BW,7,FALSE)="","",VLOOKUP($D$7,Low_Raw!$D:$BW,7,FALSE)) -> 11.445 | E85: =IF($D85="",VLOOKUP(9999999999,Buckets!$U$99:$AF$105,9,TRUE),VLOOKUP($D85,Buckets!$U$99:$AF$105,9,TRUE)) -> 1 | F85: =IF(D85="",1,PERCENTRANK(Low_Raw!$J:$J,D85)) -> 0.081 | G85: =IF(F85>0.95,IF(E84<6,E84+1,6),E84) -> 2
C86: Export Concentration by Market | D86: =IF(VLOOKUP($D$7,Low_Raw!$D:$BW,8,FALSE)="","",VLOOKUP($D$7,Low_Raw!$D:$BW,8,FALSE)) -> 12.698 | E86: =IF($D86="",VLOOKUP(9999999999,Buckets!$U$108:$AF$113,9,TRUE),VLOOKUP($D86,Buckets!$U$108:$AF$113,9,TRUE)) -> 2 | F86: =IF(D86="",1,PERCENTRANK(Low_Raw!$K:$K,D86)) -> 0.176 | G86: =IF(F86>0.95,IF(E84<6,E84+1,6),E84) -> 2
E87: =IF(E84<G85,E84+1,IF(E84<G86,E84+1,E84)) -> 2 | F87: =VLOOKUP(E84,Buckets!$Z$13:$AB$18,3,FALSE) -> 5.3660546 | G87: =IF(E87>E84,VLOOKUP(E87,Buckets!$Z$13:$AB$18,3,FALSE),VLOOKUP(E84,Buckets!$Z$13:$AB$18,3,FALSE)) -> 5.3660546 | I87: =IF($E87="",VLOOKUP(9999999999,Buckets!$Z$13:$AC$18,2,TRUE),VLOOKUP($E87,Buckets!$Z$13:$AC$18,2,TRUE)) -> 0.4707
G88: Notching | H88: Comment
C89: Is the overall inflation greater than 10.5? | F89: Yes | G89: =VLOOKUP(F89,Buckets!$AI$27:$AJ$28,2,FALSE) -> -1
C90: GDP per capita provides an incomplete picture of development in the country, given the high degree of income inequality (as measured by the GINI coefficient) | F90: Applicable | G90: =VLOOKUP(F90,Buckets!$AI$2:$AJ$3,2,FALSE) -> -1
C91: Exposure to an adverse export market (may either be one country or a grouping of countries) poses a significant concentration risk | F91: Concentration to adverse export market | G91: =VLOOKUP(F91,Buckets!$AI$7:$AJ$8,2,FALSE) -> -1
C92: Existence of a managed exchange rate regime or member of Common Monetary Area (CMA) | F92: Unsustainable peg or encumbers monetary policy | G92: =VLOOKUP(F92,Buckets!$AI$12:$AJ$14,2,FALSE) -> -1 | I92: =SUM(G89:G92) -> -4
C93: Fitted Before Adjustment | D93: Fitted After AutoAdjusted Factors | F93: Fitted After Notching
C94: =(SUMPRODUCT(K10:K12,I26:I28)+$K$20*E30)*Standardisation_Parameters!$F$2+Standardisation_Parameters!$E$2 -> 59.198455 | D94: =((K10*I83+K11*I27+K12*I87)+$K$20*E30)*Standardisation_Parameters!$F$2+Standardisation_Parameters!$E$2 -> 60.643507 | F94: =-SUM(G89:G92)*5+D94 -> 80.643507 | I94: =(F94-Standardisation_Parameters!$E$2)/Standardisation_Parameters!$F$2 -> 2.152103
B96: Currency | D96: Raw | E96: Risk Bucket | F96: Raw Fitted - Before | G96: Raw Fitted - After
C97: Debt Trend | D97: =D33 -> -21.24897 | E97: =VLOOKUP($D97,Buckets!$U$117:$AC$122,9,TRUE) -> 3
C98: Peer average Debt Trend Worst Bucket | D98: =VLOOKUP(6,Buckets!$AC$117:$AE$122,3,FALSE) -> 40.620428
E99: =IF(E97<6,IF(D97>(1.5*D98),6,E97),IF(D97>(1.5*D98),"1 Notch",E97)) -> 3 | F99: =VLOOKUP(E97,Buckets!$Z$117:$AC$122,2,FALSE)*Standardisation_Parameters!$F$13+Standardisation_Parameters!$E$13 -> 28.939827 | G99: =IF(E99="1 Notch","1 Notch",VLOOKUP(E99,Buckets!$Z$117:$AC$122,3,FALSE)) -> 28.939827 | I99: =IF(OR($E99="1 Notch", $E99=""),VLOOKUP(9999999999,Buckets!$Z$117:$AC$122,2,TRUE),VLOOKUP($E99,Buckets!$Z$117:$AC$122,2,TRUE)) -> 0.7245
G100: Notching | H100: Comment
C101: In addition to the nominal level of external debt, debt serviceability improves/impedes the rating. | F101: High Debt Service | G101: =VLOOKUP(F101,Buckets!$AI$22:$AJ$24,2,FALSE) -> -1 | I101: =IF(G99="1 Notch",G101+1,G101) -> -1
C102: Fitted Before Adjustment | D102: Fitted After AutoAdjusted Factors | F102: Fitted After Notching
C103: =(SUMPRODUCT(K13:K15,I32:I34)+$K$20*$E$36)*Standardisation_Parameters!$F$2+Standardisation_Parameters!$E$2 -> 69.227 | D103: =IF(G99="1 Notch",C103+5,((K13*I32+K14*I99+K15*I34)+$K$20*$E$36)*Standardisation_Parameters!$F$2+Standardisation_Parameters!$E$2) -> 69.227 | F103: =-G101*5+D103 -> 74.227 | I103: =(F103-Standardisation_Parameters!$E$2)/Standardisation_Parameters!$F$2 -> 1.7682269
B105: Political | G105: Notching | H105: Comment
C106: There is a risk of war within the country territory, but the risk is not expected to materialise within the next 3 years | F106: Not Applicable | G106: =VLOOKUP(F106,Buckets!$AI$17:$AJ$19,2,FALSE) -> 0 | I106: =G106 -> 0
D107: Fitted Before Adjustment | F107: Fitted After Notching
D108: =((I38*K16)+$K$21*$E$40)*Standardisation_Parameters!$F$2+Standardisation_Parameters!$E$2 -> 47.625472 | F108: =-G106*5+D108 -> 47.625472 | I108: =(F108-Standardisation_Parameters!$E$2)/Standardisation_Parameters!$F$2 -> 0.17675519
B110: Overall | C110: Quantitative Score | D110: =(((K10*I83+K11*I27+K12*I87+K13*I32+K14*I99+K15*I34)+K24)*Standardisation_Parameters!$F$2+Standardisation_Parameters!$E$2)+5*(I92+I101) -> 24.902588 | E110: =SUM($E$36,$E$30) -> 0.5 | F110: =VLOOKUP($D110,$N$3:$O$8,2,TRUE) -> Low Risk | I110: =(D110-Standardisation_Parameters!$E$2)/Standardisation_Parameters!$F$2 -> -1.1826715
C111: Qualititative Score | D111: =(((K16*I38+K17*I42+K18*I43+K19*I47)+K25)*Standardisation_Parameters!$F$2+Standardisation_Parameters!$E$2)+5*I106 -> 42.277902 | E111: =SUM($E$40,$E$49,$E$45) -> 0.5 | F111: =VLOOKUP($D111,$N$3:$O$8,2,TRUE) -> Moderate Risk | I111: =(D111-Standardisation_Parameters!$E$2)/Standardisation_Parameters!$F$2 -> -0.14317028
E112: Country Rating (CR) | F112: Risk
C113: Overall Country Score without Restriction | D113: =(I110*K20+I111*K21+K26)*Standardisation_Parameters!$F$2+Standardisation_Parameters!$E$2 -> 34.885995 | E113: =ROUND(D113/4,0) -> 9 | F113: =VLOOKUP(D113,$N$3:$O$8,2,TRUE) -> Low Risk
C114: Overall Country Score with Restriction | D114: =(I110*K21+I111*K22+K27)*Standardisation_Parameters!$F$2+Standardisation_Parameters!$E$2 -> 23.853213 | E114: =ROUND(D114/4,0) -> 6 | F114: =VLOOKUP(D114,$N$3:$O$8,2,TRUE) -> Low Risk
C115: External EIU Equivalent | D115: =VLOOKUP($D$7,Low_Raw!$D:$CD,79,FALSE)*Standardisation_Parameters!$F$2+Standardisation_Parameters!$E$2 -> 45.555777 | E115: =ROUND(D115/4,0) -> 11 | F115: =VLOOKUP(D115,$N$3:$O$8,2,TRUE) -> Moderate Risk
C116: Risk Assesment | D116: =VLOOKUP(D114,$N$3:$O$8,2,TRUE) -> Low Risk
C141: OVERALL RATING
C143: Quantitative Score | D143: =D110 -> 24.902588 | E143: =E110 -> 0.5 | F143: =VLOOKUP($D143,$N$3:$O$8,2,TRUE) -> Low Risk
C144: Qualititative Score | D144: =D111 -> 42.277902 | E144: =E111 -> 0.5 | F144: =VLOOKUP($D144,$N$3:$O$8,2,TRUE) -> Moderate Risk
E145: Country Rating (CR) | F145: Risk
C146: Overall Country Score | D146: =D114 -> 23.853213 | E146: =ROUND(D146/4,0) -> 6 | F146: =VLOOKUP($D146,$N$3:$O$8,2,TRUE) -> Low Risk
C147: External EIU Equivalent | D147: =D115 -> 45.555777 | E147: =ROUND(D147/4,0) -> 11 | F147: =VLOOKUP($D147,$N$3:$O$8,2,TRUE) -> Moderate Risk
C149: Risk Assesment | D149: =VLOOKUP($D146,$N$3:$O$8,2,TRUE) -> Low Risk

Sheet No Data Segment
L1: Low mapping
L2: Economic | M2: Currency | N2: Political | O2: Bus Risk | P2: Risk | Q2: Overall
L3: 0 | M3: 0 | N3: 0 | O3: 0 | P3: 0 | Q3: 0 | R3: Very Low Risk
B4: NO DATA | L4: 20 | M4: 20 | N4: 20 | O4: 20 | P4: 20 | Q4: 20 | R4: Low Risk
L5: 40 | M5: 40 | N5: 40 | O5: 40 | P5: 40 | Q5: 40 | R5: Moderate Risk
B6: Country Name | F6: JERSEY | L6: 60 | M6: 60 | N6: 60 | O6: 60 | P6: 60 | Q6: 60 | R6: High Risk
B7: ISO Code | F7: =IFERROR(VLOOKUP(F6,'Country List'!$A:$D,2,FALSE),"") -> JEY | L7: 80 | M7: 80 | N7: 80 | O7: 80 | P7: 80 | Q7: 80 | R7: Very High Risk
B8: HDI Segmentation | F8: =IFERROR(VLOOKUP(F7,'Country List'!$B:$D,2,FALSE),"") -> VERY HIGH HUMAN DEVELOPMENT | L8: 100 | M8: 100 | N8: 100 | O8: 100 | P8: 100 | Q8: 100 | R8: Default
B9: Region | F9: =IFERROR(VLOOKUP(F7,'Country List'!$B:$D,3,FALSE),"") -> DEVELOPED MARKET
C12: Agency | D12: Score | E12: Bucket | F12: Risk
C13: EIU Rating | D13: =IFERROR(VLOOKUP($F$7,Nodata_Raw!$C:$D,2,FALSE),"No Dependent Variable") -> 19 | E13: =IFERROR(ROUND(D13/5,0),"") -> 4 | F13: =IFERROR(VLOOKUP(D13,$Q$3:$R$8,2,TRUE),"") -> Very Low Risk

Sheet HelpSheet
A1: Help Page | B1: Welcome to the Country Model The help notes are arranged by Tab. Either select a tab from the drop down below or scroll through the notes using the next/previous buttons.
A2: Home | B2: This is a dashboard for quick navigation through the pages in this spreadsheet. ---------------------------------------------------------------------- Simply click on the country you wish to rate or the segment that you wish to visit.
A3: High Segment | B3: The High Segment allows the user to select high segment countries that they would like to rate. ---------------------------------------------------------------------- In the drop down menu choose/select a country. The Base Model section is automatically updated with source information that produces a base model rating for a given country. If you are happy with the base model score select Yes if not and the use would like to adjsut the score select No. Yes will direct the user to the final overall rating, No will direct the user to the adjustment section. Adjustment Section: Answer the category questions and select approporiate answers from the drop down lists. The user is urged to answer all questions and to select "Not Applicable" if they do not wish to answer a specific question.
A4: Low Segment | B4: The Low Segment allows the user to select low segment countries that they would like to rate. ---------------------------------------------------------------------- In the drop down menu choose/select a country. The Base Model section is automatically updated with source information that produces a base model rating for a given country. If you are happy with the base model score select Yes if not and the use would like to adjsut the score select No. Yes will direct the user to the final overall rating, No will direct the user to the adjustment section. Adjustment Section: Answer the category questions and select approporiate answers from the drop down lists. The user is urged to answer all questions and to select "Not Applicable" if they do not wish to answer a specific question.
A5: No Data Segment | B5: The No Data Segment allows the user to select no data segment countries that they would like to rate using external agency ratings. ---------------------------------------------------------------------- In the drop down menu choose/select a country. Select an appropriate agency to use and the rating will automatically be updated with rating source information for the given country from the selected agency.

Sheet Standardisation_Parameters
A1: _STAT_ | B1: N | C1: MIN | D1: MAX | E1: MEAN | F1: STD | H1: _STAT_ | I1: N | J1: MIN | K1: MAX | L1: MEAN | M1: STD
A2: EIU_Score | B2: 794 | C2: 7.44 | D2: 90.11 | E2: 44.671 | F2: 16.715049 | H2: EIU_Score | I2: 794 | J2: 7.44 | K2: 90.11 | L2: 44.671 | M2: 16.715049
A3: DCPI_5 | B3: 794 | C3: -0.68 | D3: 57.39 | E3: 6.4567 | F3: 5.3054733 | H3: DCPI_5 | I3: 794 | J3: -0.68 | K3: 57.386 | L3: 6.4567 | M3: 5.3054733
A4: macro_var | B4: 794 | C4: 1 | D4: 9 | E4: 4.437 | F4: 1.9737723 | H4: macro_var | I4: 794 | J4: 1 | K4: 9 | L4: 4.437 | M4: 1.9737723
A5: ATF | B5: 794 | C5: 1 | D5: 6 | E5: 2.2733 | F5: 1.4862522 | H5: ATF | I5: 794 | J5: 1 | K5: 6 | L5: 2.2733 | M5: 1.4862522
A6: Nom_RIR | B6: 794 | C6: 1.48 | D6: 65.39 | E6: 11.767 | F6: 7.4519868 | H6: Nom_RIR | I6: 794 | J6: 1.475 | K6: 65.392 | L6: 11.767 | M6: 7.4519868
A7: DSR | B7: 794 | C7: -0.22 | D7: 91.6 | E7: 9.2081 | F7: 11.648243 | H7: DSR | I7: 794 | J7: -0.223 | K7: 91.6 | L7: 9.2081 | M7: 11.648243
A8: DSR_5year | B8: 794 | C8: 0.02 | D8: 76.66 | E8: 10.193 | F8: 10.568419 | H8: DSR_5year | I8: 794 | J8: 0.0173 | K8: 76.66 | L8: 10.193 | M8: 10.568419
A9: GROWTH_VOL | B9: 794 | C9: 0.2 | D9: 20.68 | E9: 2.7613 | F9: 2.3480587 | H9: GROWTH_VOL | I9: 794 | J9: 0.205 | K9: 20.678651 | L9: 2.7613 | M9: 2.3480587
A10: CAB_FDI | B10: 794 | C10: -43.08 | D10: 43.31 | E10: 1.5885 | F10: 10.355063 | H10: CAB_FDI | I10: 794 | J10: -43.08 | K10: 43.308269 | L10: 1.5885 | M10: 10.355063
A11: GDP_CAPITA | B11: 794 | C11: 164.2 | D11: 104570 | E11: 14228 | F11: 18014.76 | H11: GDP_CAPITA | I11: 794 | J11: 164.2 | K11: 104570 | L11: 14228 | M11: 18014.76
A12: COF | B12: 794 | C12: 0.08 | D12: 70 | E12: 6.1683 | F12: 5.3562941 | H12: COF | I12: 794 | J12: 0.08 | K12: 70 | L12: 6.1683 | M12: 5.3562941
A13: DT | B13: 794 | C13: -87.79 | D13: 359.62 | E13: 1.1828 | F13: 38.311976 | H13: DT | I13: 794 | J13: -87.79 | K13: 359.6188 | L13: 1.1828 | M13: 38.311976
... A21: XCM | B21: 794 | C21: 0 | D21: 85.68 | E21: 25.17 | F21: 15.843089 | H21: XCM | I21: 794 | J21: 0 | K21: 85.684 | L21: 25.17 | M21: 15.843089
A22: Nom_RIR_VOL | B22: 794 | C22: 0 | D22: 78.519056 | E22: 14.6 | F22: 11.163813

Sheet Buckets
A1: HIGH SEGMENT BASE MODEL | Q1: LOW SEGMENT BASE MODEL | AH1: GDP | AI1: Attributes | AJ1: Response
Q2: Buckets | R2: DCPI_5_Adj | S2: Min | T2: Max | U2: RAW Min | W2: Frequency | X2: Average EIU | Z2: Category Num | AA2: EIU Fitted | AB2: EIU Fitted Raw | AC2: Category Num | AH2: GDP per capita provides an incomplete picture of development in the country, given the high degree of income inequality (as measured by the GINI coefficient) | AI2: Applicable | AJ2: -1
A3: Buckets | B3: ATF | C3: Min | D3: Max | G3: Frequency | H3: Average EIU | J3: Category Num | K3: EIU Fitted | L3: EIU Fitted Raw | M3: Category Num | R3: 1 | T3: 0 | U3: -9999999999 | V3: 0 | X3: 0.54862195 | Z3: 2 | AA3: 0.5845 | AB3: =AA3*Standardisation_Parameters!$F$3+Standardisation_Parameters!$E$3 -> 9.5577491 | AC3: 1 | AI3: Not applicable | AJ3: 0
A4: ="<= " &F4 -> <= 1 | B4: 1 | C4: 1 | D4: 1 | E4: -9999999999 | F4: =ROUND(D4,2) -> 1 | G4: 299 | H4: -0.88594772 | J4: 1 | K4: -0.7287 | L4: =K4*Standardisation_Parameters!$F$5+Standardisation_Parameters!$E$5 -> 1.190268 | M4: 1 | Q4: <= 3 | R4: 0 | S4: 0 | T4: 3 | U4: 0 | V4: 3 | W4: 39 | X4: 0.58864962 | Z4: 1 | AA4: 0.388 | AB4: =AA4*Standardisation_Parameters!$F$3+Standardisation_Parameters!$E$3 -> 8.5152236 | AC4: 1
A5: [2 : 2] | B5: 4 | C5: 2 | D5: 2 | E5: =ROUND(C5,2) -> 2 | F5: =ROUND(D5,2) -> 2 | G5: 88 | H5: 0.13776324 | J5: 2 | K5: -0.1767 | L5: =K5*Standardisation_Parameters!$F$5+Standardisation_Parameters!$E$5 -> 2.0106792 | M5: 2 | Q5: (3 : 6] | R5: 1 | S5: 3 | T5: 6 | U5: 3 | V5: 6 | W5: 74 | X5: 0.54862195 | Z5: 2 | AA5: 0.5845 | AB5: =AA5*Standardisation_Parameters!$F$3+Standardisation_Parameters!$E$3 -> 9.5577491 | AC5: 2
A6: > 2 | B6: 5 | C6: 3 | D6: 6 | E6: =ROUND(C6,2) -> 3 | F6: -9999999999 | G6: 89 | H6: 0.21801705 | J6: 3 | K6: 0.3753 | L6: =K6*Standardisation_Parameters!$F$5+Standardisation_Parameters!$E$5 -> 2.8310905 | M6: 3 | Q6: (6 : 10] | R6: 2 | S6: 6 | T6: 10 | U6: 6 | V6: 10 | W6: 102 | X6: 0.64005279 | Z6: 3 | AA6: 0.781 | AB6: =AA6*Standardisation_Parameters!$F$3+Standardisation_Parameters!$E$3 -> 10.600275 | AC6: 3 | AH6: Export Market | AI6: Attributes | AJ6: Response
Q7: (10 : 15] | R7: 3 | S7: 10 | T7: 15 | U7: 10 | V7: 15 | W7: 81 | X7: 0.94352377 | Z7: 4 | AA7: 0.9775 | AB7: =AA7*Standardisation_Parameters!$F$3+Standardisation_Parameters!$E$3 -> 11.6428 | AC7: 4 | AH7: Exposure to an adverse export market (may either be one country or a grouping of countries) poses a significant concentration risk; | AI7: Concentration to adverse export market | AJ7: -1
A8: Buckets | B8: dcpi_5_adj | C8: Min | D8: Max | G8: Frequency | H8: Average EIU | J8: Category Num | K8: EIU Fitted | L8: EIU Fitted Raw | M8: Category Num | Q8: (15 : 20] | R8: 4 | S8: 15 | T8: 20 | U8: 15 | V8: 20 | W8: 11 | X8: 0.80585637 | Z8: 5 | AA8: 1.174 | AB8: =AA8*Standardisation_Parameters!$F$3+Standardisation_Parameters!$E$3 -> 12.685326 | AC8: 5 | AI8: No concentration risk | AJ8: 0
B9: 1 | D9: 0 | E9: -9999999999 | F9: 0 | H9: -0.33542548 | J9: 2 | K9: -0.5387 | L9: =K9*Standardisation_Parameters!$F$3+Standardisation_Parameters!$E$3 -> 3.5986415 | M9: 2 | Q9: > 20 | R9: 5 | S9: 20 | T9: 57.39 | U9: 20 | V9: 9999999999 | W9: 11 | X9: 1.7491906 | Z9: 6 | AA9: 1.3705 | AB9: =AA9*Standardisation_Parameters!$F$3+Standardisation_Parameters!$E$3 -> 13.727851 | AC9: 6
A10: <= 3 | B10: 0 | C10: 0 | D10: 3 | E10: 0 | F10: 3 | G10: 207 | H10: -1.0651401 | J10: 1 | K10: -0.9733 | L10: =K10*Standardisation_Parameters!$F$3+Standardisation_Parameters!$E$3 -> 1.2928828 | M10: 1
A11: (3 : 6] | B11: 1 | C11: 3 | D11: 6 | E11: 3 | F11: 6 | G11: 132 | H11: -0.33542548 | J11: 2 | K11: -0.5387 | L11: =K11*Standardisation_Parameters!$F$3+Standardisation_Parameters!$E$3 -> 3.5986415 | M11: 2 | AH11: CMA | AI11: Attributes | AJ11: Response
A12: (6 : 10] | B12: 2 | C12: 6 | D12: 10 | E12: 6 | F12: 10 | G12: 64 | H12: -0.15925001 | J12: 3 | K12: -0.0591 | L12: =K12*Standardisation_Parameters!$F$3+Standardisation_Parameters!$E$3 -> 6.1431465 | M12: 3 | R12: Macro_var | S12: Min | T12: Max | W12: Frequency | X12: Average EIU | Z12: Category Num | AA12: EIU Fitted | AC12: Category Num | AH12: Existence of a managed exchange rate regime or member of Common Monetary Area (CMA) | AI12: Sustainable and provides stability | AJ12: 1
A13: (10 : 15] | B13: 3 | C13: 10 | D13: 15 | E13: 10 | F13: 15 | G13: 50 | H13: 0.46492233 | J13: 4 | K13: 0.4655 | L13: =K13*Standardisation_Parameters!$F$3+Standardisation_Parameters!$E$3 -> 8.9263978 | M13: 4 | Q13: <= -0.69 | R13: 0 | S13: 2 | T13: 3 | U13: -9999999999 | V13: 3 | W13: 43 | X13: 0.23056616 | Z13: 1 | AA13: 0.3023 | AB13: =AA13*Standardisation_Parameters!$F$4+Standardisation_Parameters!$E$4 -> 5.0336714 | AC13: 1 | AI13: Unsustainable peg or encumbers monetary policy | AJ13: -1
A14: (15 : 20] | B14: 4 | C14: 15 | D14: 20 | E14: 15 | F14: 20 | G14: 9 | H14: 0.98279659 | J14: 5 | K14: 1.0351 | L14: =K14*Standardisation_Parameters!$F$3+Standardisation_Parameters!$E$3 -> 11.948395 | M14: 5 | Q14: (-0.69 : -0.18] | R14: 1 | S14: 4 | T14: 4 | U14: 4 | V14: 4 | W14: 60 | X14: 0.56043418 | Z14: 2 | AA14: 0.4707 | AB14: =AA14*Standardisation_Parameters!$F$4+Standardisation_Parameters!$E$4 -> 5.3660546 | AC14: 2 | AI14: No impact | AJ14: 0
A15: > 20 | B15: 5 | C15: 20 | D15: 21.28 | E15: 20 | F15: -9999999999 | G15: 7 | H15: 1.6910253 | J15: 6 | K15: 1.6497 | L15: =K15*Standardisation_Parameters!$F$3+Standardisation_Parameters!$E$3 -> 15.209139 | M15: 6 | Q15: (-0.18 : 0.32] | R15: 2 | S15: 5 | T15: 5 | U15: 5 | V15: 5 | W15: 80 | X15: 0.73860667 | Z15: 3 | AA15: 0.6471 | AB15: =AA15*Standardisation_Parameters!$F$4+Standardisation_Parameters!$E$4 -> 5.7142281 | AC15: 3
Q16: (0.32 : 0.83] | R16: 3 | S16: 6 | T16: 6 | U16: 6 | V16: 6 | W16: 44 | X16: 0.7373084 | Z16: 4 | AA16: 0.8315 | AB16: =AA16*Standardisation_Parameters!$F$4+Standardisation_Parameters!$E$4 -> 6.0781917 | AC16: 4 | AH16: Political Risk | AI16: Attributes | AJ16: Category Notching
Q17: (0.83 : 1.33] | R17: 4 | S17: 7 | T17: 7 | U17: 7 | V17: 7 | W17: 55 | X17: 0.93948421 | Z17: 5 | AA17: 1.0239 | AB17: =AA17*Standardisation_Parameters!$F$4+Standardisation_Parameters!$E$4 -> 6.4579455 | AC17: 5 | AH17: There is a risk of war within the country territory, but the risk is not expected to materialise within the next 3 years | AI17: High probability | AJ17: 2
A18: Buckets | B18: GDP_Capita | C18: Min | D18: Max | G18: Frequency | H18: Average EIU | J18: Category Num | K18: EIU Fitted | M18: Category Num | Q18: > 1.33 | R18: 5 | S18: 8 | T18: 9 | U18: 8 | V18: 9999999999 | W18: 36 | X18: 1.2952654 | Z18: 6 | AA18: 1.2243 | AB18: =AA18*Standardisation_Parameters!$F$4+Standardisation_Parameters!$E$4 -> 6.8534894 | AC18: 6 | AI18: Moderate probability | AJ18: 1
A19: <= -0.5 | B19: 0 | C19: -0.69207701 | D19: -0.50359823 | E19: -9999999999 | F19: =D19*Standardisation_Parameters!$F$11+Standardisation_Parameters!$E$11 -> 5155.7987 | G19: 79 | H19: 0.53179603 | J19: 1 | K19: 0.5588 | L19: =K19*Standardisation_Parameters!$F$11+Standardisation_Parameters!$E$11 -> 24294.648 | M19: 1 | AI19: Not Applicable | AJ19: 0
A20: (-0.5 : -0.3] | B20: 1 | C20: -0.50009555 | D20: -0.29905485 | E20: =C20*Standardisation_Parameters!$F$11+Standardisation_Parameters!$E$11 -> 5218.8987 | F20: =D20*Standardisation_Parameters!$F$11+Standardisation_Parameters!$E$11 -> 8840.5987 | G20: 79 | H20: 0.16626812 | J20: 2 | K20: 0.153 | L20: =K20*Standardisation_Parameters!$F$11+Standardisation_Parameters!$E$11 -> 16984.258 | M20: 2
A21: (-0.3 : 0.03] | B21: 2 | C21: -0.29808342 | D21: 0.010863244 | E21: =C21*Standardisation_Parameters!$F$11+Standardisation_Parameters!$E$11 -> 8858.0987 | F21: =D21*Standardisation_Parameters!$F$11+Standardisation_Parameters!$E$11 -> 14423.699 | G21: 80 | H21: -0.18005981 | J21: 3 | K21: -0.2632 | L21: =K21*Standardisation_Parameters!$F$11+Standardisation_Parameters!$E$11 -> 9486.5152 | M21: 3 | Q21: Buckets | R21: ATF | S21: Min | T21: Max | W21: Frequency | X21: Average EIU | Z21: Category Num | AA21: EIU Fitted | AC21: Category Num | AH21: Debt Service | AI21: Attributes | AJ21: Notching
A22: (0.03 : 0.78] | B22: 3 | C22: 0.025118222 | D22: 0.72931856 | E22: =C22*Standardisation_Parameters!$F$11+Standardisation_Parameters!$E$11 -> 14680.499 | F22: =D22*Standardisation_Parameters!$F$11+Standardisation_Parameters!$E$11 -> 27366.499 | G22: 79 | H22: -0.74372902 | J22: 4 | K22: -0.6898 | L22: =K22*Standardisation_Parameters!$F$11+Standardisation_Parameters!$E$11 -> 1801.4186 | M22: 4 | Q22: <= 1 | R22: 0 | S22: 1 | T22: 1 | U22: -9999999999 | V22: 1 | W22: 63 | X22: 0.31408493 | Z22: 1 | AA22: 0.332 | AB22: =AA22*Standardisation_Parameters!$F$5+Standardisation_Parameters!$E$5 -> 2.7667357 | AC22: 1 | AH22: In addition to the nominal level of external debt, debt serviceability improves/impedes the rating. | AI22: No impact | AJ22: 0
A23: (0.78 : 1.7] | B23: 4 | C23: 0.73641829 | D23: 1.66655 | E23: =C23*Standardisation_Parameters!$F$11+Standardisation_Parameters!$E$11 -> 27494.399 | F23: =D23*Standardisation_Parameters!$F$11+Standardisation_Parameters!$E$11 -> 44250.499 | G23: 80 | H23: -1.1798898 | J23: 5 | K23: -1.1268 | L23: =K23*Standardisation_Parameters!$F$11+Standardisation_Parameters!$E$11 -> -6071.0316 | M23: 5 | Q23: (1 : 2.5] | R23: 1 | S23: 2 | T23: 2.5 | U23: 2 | V23: 2.5 | W23: 55 | X23: 0.56625737 | Z23: 2 | AA23: 0.513 | AB23: =AA23*Standardisation_Parameters!$F$5+Standardisation_Parameters!$E$5 -> 3.0357474 | AC23: 2 | AI23: Low debt service | AJ23: 1
A24: > 1.7 | B24: 5 | C24: 1.6726395 | D24: 5.0149155 | E24: =C24*Standardisation_Parameters!$F$11+Standardisation_Parameters!$E$11 -> 44360.199 | F24: 9999999999 | G24: 79 | H24: -1.5312429 | J24: 6 | K24: -1.5742 | L24: =K24*Standardisation_Parameters!$F$11+Standardisation_Parameters!$E$11 -> -14130.835 | M24: 6 | Q24: (2.5 : 3] | R24: 2 | S24: 3 | T24: 3 | U24: 3 | V24: 3 | W24: 77 | X24: 0.66492696 | Z24: 3 | AA24: 0.7174 | AB24: =AA24*Standardisation_Parameters!$F$5+Standardisation_Parameters!$E$5 -> 3.3395373 | AC24: 3 | AI24: high debt service | AJ24: -1
Q25: (3 : 4] | R25: 3 | S25: 4 | T25: 4 | U25: 4 | V25: 4 | W25: 68 | X25: 0.96195199 | Z25: 4 | AA25: 0.9452 | AB25: =AA25*Standardisation_Parameters!$F$5+Standardisation_Parameters!$E$5 -> 3.6781056 | AC25: 4
Q26: > 4 | R26: 4 | S26: 5 | T26: 6 | U26: 5 | V26: 9999999999 | W26: 55 | X26: 1.196874 | Z26: 5 | AA26: 1.1964 | AB26: =AA26*Standardisation_Parameters!$F$5+Standardisation_Parameters!$E$5 -> 4.0514521 | AC26: 5 | AH26: Inflation | AI26: Attributes | AJ26: Response
A27: Buckets | B27: COF | C27: Min | D27: Max | G27: Frequency | H27: Average EIU | J27: Category Num | K27: EIU Fitted | M27: Category Num | AH27: IS the inflation great than 10.5%? | AI27: Yes | AJ27: -1
A28: <= -0.86 | B28: 0 | C28: -1.1290053 | D28: -0.92531974 | E28: -9999999999 | F28: =D28*Standardisation_Parameters!$F$12+Standardisation_Parameters!$E$12 -> 1.2120153 | G28: 78 | H28: -1.1304607 | J28: 1 | K28: -1.2093 | L28: =K28*Standardisation_Parameters!$F$12+Standardisation_Parameters!$E$12 -> -0.30906646 | M28: 1 | AI28: No | AJ28: 0
A29: (-0.86 : -0.56] | B29: 1 | C29: -0.9223326 | D29: -0.5838523 | E29: =C29*Standardisation_Parameters!$F$12+Standardisation_Parameters!$E$12 -> 1.2280153 | F29: =D29*Standardisation_Parameters!$F$12+Standardisation_Parameters!$E$12 -> 3.0410153 | G29: 80 | H29: -0.83365994 | J29: 2 | K29: -0.9205 | L29: =K29*Standardisation_Parameters!$F$12+Standardisation_Parameters!$E$12 -> 1.2378313 | M29: 2 | Q29: Buckets | R29: Nom_Rir | S29: Min | T29: Max | W29: Frequency | X29: Average EIU | Z29: Category Num | AA29: EIU Fitted | AC29: Category Num
A30: (-0.56 : -0.36] | B30: 2 | C30: -0.57843811 | D30: -0.34805494 | E30: =C30*Standardisation_Parameters!$F$12+Standardisation_Parameters!$E$12 -> 3.0700153 | F30: =D30*Standardisation_Parameters!$F$12+Standardisation_Parameters!$E$12 -> 4.3040154 | G30: 80 | H30: -0.91407981 | J30: 3 | K30: -0.6317 | L30: =K30*Standardisation_Parameters!$F$12+Standardisation_Parameters!$E$12 -> 2.784729 | M30: 3 | Q30: <= -0.43 | R30: 0 | S30: -1.0020082 | T30: -0.3686201 | U30: -9999999999 | V30: =T30*Standardisation_Parameters!$F$6+Standardisation_Parameters!$E$6 -> 9.0200479 | W30: 53 | X30: 0.57734774 | Z30: 1 | AA30: 0.4808 | AB30: =AA30*Standardisation_Parameters!$F$6+Standardisation_Parameters!$E$6 -> 15.349915 | AC30: 1
A31: (-0.36 : -0.15] | B31: 3 | C31: -0.34357423 | D31: -0.1662128 | E31: =C31*Standardisation_Parameters!$F$12+Standardisation_Parameters!$E$12 -> 4.3280154 | F31: =D31*Standardisation_Parameters!$F$12+Standardisation_Parameters!$E$12 -> 5.2780154 | G31: 83 | H31: -0.37313778 | J31: 4 | K31: -0.3429 | L31: =K31*Standardisation_Parameters!$F$12+Standardisation_Parameters!$E$12 -> 4.3316268 | M31: 4 | Q31: (-0.43 : -0.22] | R31: 1 | S31: -0.36727818 | T31: 0.031273252 | U31: =S31*Standardisation_Parameters!$F$6+Standardisation_Parameters!$E$6 -> 9.0300479 | V31: =T31*Standardisation_Parameters!$F$6+Standardisation_Parameters!$E$6 -> 12.000048 | W31: 53 | X31: 0.50845591 | Z31: 2 | AA31: 0.582 | AB31: =AA31*Standardisation_Parameters!$F$6+Standardisation_Parameters!$E$6 -> 16.104056 | AC31: 2
A32: (-0.15 : 0.24] | B32: 4 | C32: -0.16210548 | D32: 0.24862626 | E32: =C32*Standardisation_Parameters!$F$12+Standardisation_Parameters!$E$12 -> 5.3000154 | F32: =D32*Standardisation_Parameters!$F$12+Standardisation_Parameters!$E$12 -> 7.5000154 | G32: 76 | H32: 0.11336807 | J32: 5 | K32: -0.0541 | L32: =K32*Standardisation_Parameters!$F$12+Standardisation_Parameters!$E$12 -> 5.8785245 | M32: 5 | Q32: (-0.22 : -0.07] | R32: 2 | S32: 0.050060188 | T32: 0.34930924 | U32: =S32*Standardisation_Parameters!$F$6+Standardisation_Parameters!$E$6 -> 12.140048 | V32: =T32*Standardisation_Parameters!$F$6+Standardisation_Parameters!$E$6 -> 14.370048 | W32: 53 | X32: 0.6625018 | Z32: 3 | AA32: 0.6832 | AB32: =AA32*Standardisation_Parameters!$F$6+Standardisation_Parameters!$E$6 -> 16.858197 | AC32: 3
A33: > 0.24 | B33: 5 | C33: 0.25011983 | D33: 7.8098243 | E33: =C33*Standardisation_Parameters!$F$12+Standardisation_Parameters!$E$12 -> 7.5080154 | F33: 9999999999 | G33: 79 | H33: 0.21491003 | J33: 6 | K33: 0.2347 | L33: =K33*Standardisation_Parameters!$F$12+Standardisation_Parameters!$E$12 -> 7.4254222 | M33: 6 | Q33: (-0.07 : 0.2] | R33: 3 | S33: 0.36138656 | T33: 0.55006107 | U33: =S33*Standardisation_Parameters!$F$6+Standardisation_Parameters!$E$6 -> 14.460048 | V33: =T33*Standardisation_Parameters!$F$6+Standardisation_Parameters!$E$6 -> 15.866048 | W33: 53 | X33: 0.77136815 | Z33: 4 | AA33: 0.7844 | AB33: =AA33*Standardisation_Parameters!$F$6+Standardisation_Parameters!$E$6 -> 17.612338 | AC33: 4
R34: 4 | S34: 0.56522481 | T34: 1.0390582 | U34: =S34*Standardisation_Parameters!$F$6+Standardisation_Parameters!$E$6 -> 15.979048 | V34: =T34*Standardisation_Parameters!$F$6+Standardisation_Parameters!$E$6 -> 19.510048 | W34: 53 | X34: 0.78589454 | Z34: 5 | AA34: 0.8856 | AB34: =AA34*Standardisation_Parameters!$F$6+Standardisation_Parameters!$E$6 -> 18.36648 | AC34: 5
R35: 5 | S35: 1.0402659 | T35: 7.1960739 | U35: =S35*Standardisation_Parameters!$F$6+Standardisation_Parameters!$E$6 -> 19.519048 | V35: 9999999999 | W35: 53 | X35: 1.0976712 | Z35: 6 | AA35: 0.9868 | AB35: =AA35*Standardisation_Parameters!$F$6+Standardisation_Parameters!$E$6 -> 19.120621 | AC35: 6
A36: Buckets | B36: DT | C36: Min | D36: Max | G36: Frequency | H36: Average EIU | J36: Category Num | K36: EIU Fitted | M36: Category Num | N36: Peer Avg
A37: <= -0.41 | B37: 0 | C37: -1.5071845 | D37: -0.47081864 | E37: -9999999999 | F37: =D37*Standardisation_Parameters!$F$13+Standardisation_Parameters!$E$13 -> -16.855192 | G37: 79 | H37: 0.013801017 | J37: 1 | K37: -0.1792 | L37: =K37*Standardisation_Parameters!$F$13+Standardisation_Parameters!$E$13 -> -5.6827061 | M37: 1 | N37: -0.73370412 | O37: =N37*Standardisation_Parameters!$F$13+Standardisation_Parameters!$E$13 -> -26.926855
A38: (-0.41 : -0.1] | B38: 1 | C38: -0.47033545 | D38: -0.16055253 | E38: =C38*Standardisation_Parameters!$F$13+Standardisation_Parameters!$E$13 -> -16.836681 | F38: =D38*Standardisation_Parameters!$F$13+Standardisation_Parameters!$E$13 -> -4.9682848 | G38: 79 | H38: -0.36685598 | J38: 2 | K38: -0.3033 | L38: =K38*Standardisation_Parameters!$F$13+Standardisation_Parameters!$E$13 -> -10.437222 | M38: 2 | N38: -0.29970547 | O38: =N38*Standardisation_Parameters!$F$13+Standardisation_Parameters!$E$13 -> -10.299509 | Q38: Buckets | R38: DSR_5yr | S38: Min | T38: Max | W38: Frequency | X38: Average EIU | Z38: Category Num | AA38: EIU Fitted | AC38: Category Num
A39: (-0.1 : 0.11] | B39: 2 | C39: -0.15983084 | D39: 0.070269783 | E39: =C39*Standardisation_Parameters!$F$13+Standardisation_Parameters!$E$13 -> -4.9406352 | F39: =D39*Standardisation_Parameters!$F$13+Standardisation_Parameters!$E$13 -> 3.8749742 | G39: 80 | H39: -0.53395164 | J39: 3 | K39: -0.4274 | L39: =K39*Standardisation_Parameters!$F$13+Standardisation_Parameters!$E$13 -> -15.191739 | M39: 3 | N39: -0.040468842 | O39: =N39*Standardisation_Parameters!$F$13+Standardisation_Parameters!$E$13 -> -0.3676413 | R39: 0 | S39: -0.95346184 | T39: -0.69391433 | U39: -9999999999 | V39: =T39*Standardisation_Parameters!$F$8+Standardisation_Parameters!$E$8 -> 2.8594226 | W39: 53 | X39: 0.69159345 | Z39: 1 | AA39: 0.6499 | AB39: =AA39*Standardisation_Parameters!$F$8+Standardisation_Parameters!$E$8 -> 17.061416 | AC39: 1
A40: (0.11 : 0.37] | B40: 3 | C40: 0.07291973 | D40: 0.33716897 | E40: =C40*Standardisation_Parameters!$F$13+Standardisation_Parameters!$E$13 -> 3.9764989 | F40: =D40*Standardisation_Parameters!$F$13+Standardisation_Parameters!$E$13 -> 14.10041 | G40: 79 | H40: -0.64697529 | J40: 4 | K40: -0.5515 | L40: =K40*Standardisation_Parameters!$F$13+Standardisation_Parameters!$E$13 -> -19.946255 | M40: 4 | N40: 0.2103889 | O40: =N40*Standardisation_Parameters!$F$13+Standardisation_Parameters!$E$13 -> 9.2432146 | R40: 1 | S40: -0.6884452 | T40: -0.48760154 | U40: =S40*Standardisation_Parameters!$F$8+Standardisation_Parameters!$E$8 -> 2.9172226 | V40: =T40*Standardisation_Parameters!$F$8+Standardisation_Parameters!$E$8 -> 5.0398227 | W40: 53 | X40: 0.59273327 | Z40: 2 | AA40: 0.6646 | AB40: =AA40*Standardisation_Parameters!$F$8+Standardisation_Parameters!$E$8 -> 17.216771 | AC40: 2
A41: (0.37 : 0.75] | B41: 4 | C41: 0.33913025 | D41: 0.74203702 | E41: =C41*Standardisation_Parameters!$F$13+Standardisation_Parameters!$E$13 -> 14.17555 | F41: =D41*Standardisation_Parameters!$F$13+Standardisation_Parameters!$E$13 -> 29.611704 | G41: 80 | H41: -0.87478721 | J41: 5 | K41: -0.6756 | L41: =K41*Standardisation_Parameters!$F$13+Standardisation_Parameters!$E$13 -> -24.700771 | M41: 5 | N41: 0.52390446 | O41: =N41*Standardisation_Parameters!$F$13+Standardisation_Parameters!$E$13 -> 21.254615 | R41: 2 | S41: -0.47938839 | T41: -0.26781464 | U41: =S41*Standardisation_Parameters!$F$8+Standardisation_Parameters!$E$8 -> 5.1266227 | V41: =T41*Standardisation_Parameters!$F$8+Standardisation_Parameters!$E$8 -> 7.3626227 | W41: 53 | X41: 0.68895958 | Z41: 3 | AA41: 0.6933 | AB41: =AA41*Standardisation_Parameters!$F$8+Standardisation_Parameters!$E$8 -> 17.520085 | AC41: 3
A42: > 0.75 | B42: 5 | C42: 0.7491108 | D42: 9.3557169 | E42: =C42*Standardisation_Parameters!$F$13+Standardisation_Parameters!$E$13 -> 29.882715 | F42: 9999999999 | G42: 79 | H42: -0.52747073 | J42: 6 | K42: -0.7997 | L42: =K42*Standardisation_Parameters!$F$13+Standardisation_Parameters!$E$13 -> -29.455287 | M42: 6 | N42: 1.5988276 | O42: =N42*Standardisation_Parameters!$F$13+Standardisation_Parameters!$E$13 -> 62.437045 | R42: 3 | S42: -0.25927977 | T42: -0.044867379 | U42: =S42*Standardisation_Parameters!$F$8+Standardisation_Parameters!$E$8 -> 7.4528227 | V42: =T42*Standardisation_Parameters!$F$8+Standardisation_Parameters!$E$8 -> 9.7188227 | W42: 53 | X42: 0.76685923 | Z42: 4 | AA42: 0.736 | AB42: =AA42*Standardisation_Parameters!$F$8+Standardisation_Parameters!$E$8 -> 17.971356 | AC42: 4
R43: 4 | S43: -0.040968972 | T43: 0.22370638 | U43: =S43*Standardisation_Parameters!$F$8+Standardisation_Parameters!$E$8 -> 9.7600227 | V43: =T43*Standardisation_Parameters!$F$8+Standardisation_Parameters!$E$8 -> 12.557223 | W43: 53 | X43: 0.82728633 | Z43: 5 | AA43: 0.7927 | AB43: =AA43*Standardisation_Parameters!$F$8+Standardisation_Parameters!$E$8 -> 18.570586 | AC43: 5
R44: 5 | S44: 0.23097332 | T44: 1.9188133 | U44: =S44*Standardisation_Parameters!$F$8+Standardisation_Parameters!$E$8 -> 12.634023 | V44: 9999999999 | W44: 53 | X44: 0.8358075 | Z44: 6 | AA44: 0.8634 | AB44: =AA44*Standardisation_Parameters!$F$8+Standardisation_Parameters!$E$8 -> 19.317773 | AC44: 6
A45: Buckets | B45: CAB_FDI | C45: Min | D45: Max | G45: Frequency | H45: Average EIU | J45: Category Num | K45: EIU Fitted | M45: Category Num
A46: <= -0.45 | B46: 0 | C46: -3.4354657 | D46: -0.65800985 | E46: -9999999999 | F46: =D46*Standardisation_Parameters!$F$10+Standardisation_Parameters!$E$10 -> -5.2252334 | G46: 79 | H46: -0.47219154 | J46: 1 | K46: -0.5486 | L46: =K46*Standardisation_Parameters!$F$10+Standardisation_Parameters!$E$10 -> -4.0922876 | M46: 1
A47: (-0.45 : -0.31] | B47: 1 | C47: -0.65773513 | D47: -0.36712308 | E47: =C47*Standardisation_Parameters!$F$10+Standardisation_Parameters!$E$10 -> -5.2223887 | F47: =D47*Standardisation_Parameters!$F$10+Standardisation_Parameters!$E$10 -> -2.2130827 | G47: 79 | H47: -0.64067291 | J47: 2 | K47: -0.5253 | L47: =K47*Standardisation_Parameters!$F$10+Standardisation_Parameters!$E$10 -> -3.8510146 | M47: 2
A48: (-0.31 : -0.19] | B48: 2 | C48: -0.35466187 | D48: -0.054929665 | E48: =C48*Standardisation_Parameters!$F$10+Standardisation_Parameters!$E$10 -> -2.084046 | F48: =D48*Standardisation_Parameters!$F$10+Standardisation_Parameters!$E$10 -> 1.0196999 | G48: 80 | H48: -0.49397436 | J48: 3 | K48: -0.502 | L48: =K48*Standardisation_Parameters!$F$10+Standardisation_Parameters!$E$10 -> -3.6097416 | M48: 3
A49: (-0.19 : 0.11] | B49: 3 | C49: -0.054813833 | D49: 0.24649703 | E49: =C49*Standardisation_Parameters!$F$10+Standardisation_Parameters!$E$10 -> 1.0208993 | F49: =D49*Standardisation_Parameters!$F$10+Standardisation_Parameters!$E$10 -> 4.1409923 | G49: 79 | H49: -0.45520625 | J49: 4 | K49: -0.4787 | L49: =K49*Standardisation_Parameters!$F$10+Standardisation_Parameters!$E$10 -> -3.3684687 | M49: 4 | Q49: Buckets | R49: PR | S49: Min | T49: Max | W49: Frequency | X49: Average EIU | Z49: Category Num | AA49: EIU Fitted | AC49: Category Num
A50: (0.11 : 0.66] | B50: 4 | C50: 0.24859059 | D50: 0.79314449 | E50: =C50*Standardisation_Parameters!$F$10+Standardisation_Parameters!$E$10 -> 4.1626712 | F50: =D50*Standardisation_Parameters!$F$10+Standardisation_Parameters!$E$10 -> 9.8015611 | G50: 80 | H50: -0.44696998 | J50: 5 | K50: -0.4554 | L50: =K50*Standardisation_Parameters!$F$10+Standardisation_Parameters!$E$10 -> -3.1271957 | M50: 5 | Q50: <= 3 | R50: 0 | S50: 2 | T50: 3 | U50: -9999999999 | V50: 3 | W50: 65 | X50: 0.26237729 | Z50: 1 | AA50: 0.296 | AB50: =AA50*Standardisation_Parameters!$F$16+Standardisation_Parameters!$E$16 -> 4.4199 | AC50: 1
A51: > 0.66 | B51: 5 | C51: 0.7979822 | D51: 4.0246836 | E51: =C51*Standardisation_Parameters!$F$10+Standardisation_Parameters!$E$10 -> 9.8516559 | F51: 9999999999 | G51: 79 | H51: -0.43314624 | J51: 6 | K51: -0.4321 | L51: =K51*Standardisation_Parameters!$F$10+Standardisation_Parameters!$E$10 -> -2.8859227 | M51: 6 | Q51: (3 : 4] | R51: 1 | S51: 4 | T51: 4 | U51: 4 | V51: 4 | W51: 52 | X51: 0.60662436 | Z51: 2 | AA51: 0.4914 | AB51: =AA51*Standardisation_Parameters!$F$16+Standardisation_Parameters!$E$16 -> 4.7877273 | AC51: 2
Q52: (4 : 5] | R52: 2 | S52: 5 | T52: 5 | U52: 5 | V52: 5 | W52: 64 | X52: 0.56643294 | Z52: 3 | AA52: 0.7122 | AB52: =AA52*Standardisation_Parameters!$F$16+Standardisation_Parameters!$E$16 -> 5.2033684 | AC52: 3
Q53: (5 : 6] | R53: 4 | S53: 6 | T53: 6 | U53: 6 | V53: 6 | W53: 100 | X53: 1.0360065 | Z53: 4 | AA53: 0.9584 | AB53: =AA53*Standardisation_Parameters!$F$16+Standardisation_Parameters!$E$16 -> 5.6668232 | AC53: 4
A54: Buckets | B54: fdg_3yr | C54: Min | D54: Max | G54: Frequency | H54: Average EIU | J54: Category Num | K54: EIU Fitted | M54: Category Num | Q54: > 6 | R54: 5 | S54: 7 | T54: 7 | U54: 7 | V54: 9999999999 | W54: 37 | X54: 1.2140632 | Z54: 5 | AA54: 1.23 | AB54: =AA54*Standardisation_Parameters!$F$16+Standardisation_Parameters!$E$16 -> 6.1780919 | AC54: 5
A55: <= -1.69 | B55: 0 | C55: -0.61889195 | D55: -0.43738724 | E55: -9999999999 | F55: =D55*Standardisation_Parameters!$F$14+Standardisation_Parameters!$E$14 -> 24.184308 | G55: 79 | H55: 0.014495204 | J55: 1 | K55: 0.1933 | L55: =K55*Standardisation_Parameters!$F$14+Standardisation_Parameters!$E$14 -> 97.784934 | M55: 1
A56: (-1.69 : -1.19] | B56: 1 | C56: -0.43325585 | D56: -0.30762797 | E56: =C56*Standardisation_Parameters!$F$14+Standardisation_Parameters!$E$14 -> 24.666437 | F56: =D56*Standardisation_Parameters!$F$14+Standardisation_Parameters!$E$14 -> 39.327096 | G56: 79 | H56: -0.095427888 | J56: 2 | K56: -0.0799 | L56: =K56*Standardisation_Parameters!$F$14+Standardisation_Parameters!$E$14 -> 65.902743 | M56: 2
A57: (-1.19 : -0.69] | B57: 2 | C57: -0.3065189 | D57: -0.18438347 | E57: =C57*Standardisation_Parameters!$F$14+Standardisation_Parameters!$E$14 -> 39.456523 | F57: =D57*Standardisation_Parameters!$F$14+Standardisation_Parameters!$E$14 -> 53.709617 | G57: 80 | H57: -0.27038178 | J57: 3 | K57: -0.3531 | L57: =K57*Standardisation_Parameters!$F$14+Standardisation_Parameters!$E$14 -> 34.020551 | M57: 3 | Q57: Buckets | R57: ROL | S57: Min | T57: Max | W57: Frequency | X57: Average EIU | Z57: Category Num | AA57: EIU Fitted | AC57: Category Num
A58: (-0.69 : -0.18] | B58: 3 | C58: -0.18187799 | D58: 0.10252217 | E58: =C58*Standardisation_Parameters!$F$14+Standardisation_Parameters!$E$14 -> 54.002003 | F58: =D58*Standardisation_Parameters!$F$14+Standardisation_Parameters!$E$14 -> 87.191244 | G58: 79 | H58: -0.2492152 | J58: 4 | K58: -0.6263 | L58: =K58*Standardisation_Parameters!$F$14+Standardisation_Parameters!$E$14 -> 2.1383599 | M58: 4 | Q58: <= -1.23 | R58: 0 | S58: -2.0042784 | T58: -1.2300559 | U58: -9999999999 | V58: =T58*Standardisation_Parameters!$F$17+Standardisation_Parameters!$E$17 -> -1.1641103 | W58: 53 | X58: 1.401229 | Z58: 1 | AA58: 1.4056 | AB58: =AA58*Standardisation_Parameters!$F$17+Standardisation_Parameters!$E$17 -> 1.4288079 | AC58: 1
A59: (-0.18 : 0.32] | B59: 4 | C59: 0.10374522 | D59: 0.66921094 | E59: =C59*Standardisation_Parameters!$F$14+Standardisation_Parameters!$E$14 -> 87.333973 | F59: =D59*Standardisation_Parameters!$F$14+Standardisation_Parameters!$E$14 -> 153.32331 | G59: 80 | H59: -0.94656634 | J59: 5 | K59: -0.8995 | L59: =K59*Standardisation_Parameters!$F$14+Standardisation_Parameters!$E$14 -> -29.743831 | M59: 5 | Q59: (-1.23 : -0.97] | R59: 1 | S59: -1.2296045 | T59: -0.96087199 | U59: =S59*Standardisation_Parameters!$F$17+Standardisation_Parameters!$E$17 -> -1.1636663 | V59: =T59*Standardisation_Parameters!$F$17+Standardisation_Parameters!$E$17 -> -0.89929126 | W59: 53 | X59: 1.1586489 | Z59: 2 | AA59: 1.12 | AB59: =AA59*Standardisation_Parameters!$F$17+Standardisation_Parameters!$E$17 -> 1.147839 | AC59: 2
A60: > 0.32 | B60: 5 | C60: 0.67895507 | D60: 8.1986465 | E60: =C60*Standardisation_Parameters!$F$14+Standardisation_Parameters!$E$14 -> 154.46044 | F60: 9999999999 | G60: 79 | H60: -1.3915716 | J60: 6 | K60: -1.1727 | L60: =K60*Standardisation_Parameters!$F$14+Standardisation_Parameters!$E$14 -> -61.626023 | M60: 6 | Q60: (-0.97 : -0.7] | R60: 2 | S60: -0.9603456 | T60: -0.71364259 | U60: =S60*Standardisation_Parameters!$F$17+Standardisation_Parameters!$E$17 -> -0.8987734 | V60: =T60*Standardisation_Parameters!$F$17+Standardisation_Parameters!$E$17 -> -0.65607073 | W60: 53 | X60: 0.79718127 | Z60: 3 | AA60: 0.847 | AB60: =AA60*Standardisation_Parameters!$F$17+Standardisation_Parameters!$E$17 -> 0.87926573 | AC60: 3
Q61: (-0.7 : -0.47] | R61: 3 | S61: -0.71188425 | T61: -0.50182507 | U61: =S61*Standardisation_Parameters!$F$17+Standardisation_Parameters!$E$17 -> -0.65434091 | V61: =T61*Standardisation_Parameters!$F$17+Standardisation_Parameters!$E$17 -> -0.44768788 | W61: 53 | X61: 0.5483765 | Z61: 4 | AA61: 0.5866 | AB61: =AA61*Standardisation_Parameters!$F$17+Standardisation_Parameters!$E$17 -> 0.62308816 | AC61: 4
Q62: (-0.47 : -0.18] | R62: 4 | S62: -0.4942469 | T62: -0.23665479 | U62: =S62*Standardisation_Parameters!$F$17+Standardisation_Parameters!$E$17 -> -0.44023259 | V62: =T62*Standardisation_Parameters!$F$17+Standardisation_Parameters!$E$17 -> -0.18681739 | W62: 53 | X62: 0.43333812 | Z62: 5 | AA62: 0.3388 | AB62: =AA62*Standardisation_Parameters!$F$17+Standardisation_Parameters!$E$17 -> 0.37930629 | AC62: 5
A63: Buckets | B63: DSR | C63: Min | D63: Max | G63: Frequency | H63: Average EIU | J63: Category Num | K63: EIU Fitted | M63: Category Num | Q63: > -0.18 | R63: 5 | S63: -0.23551776 | T63: 0.63083916 | U63: =S63*Standardisation_Parameters!$F$17+Standardisation_Parameters!$E$17 -> -0.1856988 | V63: 9999999999 | W63: 53 | X63: 0.064465547 | Z63: 6 | AA63: 0.1036 | AB63: =AA63*Standardisation_Parameters!$F$17+Standardisation_Parameters!$E$17 -> 0.14792011 | AC63: 6
A64: <= -1.32 | B64: 0 | C64: -0.78916002 | D64: -0.75445942 | E64: -9999999999 | F64: =D64*Standardisation_Parameters!$F$7+Standardisation_Parameters!$E$7 -> 0.41997331 | G64: 75 | H64: -1.3405303 | J64: 1 | K64: -1.1383 | L64: =K64*Standardisation_Parameters!$F$7+Standardisation_Parameters!$E$7 -> -4.051095 | M64: 1
A65: (-1.32 : -1.02] | B65: 1 | C65: -0.75430477 | D65: -0.66174164 | E65: =C65*Standardisation_Parameters!$F$7+Standardisation_Parameters!$E$7 -> 0.42177472 | F65: =D65*Standardisation_Parameters!$F$7+Standardisation_Parameters!$E$7 -> 1.4999726 | G65: 83 | H65: -1.2476161 | J65: 2 | K65: -0.8802 | L65: =K65*Standardisation_Parameters!$F$7+Standardisation_Parameters!$E$7 -> -1.0446835 | M65: 2
A66: (-1.02 : -0.68] | B66: 2 | C66: -0.65315665 | D66: -0.24966233 | E66: =C66*Standardisation_Parameters!$F$7+Standardisation_Parameters!$E$7 -> 1.5999726 | F66: =D66*Standardisation_Parameters!$F$7+Standardisation_Parameters!$E$7 -> 6.2999725 | G66: 80 | H66: -0.033896616 | J66: 3 | K66: -0.6221 | L66: =K66*Standardisation_Parameters!$F$7+Standardisation_Parameters!$E$7 -> 1.961728 | M66: 3 | Q66: Buckets | R66: SR | S66: Min | T66: Max | W66: Frequency | X66: Average EIU | Z66: Category Num | AA66: EIU Fitted | AC66: Category Num
A67: (-0.68 : -0.25] | B67: 3 | C67: -0.24107735 | D67: 0.2375356 | E67: =C67*Standardisation_Parameters!$F$7+Standardisation_Parameters!$E$7 -> 6.3999725 | F67: =D67*Standardisation_Parameters!$F$7+Standardisation_Parameters!$E$7 -> 11.974972 | G67: 79 | H67: -0.081621554 | J67: 4 | K67: -0.364 | L67: =K67*Standardisation_Parameters!$F$7+Standardisation_Parameters!$E$7 -> 4.9681395 | M67: 4 | Q67: <= 2.25 | R67: 0 | S67: 1.5 | T67: 2.25 | U67: -9999999999 | V67: 2.25 | W67: 44 | X67: 0.27865047 | Z67: 1 | AA67: 0.1972 | AB67: =AA67*Standardisation_Parameters!$F$18+Standardisation_Parameters!$E$18 -> 2.8720952 | AC67: 1
A68: (-0.25 : 0.45] | B68: 4 | C68: 0.23968185 | D68: 0.98485859 | E68: =C68*Standardisation_Parameters!$F$7+Standardisation_Parameters!$E$7 -> 11.999972 | F68: =D68*Standardisation_Parameters!$F$7+Standardisation_Parameters!$E$7 -> 20.679972 | G68: 80 | H68: 0.044455929 | J68: 5 | K68: -0.1059 | L68: =K68*Standardisation_Parameters!$F$7+Standardisation_Parameters!$E$7 -> 7.9745511 | M68: 5 | Q68: (2.25 : 2.75] | R68: 1 | S68: 2.5 | T68: 2.75 | U68: 2.5 | V68: 2.75 | W68: 45 | X68: 0.37394924 | Z68: 2 | AA68: 0.4056 | AB68: =AA68*Standardisation_Parameters!$F$18+Standardisation_Parameters!$E$18 -> 3.0616791 | AC68: 2
A69: > 0.45 | B69: 5 | C69: 0.99601907 | D69: 7.0733303 | E69: =C69*Standardisation_Parameters!$F$7+Standardisation_Parameters!$E$7 -> 20.809972 | F69: 9999999999 | G69: 79 | H69: -0.29970156 | J69: 6 | K69: 0.1522 | L69: =K69*Standardisation_Parameters!$F$7+Standardisation_Parameters!$E$7 -> 10.980963 | M69: 6 | Q69: (2.75 : 3] | R69: 2 | S69: 3 | T69: 3 | U69: 3 | V69: 3 | W69: 51 | X69: 0.62915827 | Z69: 3 | AA69: 0.614 | AB69: =AA69*Standardisation_Parameters!$F$18+Standardisation_Parameters!$E$18 -> 3.2512631 | AC69: 3
Q70: (3 : 3.5] | R70: 3 | S70: 3.25 | T70: 3.5 | U70: 3.25 | V70: 3.5 | W70: 66 | X70: 0.65613444 | Z70: 4 | AA70: 0.8224 | AB70: =AA70*Standardisation_Parameters!$F$18+Standardisation_Parameters!$E$18 -> 3.4408471 | AC70: 4
Q71: (3.5 : 4] | R71: 4 | S71: 3.75 | T71: 4 | U71: 3.75 | V71: 4 | W71: 69 | X71: 1.0364585 | Z71: 5 | AA71: 1.0308 | AB71: =AA71*Standardisation_Parameters!$F$18+Standardisation_Parameters!$E$18 -> 3.630431 | AC71: 5
A72: Buckets | B72: Macro_var | C72: Min | D72: Max | G72: Frequency | H72: Average EIU | J72: Category Num | K72: EIU Fitted | M72: Category Num | Q72: > 4 | R72: 5 | S72: 4.25 | T72: 4.75 | U72: 4.25 | V72: 9999999999 | W72: 43 | X72: 1.3343201 | Z72: 6 | AA72: 1.2392 | AB72: =AA72*Standardisation_Parameters!$F$18+Standardisation_Parameters!$E$18 -> 3.820015 | AC72: 6
A73: <= 1 | B73: 0 | C73: 1 | D73: 1 | E73: -9999999999 | F73: 1 | G73: 52 | H73: -1.7289571 | J73: 1 | K73: -1.6418 | L73: =K73*Standardisation_Parameters!$F$4+Standardisation_Parameters!$E$4 -> 1.1964606 | M73: 1
A74: (1 : 2] | B74: 1 | C74: 2 | D74: 2 | E74: 2 | F74: 2 | G74: 82 | H74: -1.0245124 | J74: 2 | K74: -1.1529 | L74: =K74*Standardisation_Parameters!$F$4+Standardisation_Parameters!$E$4 -> 2.1614379 | M74: 2
A75: (2 : 3] | B75: 2 | C75: 3 | D75: 3 | E75: 3 | F75: 3 | G75: 98 | H75: -0.6889155 | J75: 3 | K75: -0.7102 | L75: =K75*Standardisation_Parameters!$F$4+Standardisation_Parameters!$E$4 -> 3.0352269 | M75: 3 | R75: DB (NEGATIVE ROL) | S75: Min | T75: Max | W75: Frequency | X75: Average EIU | Z75: Category Num | AA75: EIU Fitted | AC75: Category Num
A76: (3 : 5] | B76: 3 | C76: 4 | D76: 4 | E76: 4 | F76: 5 | G76: 83 | H76: -0.27622634 | J76: 4 | K76: -0.3137 | L76: =K76*Standardisation_Parameters!$F$4+Standardisation_Parameters!$E$4 -> 3.8178276 | M76: 4 | Q76: <= 0.59 | R76: 0 | S76: -1.355429 | T76: 0.58180791 | U76: -9999999999 | V76: =T76*Standardisation_Parameters!$F$15+Standardisation_Parameters!$E$15 -> 60.109178 | W76: 96 | X76: 0.72896771 | Z76: 1 | AA76: 0.729 | AB76: =AA76*Standardisation_Parameters!$F$15+Standardisation_Parameters!$E$15 -> 64.178076 | AC76: 1
A77: > 5 | B77: 4 | C77: 5 | D77: 5 | E77: 6 | F77: 7 | G77: 67 | H77: -0.17942532 | J77: 5 | K77: 0.0366 | L77: =K77*Standardisation_Parameters!$F$4+Standardisation_Parameters!$E$4 -> 4.5092401 | M77: 5 | Q77: (0.59 : 1.27] | R77: 1 | S77: 0.58584883 | T77: 1.2539105 | U77: =S77*Standardisation_Parameters!$F$15+Standardisation_Parameters!$E$15 -> 60.220883 | V77: =T77*Standardisation_Parameters!$F$15+Standardisation_Parameters!$E$15 -> 78.688414 | W77: 97 | X77: 0.77446864 | Z77: 2 | AA77: 0.7746 | AB77: =AA77*Standardisation_Parameters!$F$15+Standardisation_Parameters!$E$15 -> 65.438617 | AC77: 2
B78: 5 | C78: 6 | D78: 9 | E78: 7 | F78: 9999999999 | G78: 94 | H78: 0.4575117 | J78: 6 | K78: 0.3407 | L78: =K78*Standardisation_Parameters!$F$4+Standardisation_Parameters!$E$4 -> 5.1094642 | M78: 6 | Q78: > 1.27 | R78: 2 | S78: 1.265378 | T78: 2.0248517 | U78: =S78*Standardisation_Parameters!$F$15+Standardisation_Parameters!$E$15 -> 79.005414 | V78: 9999999999 | W78: 95 | X78: 0.9674816 | Z78: 3 | AA78: 0.9678 | AB78: =AA78*Standardisation_Parameters!$F$15+Standardisation_Parameters!$E$15 -> 70.779332 | AC78: 3
A80: Buckets | B80: DB | C80: Min | D80: Max | G80: Frequency | H80: Average EIU | J80: Category Num | K80: EIU Fitted | M80: Category Num
A81: <= -1.32 | B81: 0 | C81: -1.5728739 | D81: -1.3158935 | E81: -9999999999 | F81: =D81*Standardisation_Parameters!$F$15+Standardisation_Parameters!$E$15 -> 7.6501613 | G81: 78 | H81: -1.4702274 | J81: 1 | K81: -1.491 | L81: =K81*Standardisation_Parameters!$F$15+Standardisation_Parameters!$E$15 -> 2.8096146 | M81: 1
A82: (-1.32 : -1.02] | B82: 1 | C82: -1.3128356 | D82: -1.0589131 | E82: =C82*Standardisation_Parameters!$F$15+Standardisation_Parameters!$E$15 -> 7.7346947 | F82: =D82*Standardisation_Parameters!$F$15+Standardisation_Parameters!$E$15 -> 14.753987 | G82: 82 | H82: -1.1261555 | J82: 2 | K82: -1.0902 | L82: =K82*Standardisation_Parameters!$F$15+Standardisation_Parameters!$E$15 -> 13.88911 | M82: 2
A83: (-1.02 : -0.68] | B83: 2 | C83: -1.0551855 | D83: -0.68332639 | E83: =C83*Standardisation_Parameters!$F$15+Standardisation_Parameters!$E$15 -> 14.857031 | F83: =D83*Standardisation_Parameters!$F$15+Standardisation_Parameters!$E$15 -> 25.1365 | G83: 78 | H83: -0.66541842 | J83: 3 | K83: -0.6894 | L83: =K83*Standardisation_Parameters!$F$15+Standardisation_Parameters!$E$15 -> 24.968605 | M83: 3 | R83: DB (POSITIVE ROL) | S83: Min | T83: Max | W83: Frequency | X83: Average EIU | Z83: Category Num | AA83: EIU Fitted | AC83: Category Num
A84: (-0.68 : -0.25] | B84: 3 | C84: -0.67327871 | D84: -0.24900127 | E84: =C84*Standardisation_Parameters!$F$15+Standardisation_Parameters!$E$15 -> 25.414253 | F84: =D84*Standardisation_Parameters!$F$15+Standardisation_Parameters!$E$15 -> 37.142746 | G84: 80 | H84: -0.29406635 | J84: 4 | K84: -0.2886 | L84: =K84*Standardisation_Parameters!$F$15+Standardisation_Parameters!$E$15 -> 36.0481 | M84: 4 | Q84: <= -0.71 | R84: 0 | S84: -1.2205566 | T84: -0.63330641 | U84: -9999999999 | V84: =T84*Standardisation_Parameters!$F$15+Standardisation_Parameters!$E$15 -> 26.519225 | W84: 10 | X84: -0.16304005 | Z84: 1 | AA84: -0.2519 | AB84: =AA84*Standardisation_Parameters!$F$15+Standardisation_Parameters!$E$15 -> 37.062615 | AC84: 1
A85: (-0.25 : 0.45] | B85: 4 | C85: -0.22866875 | D85: 0.44343385 | E85: =C85*Standardisation_Parameters!$F$15+Standardisation_Parameters!$E$15 -> 37.704807 | F85: =D85*Standardisation_Parameters!$F$15+Standardisation_Parameters!$E$15 -> 56.284042 | G85: 79 | H85: 0.089868802 | J85: 5 | K85: 0.1122 | L85: =K85*Standardisation_Parameters!$F$15+Standardisation_Parameters!$E$15 -> 47.127595 | M85: 5 | Q85: (-0.71 : 0.25] | R85: 1 | S85: -0.60041491 | T85: 0.24711211 | U85: =S85*Standardisation_Parameters!$F$15+Standardisation_Parameters!$E$15 -> 27.42846 | V85: =T85*Standardisation_Parameters!$F$15+Standardisation_Parameters!$E$15 -> 50.857032 | W85: 11 | X85: -0.28554503 | Z85: 2 | AA85: -0.1077 | AB85: =AA85*Standardisation_Parameters!$F$15+Standardisation_Parameters!$E$15 -> 41.0488 | AC85: 2
A86: > 0.45 | B86: 5 | C86: 0.44594577 | D86: 1.9062454 | E86: =C86*Standardisation_Parameters!$F$15+Standardisation_Parameters!$E$15 -> 56.35348 | F86: 9999999999 | G86: 79 | H86: 0.5313812 | J86: 6 | K86: 0.513 | L86: =K86*Standardisation_Parameters!$F$15+Standardisation_Parameters!$E$15 -> 58.20709 | M86: 6 | Q86: > 0.25 | R86: 2 | S86: 0.28529206 | T86: 1.1773247 | U86: =S86*Standardisation_Parameters!$F$15+Standardisation_Parameters!$E$15 -> 51.912457 | V86: 9999999999 | W86: 9 | X86: 0.12533023 | Z86: 3 | AA86: 0.0365 | AB86: =AA86*Standardisation_Parameters!$F$15+Standardisation_Parameters!$E$15 -> 45.034986 | AC86: 3
Q88: EXTRA CHARACTERISTICS THAT ARE REQUIRED FOR THE ADJUSMENT FACTORS
A89: Buckets | B89: PR | C89: Min | D89: Max | G89: Frequency | H89: Average EIU | J89: Category Num | K89: EIU Fitted | M89: Category Num
A90: <= 1 | B90: 0 | C90: 1 | D90: 1 | E90: -9999999999 | F90: 1 | G90: 122 | H90: -1.5639476 | J90: 1 | K90: -1.5285 | L90: =K90*Standardisation_Parameters!$F$16+Standardisation_Parameters!$E$16 -> 0.98540208 | M90: 1 | R90: DCPI_5yr_Diff | S90: Min | T90: Max | W90: Frequency | X90: Average EIU | Z90: Category Num | AA90: EIU Fitted | AC90: Category Num | AD90: Peer Average
A91: (1 : 2] | B91: 2 | C91: 2 | D91: 2 | E91: 2 | F91: 2 | G91: 85 | H91: -0.87386127 | J91: 2 | K91: -0.9315 | L91: =K91*Standardisation_Parameters!$F$16+Standardisation_Parameters!$E$16 -> 2.1092142 | M91: 2 | R91: 0 | S91: -8.3194217 | T91: -0.73818761 | U91: -9999999999 | V91: =T91*Standardisation_Parameters!$F$19+Standardisation_Parameters!$E$19 -> -4.0734171 | W91: 53 | X91: 0.93578771 | Z91: 1 | AA91: 0.8896 | AB91: =AA91*Standardisation_Parameters!$F$19+Standardisation_Parameters!$E$19 -> 4.7435472 | AC91: 1 | AD91: -1.6545241 | AE91: =AD91*Standardisation_Parameters!$F$19+Standardisation_Parameters!$E$19 -> -9.0367831
A92: (2 : 3] | B92: 3 | C92: 3 | D92: 3 | E92: 3 | F92: 3 | G92: 83 | H92: -0.31739998 | J92: 3 | K92: -0.3583 | L92: =K92*Standardisation_Parameters!$F$16+Standardisation_Parameters!$E$16 -> 3.1882245 | M92: 3 | R92: 1 | S92: -0.69465422 | T92: -0.31245398 | U92: =S92*Standardisation_Parameters!$F$19+Standardisation_Parameters!$E$19 -> -3.8376171 | V92: =T92*Standardisation_Parameters!$F$19+Standardisation_Parameters!$E$19 -> -1.7674171 | W92: 53 | X92: 0.71917376 | Z92: 2 | AA92: 0.7589 | AB92: =AA92*Standardisation_Parameters!$F$19+Standardisation_Parameters!$E$19 -> 4.0356064 | AC92: 2 | AD92: -0.49132704 | AE92: =AD92*Standardisation_Parameters!$F$19+Standardisation_Parameters!$E$19 -> -2.7362888
A93: (3 : 5] | B93: 4 | C93: 4 | D93: 5 | E93: 4 | F93: 5 | G93: 123 | H93: 0.079565161 | J93: 4 | K93: 0.1911 | L93: =K93*Standardisation_Parameters!$F$16+Standardisation_Parameters!$E$16 -> 4.2224328 | M93: 4 | R93: 2 | S93: -0.3120109 | T93: -0.079611289 | U93: =S93*Standardisation_Parameters!$F$19+Standardisation_Parameters!$E$19 -> -1.7650171 | V93: =T93*Standardisation_Parameters!$F$19+Standardisation_Parameters!$E$19 -> -0.50621713 | W93: 53 | X93: 0.56165493 | Z93: 3 | AA93: 0.6796 | AB93: =AA93*Standardisation_Parameters!$F$19+Standardisation_Parameters!$E$19 -> 3.6060754 | AC93: 3 | AD93: -0.18722731 | AE93: =AD93*Standardisation_Parameters!$F$19+Standardisation_Parameters!$E$19 -> -1.0891228
A94: > 5 | B94: 5 | C94: 6 | D94: 7 | E94: 6 | F94: 9999999999 | G94: 63 | H94: 0.766124 | J94: 5 | K94: 0.7167 | L94: =K94*Standardisation_Parameters!$F$16+Standardisation_Parameters!$E$16 -> 5.2118393 | M94: 5 | R94: 3 | S94: -0.059746181 | T94: 0.23254414 | U94: =S94*Standardisation_Parameters!$F$19+Standardisation_Parameters!$E$19 -> -0.39861713 | V94: =T94*Standardisation_Parameters!$F$19+Standardisation_Parameters!$E$19 -> 1.1845829 | W94: 53 | X94: 0.78063559 | Z94: 4 | AA94: 0.6517 | AB94: =AA94*Standardisation_Parameters!$F$19+Standardisation_Parameters!$E$19 -> 3.4549542 | AC94: 4 | AD94: 0.069462014 | AE94: =AD94*Standardisation_Parameters!$F$19+Standardisation_Parameters!$E$19 -> 0.30124325
R95: 4 | S95: 0.25455084 | T95: 0.72913491 | U95: =S95*Standardisation_Parameters!$F$19+Standardisation_Parameters!$E$19 -> 1.3037829 | V95: =T95*Standardisation_Parameters!$F$19+Standardisation_Parameters!$E$19 -> 3.8743829 | W95: 53 | X95: 0.69710575 | Z95: 5 | AA95: 0.6752 | AB95: =AA95*Standardisation_Parameters!$F$19+Standardisation_Parameters!$E$19 -> 3.5822427 | AC95: 5 | AD95: 0.47359929 | AE95: =AD95*Standardisation_Parameters!$F$19+Standardisation_Parameters!$E$19 -> 2.4902659
R96: 5 | S96: 0.72976262 | T96: 5.9134111 | U96: =S96*Standardisation_Parameters!$F$19+Standardisation_Parameters!$E$19 -> 3.8777829 | V96: 9999999999 | W96: 53 | X96: 0.70888163 | Z96: 6 | AA96: 0.7501 | AB96: =AA96*Standardisation_Parameters!$F$19+Standardisation_Parameters!$E$19 -> 3.987941 | AC96: 6 | AD96: 1.4647549 | AE96: =AD96*Standardisation_Parameters!$F$19+Standardisation_Parameters!$E$19 -> 7.8588923
R98: XCS | S98: Min | T98: Max | W98: Frequency | X98: Average EIU | Z98: Category Num | AA98: EIU Fitted | AC98: Category Num
A99: Buckets | B99: ROL | C99: Min | D99: Max | G99: Frequency | H99: Average EIU | J99: Category Num | K99: EIU Fitted | M99: Category Num | R99: 0 | S99: -1.5030742 | T99: -1.1066598 | U99: -9999999999 | V99: =T99*Standardisation_Parameters!$F$20+Standardisation_Parameters!$E$20 -> 14.967682 | W99: 53 | X99: 0.65707102 | Y99: -1.2943852 | Z99: 1 | AA99: 0.7397 | AB99: =AA99*Standardisation_Parameters!$F$20+Standardisation_Parameters!$E$20 -> 58.311778 | AC99: 1
A100: <= -0.64 | B100: 0 | C100: -1.7162724 | D100: -0.61627232 | E100: -9999999999 | F100: =D100*Standardisation_Parameters!$F$17+Standardisation_Parameters!$E$17 -> -0.56027934 | G100: 79 | H100: 0.85752388 | J100: 1 | K100: 0.8449 | L100: =K100*Standardisation_Parameters!$F$17+Standardisation_Parameters!$E$17 -> 0.87719978 | M100: 1 | R100: 1 | S100: -1.0937953 | T100: -0.64238719 | U100: =S100*Standardisation_Parameters!$F$20+Standardisation_Parameters!$E$20 -> 15.269682 | V100: =T100*Standardisation_Parameters!$F$20+Standardisation_Parameters!$E$20 -> 25.866682 | W100: 53 | X100: 0.76084023 | Y100: -0.90918621 | Z100: 2 | AA100: 0.6265 | AB100: =AA100*Standardisation_Parameters!$F$20+Standardisation_Parameters!$E$20 -> 55.654359 | AC100: 2
A101: (-0.64 : -0.14] | B101: 1 | C101: -0.61423373 | D101: -0.09794663 | E101: =C101*Standardisation_Parameters!$F$17+Standardisation_Parameters!$E$17 -> -0.5582738 | F101: =D101*Standardisation_Parameters!$F$17+Standardisation_Parameters!$E$17 -> -0.050358406 | G101: 79 | H101: 0.21675026 | J101: 2 | K101: 0.2436 | L101: =K101*Standardisation_Parameters!$F$17+Standardisation_Parameters!$E$17 -> 0.28564998 | M101: 2 | R101: 2 | S101: -0.64136485 | T101: -0.23574932 | U101: =S101*Standardisation_Parameters!$F$20+Standardisation_Parameters!$E$20 -> 25.890682 | V101: =T101*Standardisation_Parameters!$F$20+Standardisation_Parameters!$E$20 -> 35.412683 | W101: 57 | X101: 0.61704627 | Y101: -0.41717862 | Z101: 3 | AA101: 0.5965 | AB101: =AA101*Standardisation_Parameters!$F$20+Standardisation_Parameters!$E$20 -> 54.950096 | AC101: 3
A102: (-0.14 : 0.52] | B102: 2 | C102: -0.062014941 | D102: 0.53681978 | E102: =C102*Standardisation_Parameters!$F$17+Standardisation_Parameters!$E$17 -> -0.015009356 | F102: =D102*Standardisation_Parameters!$F$17+Standardisation_Parameters!$E$17 -> 0.57411514 | G102: 80 | H102: -0.30279934 | J102: 3 | K102: -0.3067 | L102: =K102*Standardisation_Parameters!$F$17+Standardisation_Parameters!$E$17 -> -0.2557268 | M102: 3 | R102: 3 | S102: -0.22535548 | T102: 0.22494506 | U102: =S102*Standardisation_Parameters!$F$20+Standardisation_Parameters!$E$20 -> 35.656683 | V102: =T102*Standardisation_Parameters!$F$20+Standardisation_Parameters!$E$20 -> 46.227683 | W102: 49 | X102: 0.6063143 | Y102: 0.016455995 | Z102: 4 | AA102: 0.6497 | AB102: =AA102*Standardisation_Parameters!$F$20+Standardisation_Parameters!$E$20 -> 56.198989 | AC102: 4
A103: (0.52 : 0.95] | B103: 3 | C103: 0.54065152 | D103: 0.98123937 | E103: =C103*Standardisation_Parameters!$F$17+Standardisation_Parameters!$E$17 -> 0.57788475 | F103: =D103*Standardisation_Parameters!$F$17+Standardisation_Parameters!$E$17 -> 1.0113284 | G103: 79 | H103: -0.78706987 | J103: 4 | K103: -0.806 | L103: =K103*Standardisation_Parameters!$F$17+Standardisation_Parameters!$E$17 -> -0.74693055 | M103: 4 | R103: 4 | S103: 0.27857559 | T103: 1.3693329 | U103: =S103*Standardisation_Parameters!$F$20+Standardisation_Parameters!$E$20 -> 47.486683 | V103: =T103*Standardisation_Parameters!$F$20+Standardisation_Parameters!$E$20 -> 73.092683 | W103: 53 | X103: 0.68467015 | Y103: 0.89741902 | Z103: 5 | AA103: 0.7861 | AB103: =AA103*Standardisation_Parameters!$F$20+Standardisation_Parameters!$E$20 -> 59.401038 | AC103: 5
...

Sheet Low_Raw
A1: RAW 2011 DATA | B1: country | C1: em_dm | D1: iso_code | E1: dcpi_2011 | F1: dcpi_2009_2011 | G1: dcpi_2007_2011 | H1: rir_2011 | I1: rir_vol_2010_2011 | J1: xcs_2011 | K1: xcm_2011 | L1: growth_vol_2010_2011 | M1: real_gdp_2011 | N1: gdp_capita_2011 | O1: currency_vol_2011 | P1: atf_2011 | Q1: ic_2011 | R1: liq_2011 | S1: cab_2011 | T1: cab_fdi_2011 | U1: fdg_2011 | V1: dsr_2011 | W1: dt_2011 | X1: reer_2011 | Y1: fi_2011 | Z1: cof_2011 | AA1: pr_2011 | AB1: hdi_2011 | AC1: va_2011 | AD1: rol_2011 | AE1: db_2011 | AF1: gci_2011 | AG1: or_2011 | AH1: lr_2011 | AI1: sr_2011 | AJ1: dcpi_3yr_vol_2011 | AK1: dcpi_5yr_vol_2011 | AL1: nom_rir_2011 | AM1: nom_rir_vol_2011 | AN1: growth_vol_sh_2011 | AO1: ic_rc_2011 | AP1: liq_rc_2011 | AQ1: rc_2011 | AR1: rir_rir_vol_2011 | AS1: nir_nir_vol_2011 | AT1: growth_vol_gdp_capita_2011 | AU1: avg_cof_2011 | AV1: currency_vol_adj_2011 | AW1: liq_fx_adj_2011 | AX1: ddi_2011 | AY1: currency_vol_quart_2011 | AZ1: fdg_3year_2011 | BA1: fdg_5year_2011 | BB1: dsr_3year_2011 | BC1: dsr_5year_2011 | BD1: dt_5year_2011 | BE1: ic_rc_3year_2011 | BF1: ic_rc_5year_2011 | BG1: real_gdp_3year_2011 | BH1: real_gdp_5year_2011 | BI1: real_gdp_growth_1year_2011 | BJ1: real_gdp_growth_2year_2011 | BK1: real_gdp_growth_3year_2011 | BL1: real_gdp_growth_5year_2011 | BM1: macro_2011 | BN1: cab_3year_2011 | BO1: cab_actual_2011 | BP1: cab_actual_3year_2011 | BQ1: cab_change_2011 | BR1: cab_liq_rc_2011 | BS1: legal2011 | BT1: tax2011 | BU1: infra2011 | BV1: avgrol2011 | BW1: year | BX1: STD 2011 DATA | BY1: DB | BZ1: Quant | CA1: Qual | CB1: Full without Restriction | CC1: Full with Restriction | CD1: EIU | CF1: country | CG1: em_dm | CH1: iso_code | CI1: yhat_QUANT | CJ1: yhat_qualitative | CK1: eiu_score_std | CL1: yhat_Full1 | CM1: Y_Hat (AFTER) | CN1: db | CP1: country | CQ1: em_dm | CR1: iso_code | CT1: Row Num | CU1: Quant Score | CV1: Qual Score | CW1: EIU_Score | CX1: Fitted Score | CY1: Unstandardised EIU | CZ1: Unstandardised Fitted | DA1: Unstandardised Quant | DB1: Unstandardised Qual
B2: AFGHANISTAN | C2: LOW HUMAN DEVELOPMENT | D2: AFG | F2: -3.6985 | G2: 7.9105 | I2: 16.820837 | L2: 8.6707703 | P2: 3 | Q2: 7.3297637 | U2: 13.459759 | W2: -24.363053 | Y2: 3.8190928 | AA2: 7 | AB2: 0.398 | AC2: -1.4545945 | AD2: -1.8976236 | AE2: 84.153005 | AG2: 4.5 | AH2: 4 | AI2: 4.75 | AM2: 1.4924093 | AN2: 1.469189 | AO2: 21.989291 | AQ2: 3 | AR2: 163.46489 | AS2: 27.151403 | AX2: 0 | AY2: 2.0538148 | AZ2: 15.211538 | BA2: 16.721439 | BD2: -0.34318934 | BE2: 18.994713 | BF2: 16.477656 | BG2: 20.867 | BH2: 12.739 | BJ2: 5.367 | BK2: 11.6545 | BL2: 8.85375 | BM2: 9 | BS2: 83 | BT2: 38 | BU2: 84 | BV2: 68.333333 | BW2: 2011 | BY2: =(AE2-Standardisation_Parameters!$E$15)/Standardisation_Parameters!$F$15 -> 1.4515918 | BZ2: =VLOOKUP($D2,$CH:$CN,2,FALSE) -> #N/A | CA2: =VLOOKUP($D2,$CH:$CN,3,FALSE) -> #N/A | CB2: =VLOOKUP($D2,$CH:$CN,5,FALSE) -> #N/A | CC2: =VLOOKUP($D2,$CH:$CN,6,FALSE) -> #N/A | CD2: =VLOOKUP($D2,$CH:$CN,4,FALSE) -> #N/A | CF2: ANGOLA | CG2: LOW HUMAN DEVELOPMENT | CH2: AGO | CI2: 1.0000433 | CJ2: 1.2666655 | CK2: 0.61131204 | CL2: 1.2612366 | CM2: 1.2017588 | CN2: 1.0054 | CP2: ANGOLA | CQ2: LOW HUMAN DEVELOPMENT | CR2: AGO | CS2: AGO2011 | CT2: 7 | CU2: 1.0000433 | CV2: 1.2666655 | CW2: 0.61131204 | CX2: 1.2017545 | CY2: 54.888889 | CZ2: 64.758165 | DA2: 61.38655 | DB2: 65.843154
B3: ALGERIA | C3: MEDIUM HUMAN DEVELOPMENT | D3: DZA | E3: 4.531 | F3: 4.7276667 | G3: 4.8714 | H3: 3.469 | I3: 1.3044918 | J3: 98.303 | K3: 24.225 | L3: 0.42778499 | M3: 2.5 | N3: 5680 | O3: 3.9295193 | P3: 1 | Q3: 36.7 | R3: 0.89563399 | S3: 8.9 | T3: 10.291363 | U3: 1.9147501 | V3: 1.7 | W3: -51.241651 | X3: 3.113 | Y3: -7.4197348 | Z3: 1.06 | AA3: 5 | AB3: 0.698 | AC3: -1.0087942 | AD3: -0.75892415 | AE3: 78.142077 | AF3: 3.9584222 | AG3: 3.5 | AH3: 3 | AI3: 3.5 | AJ3: -0.19666667 | AK3: -1.2714 | AL3: 8 | AM3: 0 | AN3: 6.4050868 | AO3: 110.1 | AP3: 2.686902 | AQ3: 3 | AR3: 5.8428187 | AS3: 0 | AT3: 1180.4 | AU3: 0.18211576 | AV3: 5.2610142 | AW3: -0.99104366 | AX3: 10 | AY3: 3.8803788 | AZ3: 3.0328998 | BA3: 3.385049 | BB3: 1.9666667 | BC3: 1.1918 | BD3: -0.56189926 | BE3: 111.706 | BF3: 112.0188 | BG3: 2.7333333 | BH3: 2.74 | BI3: 1.7 | BJ3: 1.5 | BK3: 1.2333333 | BL3: 1.1156 | BM3: 5 | BN3: 5.568 | BO3: 8.9 | BP3: 5.568 | BQ3: 0.2501796 | BR3: 0.17345127 | BS3: 80 | BT3: 69 | BU3: 69 | BV3: 72.666667 | BW3: 2011 | BY3: =(AE3-Standardisation_Parameters!$E$15)/Standardisation_Parameters!$F$15 -> 1.2341468 | BZ3: =VLOOKUP($D3,$CH:$CN,2,FALSE) -> 0.31284052 | CA3: =VLOOKUP($D3,$CH:$CN,3,FALSE) -> 0.83406275 | CB3: =VLOOKUP($D3,$CH:$CN,5,FALSE) -> 0.68928127 | CC3: =VLOOKUP($D3,$CH:$CN,6,FALSE) -> 0.50387547 | CD3: =VLOOKUP($D3,$CH:$CN,4,FALSE) -> 1.0566858 | CF3: BURKINA FASO | CG3: LOW HUMAN DEVELOPMENT | CH3: BFA | CI3: 0.25120715 | CJ3: 0.51701512 | CK3: 0.35206462 | CL3: 0.40499109 | CM3: 0.29076185 | CN3: 0.8966 | CP3: BURKINA FASO | CQ3: LOW HUMAN DEVELOPMENT | CR3: BFA | CS3: BFA2011 | CT3: 12 | CU3: 0.25120715 | CV3: 0.51701512 | CW3: 0.35206462 | CX3: 0.29075932 | CY3: 50.555556 | CZ3: 49.530834 | DA3: 48.869718 | DB3: 53.312711
B4: ANGOLA | C4: LOW HUMAN DEVELOPMENT | D4: AGO | E4: 13.465 | F4: 13.945 | G4: 13.3116 | H4: 3.535 | I4: 3.1412234 | J4: 96.624 | K4: 43.063 | L4: 8.4735089 | M4: 3.4 | N4: 5330 | O4: 8.8121997 | P4: 3 | Q4: 7.7 | R4: 11.54617 | S4: 13.2 | T4: 24.034578 | U4: 17.360197 | V4: 8.9 | W4: -21.126399 | X4: -0.4 | Y4: 22.865688 | AA4: 5 | AB4: 0.486 | AC4: -1.1392457 | AD4: -1.2437801 | AE4: 93.442623 | AF4: 2.9614977 | AG4: 3.25 | AH4: 3.25 | AI4: 3.5 | AJ4: -0.48 | AK4: -2.0116 | AL4: 17 | AM4: 3.6504 | AN4: 0.9725841 | AO4: 23.1 | AP4: 34.638511 | AQ4: 3 | AR4: 17.122809 | AS4: 64.61208 | AT4: 1010 | AV4: 22.204027 | AW4: -0.8845383 | AX4: 0 | AY4: 8.3976008 | AZ4: 20.62602 | BA4: 19.841876 | BB4: 7.3666667 | BC4: 6.88 | BD4: -0.104812 | BE4: 18.311 | BF4: 17.0352 | BG4: 2.5206667 | BH4: 8.2412 | BI4: 0.5 | BJ4: 0.5 | BK4: -0.349 | BL4: 5.1674 | BM4: 7 | BN4: 4.056 | BO4: 13.2 | BP4: 4.056 | BQ4: 1.0359961 | BR4: 1.797397 | BS4: 75 | BT4: 38 | BU4: 72 | BV4: 61.666667 | BW4: 2011 | BY4: =(AE4-Standardisation_Parameters!$E$15)/Standardisation_Parameters!$F$15 -> 1.787643 | BZ4: =VLOOKUP($D4,$CH:$CN,2,FALSE) -> 1.0000433 | CA4: =VLOOKUP($D4,$CH:$CN,3,FALSE) -> 1.2666655 | CB4: =VLOOKUP($D4,$CH:$CN,5,FALSE) -> 1.2612366 | CC4: =VLOOKUP($D4,$CH:$CN,6,FALSE) -> 1.2017588 | CD4: =VLOOKUP($D4,$CH:$CN,4,FALSE) -> 0.61131204 | CF4: BANGLADESH | CG4: LOW HUMAN DEVELOPMENT | CH4: BGD | CI4: 0.81968458 | CJ4: 0.74080165 | CK4: 0.64454888 | CL4: 0.76586176 | CM4: 0.79554383 | CN4: 0.679 | CP4: BANGLADESH | CQ4: LOW HUMAN DEVELOPMENT | CR4: BGD | CS4: BGD2011 | CT4: 18 | CU4: 0.81968458 | CV4: 0.74080165 | CW4: 0.64454888 | CX4: 0.79554116 | CY4: 55.444444 | CZ4: 57.968288 | DA4: 58.371846 | DB4: 57.053314
B5: BANGLADESH | C5: LOW HUMAN DEVELOPMENT | D5: BGD | E5: 10.706 | F5: 8.0853333 | G5: 8.453 | H5: 2.294 | I5: 2.6446919 | J5: 65.834 | K5: 22.142 | L5: 0.35062444 | M5: 6.662 | N5: 649 | O5: 2.3183851 | P5: 3 | Q5: 3 | R5: 35.06669 | S5: 0.4 | T5: 1.4145141 | U5: 23.391782 | V5: 3.4 | W5: -12.178117 | X5: -0.4 | Y5: 65.941996 | Z5: 5 | AA5: 3 | AB5: 0.5 | AC5: -0.27560594 | AD5: -0.76846154 | AE5: 64.480874 | AF5: 3.7308962 | AG5: 3.5 | AH5: 3.25 | AI5: 3.75 | AJ5: 2.6206667 | AK5: 1.647 | AL5: 13 | AM5: 1.6006499 | AN5: 17.734075 | AO5: 9 | AP5: 105.20007 | AQ5: 3 | AR5: 18.229862 | AS5: 25.610398 | AT5: 40.3 | AU5: 0.85903661 | AV5: 7.6624431 | AW5: -0.6493331 | AX5: 0 | AY5: 2.35902 | AZ5: 24.989638 | BA5: 26.963199 | BB5: 3.345 | BC5: 3.6728 | BD5: 1.3441242 | BE5: 12.992 | BF5: 11.3946 | BG5: 6.1573333 | BH5: 6.218 | BI5: 16.542 | BJ5: 10.593 | BK5: 8.4933333 | BL5: 7.012 | BM5: 7 | BN5: 2.2933333 | BO5: 0.4 | BP5: 2.2933333 | BQ5: -0.91569767 | BR5: 1.1930196 | BS5: 68 | BT5: 38 | BU5: 81 | BV5: 62.333333 | BW5: 2011 | BY5: =(AE5-Standardisation_Parameters!$E$15)/Standardisation_Parameters!$F$15 -> 0.73995372 | BZ5: =VLOOKUP($D5,$CH:$CN,2,FALSE) -> 0.81968458 | CA5: =VLOOKUP($D5,$CH:$CN,3,FALSE) -> 0.74080165 | CB5: =VLOOKUP($D5,$CH:$CN,5,FALSE) -> 0.76586176 | CC5: =VLOOKUP($D5,$CH:$CN,6,FALSE) -> 0.79554383 | CD5: =VLOOKUP($D5,$CH:$CN,4,FALSE) -> 0.64454888 | CF5: BOLIVIA, PLURINATIONAL STATE OF | CG5: MEDIUM HUMAN DEVELOPMENT | CH5: BOL | CI5: 0.91507548 | CJ5: 1.1625483 | CK5: 1.22287 | CL5: 1.148124 | CM5: 1.0880821 | CN5: 0.8966 | CP5: BOLIVIA, PLURINATIONAL STATE OF | CQ5: MEDIUM HUMAN DEVELOPMENT | CR5: BOL | CS5: BOL2011 | CT5: 24 | CU5: 0.91507548 | CV5: 1.1625483 | CW5: 1.22287 | CX5: 1.0880781 | CY5: 65.111111 | CZ5: 62.858057 | DA5: 59.96631 | DB5: 64.102831
B6: BOLIVIA, PLURINATIONAL STATE OF | C6: MEDIUM HUMAN DEVELOPMENT | D6: BOL | E6: 9.883 | F6: 5.2436667 | G6: 7.6888 | H6: 1.017 | I6: 3.9485443 | J6: 14.103 | K6: 42.367 | L6: 1.021486 | M6: 4.4 | N6: 2220 | O6: 0.35199552 | P6: 3 | Q6: 17.6 | R6: 1.3984885 | S6: 4.1 | T6: 6.9101992 | U6: 25.961836 | V6: 4.8 | W6: -23.063166 | X6: 4.676 | Y6: 49.371658 | Z6: 1.8 | AA6: 6 | AB6: 0.663 | AC6: -0.088978093 | AD6: -1.0649306 | AE6: 80.327869 | AF6: 3.8158868 | AG6: 4 | AH6: 4.25 | AI6: 3.25 | AJ6: 4.6393333 | AK6: -3.1888 | AL6: 10.9 | AM6: 1.5772734 | AN6: 4.4241428 | AO6: 52.8 | AP6: 4.1954655 | AQ6: 3 | AR6: 16.414098 | AS6: 20.285314 | AT6: 275.5 | AU6: 0.30925318 | AV6: -11.001342 | AW6: -0.98601511 | AX6: 3 | AY6: 0.33870193 | AZ6: 29.017893 | BA6: 31.672397 | BB6: 7.669 | BC6: 9.1058 | BD6: 1.6782946 | BE6: 56.232 | BF6: 52.5978 | BG6: 3.9613333 | BH6: 4.5192 | BI6: 3.506 | BJ6: 2.9775 | BK6: 2.575 | BL6: 3.0028 | BM6: 7 | BN6: 4.532 | BO6: 4.1 | BP6: 4.532 | BQ6: -0.14805825 | BR6: 1.2830375 | BS6: 75 | BT6: 63 | BU6: 75 | BV6: 71 | BW6: 2011 | BY6: =(AE6-Standardisation_Parameters!$E$15)/Standardisation_Parameters!$F$15 -> 1.3132177 | BZ6: =VLOOKUP($D6,$CH:$CN,2,FALSE) -> 0.91507548 | CA6: =VLOOKUP($D6,$CH:$CN,3,FALSE) -> 1.1625483 | CB6: =VLOOKUP($D6,$CH:$CN,5,FALSE) -> 1.148124 | CC6: =VLOOKUP($D6,$CH:$CN,6,FALSE) -> 1.0880821 | CD6: =VLOOKUP($D6,$CH:$CN,4,FALSE) -> 1.22287 | CF6: BOTSWANA | CG6: MEDIUM HUMAN DEVELOPMENT | CH6: BWA | CI6: 0.10257794 | CJ6: -0.23900037 | CK6: -0.53868291 | CL6: -0.27341966 | CM6: -0.21853939 | CN6: 0.4614 | CP6: BOTSWANA | CQ6: MEDIUM HUMAN DEVELOPMENT | CR6: BWA | CS6: BWA2011 | CT6: 30 | CU6: 0.10257794 | CV6: -0.23900037 | CW6: -0.53868291 | CX6: -0.21853953 | CY6: 35.666667 | CZ6: 41.017879 | DA6: 46.385373 | DB6: 40.675875
B7: BOTSWANA | C7: MEDIUM HUMAN DEVELOPMENT | D7: BWA | E7: 8.5 | F7: 7.856 | G7: 8.6532 | H7: 2.5 | I7: 2.5058413 | J7: 69.8 | K7: 55.275 | L7: 4.7294234 | M7: 5.4 | N7: 8450 | O7: 0.36897065 | P7: 1 | Q7: 13.5 | R7: 5.5360353 | S7: -2.8 | T7: -0.92586023 | U7: 11.663119 | V7: 2.1 | W7: -17.257694 | X7: 14.9 | Y7: 9.3515395 | Z7: 9.5 | AA7: 3 | AB7: 0.633 | AC7: 0.43229165 | AD7: 0.66341102 | AE7: 28.415301 | AF7: 4.0470745 | AG7: 2 | AH7: 2.25 | AI7: 1.5 | AJ7: 0.644 | AK7: -2.3532 | AL7: 11 | AM7: 2.5826885 | AN7: 0.64798597 | AO7: 40.5 | AP7: 16.608106 | AQ7: 3 | AR7: 22.905895 | AS7: 41.891208 | AT7: 936.9 | AU7: 1.6321696 | AV7: 9.0604027 | AW7: -0.94463965 | AX7: 3 | AY7: 0.52256681 | AZ7: 12.419635 | BA7: 8.7632766 | BB7: 2.1186667 | BC7: 1.6382 | BD7: -0.18565311 | BE7: 50.622 | BF7: 58.842 | BG7: 2.5543333 | BH7: 3.0646 | BI7: 3.8 | BJ7: 4.662 | BK7: 1.0113333 | BL7: 1.613 | BM7: 3 | BN7: -4.2013333 | BO7: -2.8 | BP7: -4.2013333 | BQ7: -0.5407807 | BR7: -0.82102777 | BS7: 40 | BT7: 25 | BU7: 38 | BV7: 34.333333 | BW7: 2011 | BY7: =(AE7-Standardisation_Parameters!$E$15)/Standardisation_Parameters!$F$15 -> -0.56471601 | BZ7: =VLOOKUP($D7,$CH:$CN,2,FALSE) -> 0.10257794 | CA7: =VLOOKUP($D7,$CH:$CN,3,FALSE) -> -0.23900037 | CB7: =VLOOKUP($D7,$CH:$CN,5,FALSE) -> -0.27341966 | CC7: =VLOOKUP($D7,$CH:$CN,6,FALSE) -> -0.21853939 | CD7: =VLOOKUP($D7,$CH:$CN,4,FALSE) -> -0.53868291 | CF7: CENTRAL AFRICAN REPUBLIC | CG7: LOW HUMAN DEVELOPMENT | CH7: CAF | CI7: 0.95445381 | CJ7: 1.446723 | CK7: 1.0367437 | CL7: 1.3980963 | CM7: 1.2683905 | CN7: 1.0054 | CP7: CENTRAL AFRICAN REPUBLIC | CQ7: LOW HUMAN DEVELOPMENT | CR7: CAF | CS7: CAF2011 | CT7: 33 | CU7: 0.95445381 | CV7: 1.446723 | CW7: 1.0367437 | CX7: 1.2683856 | CY7: 62 | CZ7: 65.871906 | DA7: 60.624521 | DB7: 68.852825
B8: BURKINA FASO | C8: LOW HUMAN DEVELOPMENT | D8: BFA | E8: 2.7 | F8: 1.5146667 | G8: 2.9946 | K8: 7.769 | L8: 1.8687568 | M8: 5.6 | N8: 597 | O8: 17.115318 | P8: 3 | Q8: 4.5 | R8: 4.4264078 | S8: -3.5 | U8: 22.680158 | V8: 3.3 | W8: 15.816991 | X8: -1.5 | Y8: 16.442008 | Z8: 3.3 | AA8: 5 | AB8: 0.331 | AC8: -0.24020444 | AD8: -0.21392659 | AE8: 82.513661 | AF8: 3.2529644 | AG8: 3.75 | AH8: 3.25 | AI8: 3 | AJ8: 1.1853333 | AK8: 0.0054 | AN8: 2.7287661 | AO8: 13.5 | AP8: 13.279223 | AQ8: 3 | AT8: 43 | AU8: 0.56696416 | AV8: -1.5440256 | AW8: -0.95573592 | AX8: 1 | AY8: 26.341653 | AZ8: 21.383601 | BA8: 20.470982 | BB8: 3.7 | BC8: 3.96 | BD8: -0.24944125 | BE8: 17.8 | BF8: 17.8548 | BG8: 5.5666667 | BH8: 5.0994 | BI8: 1.1 | BJ8: 2.9 | BK8: 1.9 | BL8: 1.798 | BM8: 4 | BN8: -3.854 | BO8: -3.5 | BP8: -3.854 | BQ8: -0.032693306 | BR8: -8.6530834 | BS8: 63 | BT8: 25 | BU8: 69 | BV8: 52.333333 | BW8: 2011 | BY8: =(AE8-Standardisation_Parameters!$E$15)/Standardisation_Parameters!$F$15 -> 1.3922886 | BZ8: =VLOOKUP($D8,$CH:$CN,2,FALSE) -> 0.25120715 | CA8: =VLOOKUP($D8,$CH:$CN,3,FALSE) -> 0.51701512 | CB8: =VLOOKUP($D8,$CH:$CN,5,FALSE) -> 0.40499109 | CC8: =VLOOKUP($D8,$CH:$CN,6,FALSE) -> 0.29076185 | CD8: =VLOOKUP($D8,$CH:$CN,4,FALSE) -> 0.35206462 | CF8: CHINA | CG8: MEDIUM HUMAN DEVELOPMENT | CH8: CHN | CI8: -0.060995903 | CJ8: 0.47600229 | CK8: 0.21911723 | CL8: 0.27537403 | CM8: 0.057838697 | CN8: 0.5702 | CP8: CHINA | CQ8: MEDIUM HUMAN DEVELOPMENT | CR8: CHN | CS8: CHN2011 | CT8: 39 | CU8: -0.060995903 | CV8: 0.47600229 | CW8: 0.21911723 | CX8: 0.057835966 | CY8: 48.333333 | CZ8: 45.637509 | DA8: 43.651229 | DB8: 52.62718
B9: CAMBODIA | C9: MEDIUM HUMAN DEVELOPMENT | D9: KHM | E9: 5.5 | F9: 2.945 | G9: 8.3 | H9: 9.7 | I9: 9.6846183 | J9: 71.6 | K9: 37.008 | L9: 3.6402514 | M9: 6.1 | N9: 829 | O9: 60.192792 | P9: 4 | Q9: 5.3 | R9: 0.13264163 | S9: -8.7 | T9: -2.0638298 | U9: 5.6997636 | V9: 0.5 | W9: 113.69492 | X9: 0.2 | Y9: 22.735256 | AA9: 6 | AB9: 0.523 | AC9: -0.87283659 | AD9: -1.0876105 | AE9: 75.409836 | AF9: 3.8531476 | AG9: 3.5 | AH9: 3.25 | AI9: 2.75 | AJ9: 2.555 | AK9: -4.5 | AL9: 15.2 | AM9: 0.37714149 | AN9: 1.5920329 | AO9: 15.9 | AP9: 0.3979249 | AQ9: 3 | AR9: 82.387048 | AS9: 6.1002635 | AT9: 100 | AV9: 0.05752557 | AW9: -0.99867358 | AX9: 2 | AY9: 64.448018 | AZ9: 4.2628591 | BA9: 3.7610402 | BB9: 0.243 | BC9: 0.2736 | BD9: 2.4942773 | BE9: 16.853 | BF9: 15.063 | BG9: 4.024 | BH9: 5.7954 | BI9: 4.8 | BJ9: 4.75 | BK9: 2.8136667 | BL9: 4.5956 | BM9: 6 | BN9: -8.552 | BO9: -8.7 | BP9: -8.552 | BQ9: 0.080799813 | BR9: -7.6892354 | BS9: 63 | BT9: 31 | BU9: 78 | BV9: 57.333333 | BW9: 2011 | BY9: =(AE9-Standardisation_Parameters!$E$15)/Standardisation_Parameters!$F$15 -> 1.1353082 | BZ9: =VLOOKUP($D9,$CH:$CN,2,FALSE) -> 0.79299413 | CA9: =VLOOKUP($D9,$CH:$CN,3,FALSE) -> 1.0008626 | CB9: =VLOOKUP($D9,$CH:$CN,5,FALSE) -> 0.9754801 | CC9: =VLOOKUP($D9,$CH:$CN,6,FALSE) -> 0.91821124 | CD9: =VLOOKUP($D9,$CH:$CN,4,FALSE) -> 1.0433911 | CF9: COTE D'IVOIRE | CG9: LOW HUMAN DEVELOPMENT | CH9: CIV | CI9: 0.89824532 | CJ9: 1.446723 | CK9: 0.81738049 | CL9: 1.3809432 | CM9: 1.2304498 | CN9: 1.0054 | CP9: COTE D'IVOIRE | CQ9: LOW HUMAN DEVELOPMENT | CR9: CIV | CS9: CIV2011 | CT9: 45 | CU9: 0.89824532 | CV9: 1.446723 | CW9: 0.81738049 | CX9: 1.2304449 | CY9: 58.333333 | CZ9: 65.237725 | DA9: 59.684993 | DB9: 68.852825
B10: CAMEROON | C10: LOW HUMAN DEVELOPMENT | D10: CMR | E10: 2.9 | F10: 2.4063333 | G10: 2.6956 | H10: 11.1 | I10: 1.8718983 | J10: 35.657 | K10: 14.828 | L10: 0.77653075 | M10: 4.1 | N10: 1280 | O10: 17.115615 | P10: 3 | Q10: 5 | R10: 0.79222402 | S10: -5.2 | T10: -3.1924271 | U10: 12.056107 | V10: 6.5 | W10: -9.2151446 | X10: -1.621 | Y10: 8.9983205 | Z10: 4 | AA10: 6 | AB10: 0.482 | AC10: -1.0617968 | AD10: -1.0436544 | AE10: 90.163934 | AF10: 3.6068585 | AG10: 3.75 | AH10: 3.5 | AI10: 3.25 | AJ10: 0.49366667 | AK10: -0.0956 | AL10: 14 | AM10: 0.4472136 | AN10: 4.0436261 | AO10: 15 | AP10: 2.376672 | AQ10: 3 | AR10: 26.354456 | AS10: 6.7082039 | AT10: 120 | AU10: 0.68722929 | AV10: -1.5440149 | AW10: -0.99207776 | AX10: 10 | AY10: 26.341653 | AZ10: 12.714947 | BA10: 12.855149 | BB10: 6.345 | BC10: 6.6774 | BD10: -0.062700081 | BE10: 18.822 | BF10: 17.5704 | BG10: 3.1 | BH10: 3.14 | BI10: 1.8 | BJ10: 1.4 | BK10: 0.85533333 | BL10: 0.8922 | BM10: 7 | BN10: -4.6476667 | BO10: -5.2 | BP10: -4.6476667 | BQ10: 0.32274259 | BR10: -4.7295774 | BS10: 70 | BT10: 44 | BU10: 66 | BV10: 60 | BW10: 2011 | BY10: =(AE10-Standardisation_Parameters!$E$15)/Standardisation_Parameters!$F$15 -> 1.6690367 | BZ10: =VLOOKUP($D10,$CH:$CN,2,FALSE) -> 0.64775859 | CA10: =VLOOKUP($D10,$CH:$CN,3,FALSE) -> 1.1625483 | CB10: =VLOOKUP($D10,$CH:$CN,5,FALSE) -> 1.0665471 | CC10: =VLOOKUP($D10,$CH:$CN,6,FALSE) -> 0.90764347 | CD10: =VLOOKUP($D10,$CH:$CN,4,FALSE) -> 0.8373226 | CF10: CAMEROON | CG10: LOW HUMAN DEVELOPMENT | CH10: CMR | CI10: 0.64775859 | CJ10: 1.1625483 | CK10: 0.8373226 | CL10: 1.0665471 | CM10: 0.90764347 | CN10: 1.0054 | CP10: CAMEROON | CQ10: LOW HUMAN DEVELOPMENT | CR10: CMR | CS10: CMR2011 | CT10: 51 | CU10: 0.64775859 | CV10: 1.1625483 | CW10: 0.8373226 | CX10: 0.90763919 | CY10: 58.666667 | CZ10: 59.842012 | DA10: 55.498095 | DB10: 64.102831
B11: CHINA | C11: MEDIUM HUMAN DEVELOPMENT | D11: CHN | E11: 5.527 | F11: 2.6566667 | G11: 3.7426 | H11: 1.073 | I11: 2.4609159 | J11: 12.44 | K11: 17.98 | L11: 2.103768 | M11: 9.153 | N11: 5340 | O11: 0.42249831 | P11: 1 | Q11: 20.313 | R11: 13.457009 | S11: 2.9 | T11: 4.863675 | U11: 9.319016 | V11: 1.7 | W11: 9.3082485 | X11: 2.453 | Y11: 146.3911 | Z11: 5.3 | AA11: 4 | AB11: 0.687 | AC11: -1.6495012 | AD11: -0.34683992 | AE11: 47.540984 | AF11: 4.8977891 | AG11: 3 | AH11: 3.25 | AI11: 2.5 | AJ11: 2.8703333 | AK11: -0.0426 | AL11: 6.6 | AM11: 0.92994624 | AN11: 4.9960832 | AO11: 60.939 | AP11: 40.371027 | AQ11: 3 | AR11: 6.5312709 | AS11: 6.9466984 | AT11: 900 | AU11: 0.91057881 | AV11: -15.065008 | AW11: -0.86542991 | AX11: 2 | AY11: 0.39995675 | AZ11: 9.0877007 | BA11: 9.2641946 | BB11: 2.5273333 | BC11: 2.335 | BD11: 0.11139379 | BE11: 69.158 | BF11: 63.579 | BG11: 9.5843333 | BH11: 10.5106 | BI11: 8.5 | BJ11: 9.1 | BK11: 8.9333333 | BL11: 9.88 | BM11: 3 | BN11: 4.4313333 | BO11: 2.9 | BP11: 4.4313333 | BQ11: -0.52873477 | BR11: 0.40642665 | BS11: 60 | BT11: 38 | BU11: 47 | BV11: 48.333333 | BW11: 2011 | BY11: =(AE11-Standardisation_Parameters!$E$15)/Standardisation_Parameters!$F$15 -> 0.1271543 | BZ11: =VLOOKUP($D11,$CH:$CN,2,FALSE) -> -0.060995903 | CA11: =VLOOKUP($D11,$CH:$CN,3,FALSE) -> 0.47600229 | CB11: =VLOOKUP($D11,$CH:$CN,5,FALSE) -> 0.27537403 | CC11: =VLOOKUP($D11,$CH:$CN,6,FALSE) -> 0.057838697 | CD11: =VLOOKUP($D11,$CH:$CN,4,FALSE) -> 0.21911723 | CF11: CONGO, THE DEMOCRATIC REP OF THE | CG11: LOW HUMAN DEVELOPMENT | CH11: COD | CI11: 1.3774404 | CJ11: 1.5390307 | CK11: 1.9208439 | CL11: 1.6044731 | CM11: 1.603841 | CN11: 1.0054 | CP11: CONGO, THE DEMOCRATIC REP OF THE | CQ11: LOW HUMAN DEVELOPMENT | CR11: COD | CS11: COD2011 | CT11: 54 | CU11: 1.3774404 | CV11: 1.5390307 | CW11: 1.9208439 | CX11: 1.6038363 | CY11: 76.777778 | CZ11: 71.478981 | DA11: 67.694762 | DB11: 70.395752
B12: CONGO | C12: MEDIUM HUMAN DEVELOPMENT | D12: COG | E12: 6 | F12: 5.3453333 | G12: 5.2052 | H12: 9.3 | I12: 1.6808995 | K12: 37.601 | L12: 4.0141774 | M12: 5.1 | N12: 4100 | O12: 17.115318 | P12: 5 | Q12: 9.2 | R12: 26.64115 | S12: 12.3 | T12: 24.128538 | U12: 31.942807 | V12: 1.9 | W12: -23.648499 | X12: 1.3 | Y12: -16.356396 | AA12: 7 | AB12: 0.533 | AC12: -1.0313878 | AD12: -1.1330083 | AE12: 98.360656 | AG12: 4 | AH12: 4 | AI12: 3.75 | AJ12: 0.65466667 | AK12: -0.1052 | AL12: 15.3 | AM12: 0.17888544 | AN12: 1.2660128 | AO12: 27.6 | AP12: 79.92345 | AQ12: 3 | AR12: 20.749024 | AS12: 2.6832816 | AT12: 850 | AV12: -1.5440256 | AW12: -0.7335885 | AX12: 8 | AY12: 26.341653 | AZ12: 35.425552 | BA12: 45.507584 | BB12: 2.9303333 | BC12: 2.5262 | BD12: 0.24002714 | BE12: 27.8 | BF12: 24.2124 | BG12: 7.1333333 | BH12: 5.082 | BI12: 2.1 | BJ12: 4.054 | BK12: 4.238 | BL12: 2.2228 | BM12: 7 | BN12: 3.3 | BO12: 12.3 | BP12: 3.3 | BQ12: 2.3636364 | BR12: 7.076346 | BS12: 75 | BT12: 56 | BU12: 75 | BV12: 68.666667 | BW12: 2011 | BY12: =(AE12-Standardisation_Parameters!$E$15)/Standardisation_Parameters!$F$15 -> 1.9655526 | BZ12: =VLOOKUP($D12,$CH:$CN,2,FALSE) -> 1.0595071 | CA12: =VLOOKUP($D12,$CH:$CN,3,FALSE) -> 1.3030473 | CB12: =VLOOKUP($D12,$CH:$CN,5,FALSE) -> 1.3098476 | CC12: =VLOOKUP($D12,$CH:$CN,6,FALSE) -> 1.261578 | CD12: =VLOOKUP($D12,$CH:$CN,4,FALSE) -> 1.023449 | CF12: CONGO | CG12: MEDIUM HUMAN DEVELOPMENT | CH12: COG | CI12: 1.0595071 | CJ12: 1.3030473 | CK12: 1.023449 | CL12: 1.3098476 | CM12: 1.261578 | CN12: 1.0054 | CP12: CONGO | CQ12: MEDIUM HUMAN DEVELOPMENT | CR12: COG | CS12: COG2011 | CT12: 60 | CU12: 1.0595071 | CV12: 1.3030473 | CW12: 1.023449 | CX12: 1.2615737 | CY12: 61.777778 | CZ12: 65.758045 | DA12: 62.380491 | DB12: 66.451277
B13: CONGO, THE DEMOCRATIC REP OF THE | C13: LOW HUMAN DEVELOPMENT | D13: COD | E13: 17 | F13: 28.733333 | G13: 24.0892 | H13: 28 | I13: 5.2939387 | L13: 2.5955732 | M13: 6.5 | N13: 240 | O13: 195.92422 | P13: 4 | Q13: 1.3332604 | R13: 80.701665 | S13: -2.5 | U13: 88.555888 | V13: 2.1 | W13: -21.222599 | Y13: 0.98077144 | Z13: 17 | AA13: 7 | AB13: 0.286 | AC13: -1.4173798 | AD13: -1.611951 | AE13: 96.174863 | AG13: 4.5 | AH13: 4.5 | AI13: 4.5 | AJ13: -11.733333 | AK13: -9.0892 | AL13: 45 | AM13: 9.3583533 | AN13: 2.5504964 | AO13: 3.9997812 | AP13: 242.105 | AQ13: 3 | AR13: 159.19932 | AS13: 440.0017 | AT13: 49 | AU13: 2.9207245 | AV13: 79.441118 | AW13: -19.298335 | AX13: 0 | AY13: 178.4298 | AZ13: 100.8399 | BA13: 106.77504 | BB13: 9.5563333 | BC13: 7.552 | BD13: -0.12718027 | BE13: 4.7134161 | BF13: 3.0804585 | BG13: 5.4666667 | BH13: 6.62 | BI13: 4.052 | BJ13: 4.16 | BK13: 2.773 | BL13: 3.0062 | BM13: 7 | BN13: -6.7333333 | BO13: -2.5 | BP13: -6.7333333 | BQ13: -0.65346535 | BR13: -3.4961098 | BS13: 88 | BT13: 75 | BU13: 100 | BV13: 87.666667 | BW13: 2011 | BY13: =(AE13-Standardisation_Parameters!$E$15)/Standardisation_Parameters!$F$15 -> 1.8864817 | BZ13: =VLOOKUP($D13,$CH:$CN,2,FALSE) -> 1.3774404 | CA13: =VLOOKUP($D13,$CH:$CN,3,FALSE) -> 1.5390307 | CB13: =VLOOKUP($D13,$CH:$CN,5,FALSE) -> 1.6044731 | CC13: =VLOOKUP($D13,$CH:$CN,6,FALSE) -> 1.603841 | CD13: =VLOOKUP($D13,$CH:$CN,4,FALSE) -> 1.9208439 | CF13: DOMINICAN REPUBLIC | CG13: MEDIUM HUMAN DEVELOPMENT | CH13: DOM | CI13: 0.43314613 | CJ13: 0.80594214 | CK13: 0.71102258 | CL13: 0.70244789 | CM13: 0.5698694 | CN13: 0.679 | CP13: DOMINICAN REPUBLIC | CQ13: MEDIUM HUMAN DEVELOPMENT | CR13: DOM | CS13: DOM2011 | CT13: 66 | CU13: 0.43314613 | CV13: 0.80594214 | CW13: 0.71102258 | CX13: 0.5698661 | CY13: 56.555556 | CZ13: 54.196118 | DA13: 51.910837 | DB13: 58.142141
B14: COTE D'IVOIRE | C14: LOW HUMAN DEVELOPMENT | D14: CIV | E14: 5.1 | F14: 2.388 | G14: 2.7982 | H14: -0.8 | I14: 1.935853 | J14: 30.7 | K14: 10.04 | L14: 3.8826785 | M14: -5.9 | N14: 1050 | O14: 17.132068 | P14: 5 | Q14: 4.6 | R14: 4.172093 | S14: -0.8 | T14: 0.69217541 | U14: 49.730868 | V14: 4.3 | W14: -3.7458973 | X14: 1.6 | Y14: 25.138534 | Z14: 4.3 | AA14: 6 | AB14: 0.4 | AC14: -1.1170357 | AD14: -1.2179363 | AE14: 92.896175 | AF14: 3.3715417 | AG14: 4 | AH14: 3.75 | AI14: 4.5 | AJ14: 2.712 | AK14: -0.3982 | AL14: 4.3 | AM14: 0.2236068 | AN14: 0.23818608 | AO14: 13.8 | AP14: 12.516279 | AQ14: 3 | AR14: 4.6537905 | AS14: 0.96150923 | AT14: 0 | AU14: 0.73877149 | AV14: -1.6838108 | AW14: -0.95827907 | AX14: 7 | AY14: 26.341653 | AZ14: 51.081366 | BA14: 55.548764 | BB14: 6.039 | BC14: 8.0698 | BD14: -0.56785058 | BE14: 13.503 | BF14: 11.8812 | BG14: 0.23166667 | BH14: 0.9248 | BI14: -6.9 | BJ14: -3.15 | BK14: -1.7043333 | BL14: -1.1584 | BM14: 7 | BN14: 2.9583333 | BO14: -0.8 | BP14: 2.9583333 | BQ14: -1.0478873 | BR14: -0.43297674 | BS14: 75 | BT14: 63 | BU14: 56 | BV14: 64.666667 | BW14: 2011 | BY14: =(AE14-Standardisation_Parameters!$E$15)/Standardisation_Parameters!$F$15 -> 1.7678753 | BZ14: =VLOOKUP($D14,$CH:$CN,2,FALSE) -> 0.89824532 | CA14: =VLOOKUP($D14,$CH:$CN,3,FALSE) -> 1.446723 | CB14: =VLOOKUP($D14,$CH:$CN,5,FALSE) -> 1.3809432 | CC14: =VLOOKUP($D14,$CH:$CN,6,FALSE) -> 1.2304498 | CD14: =VLOOKUP($D14,$CH:$CN,4,FALSE) -> 0.81738049 | CF14: ALGERIA | CG14: MEDIUM HUMAN DEVELOPMENT | CH14: DZA | CI14: 0.31284052 | CJ14: 0.83406275 | CK14: 1.0566858 | CL14: 0.68928127 | CM14: 0.50387547 | CN14: 0.8966 | CP14: ALGERIA | CQ14: MEDIUM HUMAN DEVELOPMENT | CR14: DZA | CS14: DZA2011 | CT14: 72 | CU14: 0.31284052 | CV14: 0.83406275 | CW14: 1.0566858 | CX14: 0.50387194 | CY14: 62.333333 | CZ14: 53.093022 | DA14: 49.899923 | DB14: 58.612178
B15: DOMINICAN REPUBLIC | C15: MEDIUM HUMAN DEVELOPMENT | D15: DOM | E15: 8.46 | F15: 5.4106667 | G15: 6.6036 | H15: 6.04 | I15: 4.4002989 | J15: 62.449 | K15: 52.455 | L15: 2.216496 | M15: 4.1 | N15: 5780 | O15: 1.8947289 | P15: 1 | Q15: 1.7 | R15: 73.249183 | S15: -10.2 | T15: -6.4398008 | U15: 26.333103 | V15: 8 | W15: 12.991149 | X15: 2.816 | Y15: 39.630333 | Z15: 7.5 | AA15: 6 | AB15: 0.689 | AC15: 0.052127646 | AD15: -0.80715729 | AE15: 57.377049 | AF15: 3.7263502 | AG15: 2.75 | AH15: 2.75 | AI15: 2.5 | AJ15: 3.0493333 | AK15: -1.6036 | AL15: 14.5 | AM15: 3.0535995 | AN15: 2.6199911 | AO15: 5.1 | AP15: 219.74755 | AQ15: 3 | AR15: 42.634496 | AS15: 48.33848 | AT15: 420 | AU15: 1.2885549 | AV15: 14.57003 | AW15: -0.26750817 | AX15: 3 | AY15: 1.7807783 | AZ15: 25.10401 | BA15: 24.455866 | BB15: 8.5383333 | BC15: 8.625 | BD15: 0.15109828 | BE15: 6.575 | BF15: 6.0612 | BG15: 5.1016667 | BH15: 5.8072 | BI15: 3.1 | BJ15: 4.613 | BK15: 3.8113333 | BL15: 4.5204 | BM15: 5 | BN15: -7.9336667 | BO15: -10.2 | BP15: -7.9336667 | BQ15: 0.20179824 | BR15: -8.4430419 | BS15: 60 | BT15: 38 | BU15: 63 | BV15: 53.666667 | BW15: 2011 | BY15: =(AE15-Standardisation_Parameters!$E$15)/Standardisation_Parameters!$F$15 -> 0.48297332 | BZ15: =VLOOKUP($D15,$CH:$CN,2,FALSE) -> 0.43314613 | CA15: =VLOOKUP($D15,$CH:$CN,3,FALSE) -> 0.80594214 | CB15: =VLOOKUP($D15,$CH:$CN,5,FALSE) -> 0.70244789 | CC15: =VLOOKUP($D15,$CH:$CN,6,FALSE) -> 0.5698694 | CD15: =VLOOKUP($D15,$CH:$CN,4,FALSE) -> 0.71102258 | CF15: EGYPT | CG15: MEDIUM HUMAN DEVELOPMENT | CH15: EGY | CI15: 0.55566191 | CJ15: 0.47178249 | CK15: 0.41853832 | CL15: 0.46002552 | CM15: 0.4717993 | CN15: 0.679 | CP15: EGYPT | CQ15: MEDIUM HUMAN DEVELOPMENT | CR15: EGY | CS15: EGY2011 | CT15: 78 | CU15: 0.55566191 | CV15: 0.47178249 | CW15: 0.41853832 | CX15: 0.47179725 | CY15: 51.666667 | CZ15: 52.556892 | DA15: 53.958694 | DB15: 52.556646
B16: EGYPT | C16: MEDIUM HUMAN DEVELOPMENT | D16: EGY | E16: 10.151 | F16: 11.017667 | G16: 12.174 | H16: 1.849 | I16: 3.4819009 | J16: 43.102 | K16: 8.26 | L16: 2.201001 | M16: 1.776 | N16: 2680 | O16: 0.18664151 | P16: 2 | Q16: 3.5 | R16: 30.095687 | S16: -3 | T16: -3.2973172 | U16: 14.792947 | V16: 7.8 | W16: -16.814712 | X16: 5 | Y16: 69.422034 | Z16: 12.5 | AA16: 6 | AB16: 0.644 | AC16: -1.2043639 | AD16: -0.10896561 | AE16: 59.016393 | AF16: 3.879084 | AG16: 2.75 | AH16: 3 | AI16: 2.75 | AJ16: -0.86666667 | AK16: -1.174 | AL16: 12 | AM16: 0.57913876 | AN16: 2.3481135 | AO16: 10.5 | AP16: 90.287061 | AQ16: 3 | AR16: 10.536232 | AS16: 7.2438676 | AT16: 141.3 | AU16: 2.1475915 | AV16: 5.3542254 | AW16: -0.69904313 | AX16: 0 | AY16: 0.18748718 | AZ16: 16.274954 | BA16: 18.957194 | BB16: 6.042 | BC16: 5.361 | BD16: 0.075877318 | BE16: 18.178 | BF16: 18.7152 | BG16: 3.8656667 | BH16: 5.1682 | BI16: 0.014 | BJ16: 1.667 | BK16: 2.0606667 | BL16: 3.3264 | BM16: 5 | BN16: -2.269 | BO16: -3 | BP16: -2.269 | BQ16: 0.34508594 | BR16: 0.31543392 | BS16: 40 | BT16: 31 | BU16: 47 | BV16: 39.333333 | BW16: 2011 | BY16: =(AE16-Standardisation_Parameters!$E$15)/Standardisation_Parameters!$F$15 -> 0.54227649 | BZ16: =VLOOKUP($D16,$CH:$CN,2,FALSE) -> 0.55566191 | CA16: =VLOOKUP($D16,$CH:$CN,3,FALSE) -> 0.47178249 | CB16: =VLOOKUP($D16,$CH:$CN,5,FALSE) -> 0.46002552 | CC16: =VLOOKUP($D16,$CH:$CN,6,FALSE) -> 0.4717993 | CD16: =VLOOKUP($D16,$CH:$CN,4,FALSE) -> 0.41853832 | CF16: ETHIOPIA | CG16: LOW HUMAN DEVELOPMENT | CH16: ETH | CI16: 1.3603508 | CJ16: 1.0910148 | CK16: 0.93703315 | CL16: 1.2241093 | CM16: 1.3499454 | CN16: 0.5702 | CP16: ETHIOPIA | CQ16: LOW HUMAN DEVELOPMENT | CR16: ETH | CS16: ETH2011 | CT16: 84 | CU16: 1.3603508 | CV16: 1.0910148 | CW16: 0.93703315 | CX16: 1.3499421 | CY16: 60.333333 | CZ16: 67.235128 | DA16: 67.409108 | DB16: 62.907144
B17: EL SALVADOR | C17: MEDIUM HUMAN DEVELOPMENT | D17: SLV | E17: 5.127 | F17: 2.4543333 | G17: 3.7298 | H17: 1.073 | I17: 3.2148423 | J17: 24.786 | K17: 48.033 | L17: 2.4207535 | M17: 1.5 | N17: 3610 | O17: 0 | P17: 1 | Q17: 2.8 | R17: 55.268182 | S17: -5.4 | T17: -2.4677003 | U17: 54.262675 | V17: 9.5 | W17: 10.980115 | X17: -2.667 | Y17: 45.110805 | Z17: 2.6 | AA17: 4 | AB17: 0.674 | AC17: 0.037775842 | AD17: -0.87121226 | AE17: 61.202186 | AF17: 3.8890464 | AG17: 3.5 | AH17: 3 | AI17: 3.75 | AJ17: 2.6726667 | AK17: -0.5298 | AL17: 6.2 | AM17: 1.1069462 | AN17: 0.435319 | AO17: 8.4 | AP17: 165.80455 | AQ17: 3 | AR17: 10.39037 | AS17: 8.6452502 | AT17: 222.1 | AU17: 0.44669904 | AV17: 0 | AW17: -0.44731818 | AX17: 10 | AY17: 0 | AZ17: 51.978985 | BA17: 50.835914 | BB17: 11.861667 | BC17: 11.5516 | BD17: 0.064649931 | BE17: 11.022 | BF17: 9.9636 | BG17: 0.028333333 | BH17: 1.0538 | BI17: 0.819 | BJ17: 0.8465 | BK17: -0.63733333 | BL17: 0.4392 | BM17: 4 | BN17: -3.0666667 | BO17: -5.4 | BP17: -3.0666667 | BQ17: 1.0017391 | BR17: -5.7055909 | BS17: 58 | BT17: 31 | BU17: 56 | BV17: 48.333333 | BW17: 2011 | BY17: =(AE17-Standardisation_Parameters!$E$15)/Standardisation_Parameters!$F$15 -> 0.62134738 | BZ17: =VLOOKUP($D17,$CH:$CN,2,FALSE) -> 0.20464658 | CA17: =VLOOKUP($D17,$CH:$CN,3,FALSE) -> 0.80721152 | CB17: =VLOOKUP($D17,$CH:$CN,5,FALSE) -> 0.63377979 | CC17: =VLOOKUP($D17,$CH:$CN,6,FALSE) -> 0.41631915 | CD17: =VLOOKUP($D17,$CH:$CN,4,FALSE) -> 0.29223829 | CF17: GABON | CG17: MEDIUM HUMAN DEVELOPMENT | CH17: GAB | CI17: 1.0968192 | CJ17: 0.76362754 | CK17: 0.33876988 | CL17: 0.86954809 | CM17: 0.99495736 | CN17: 1.0054 | CP17: GABON | CQ17: MEDIUM HUMAN DEVELOPMENT | CR17: GAB | CS17: GAB2011 | CT17: 90 | CU17: 1.0968192 | CV17: 0.76362754 | CW17: 0.33876988 | CX17: 0.99495492 | CY17: 50.333333 | CZ17: 61.301499 | DA17: 63.004165 | DB17: 57.43485
B18: ETHIOPIA | C18: LOW HUMAN DEVELOPMENT | D18: ETH | E18: 33 | F18: 16.535 | G18: 22.2468 | H18: -17 | I18: 17.748532 | J18: 17.4 | K18: 9.654 | L18: 1.589189 | M18: 7.5 | N18: 408 | O18: 3.3271188 | P18: 5 | Q18: 2.4 | R18: 8.9691147 | S18: -5.4 | T18: -3.9248072 | U18: 25.67063 | V18: 3.5 | W18: 45.338964 | X18: -9.936 | Z18: 0.9 | AA18: 7 | AB18: 0.363 | AC18: -1.3144747 | AD18: -0.75555568 | AE18: 56.830601 | AF18: 3.7640201 | AG18: 3.5 | AH18: 3.5 | AI18: 4.25 | AJ18: 16.465 | AK18: -6.5468 | AL18: 16 | AM18: 3.9767698 | AN18: 6.1255142 | AO18: 7.2 | AP18: 26.907344 | AQ18: 3 | AR18: -172.83521 | AS18: 29.825773 | AT18: 53.6 | AU18: 0.15462659 | AV18: 88.482347 | AW18: -0.91030885 | AX18: 0 | AY18: 3.1309661 | AZ18: 23.399115 | BA18: 18.997437 | BB18: 3.409 | BC18: 3.4746 | BD18: -0.4248251 | BE18: 8.062 | BF18: 6.8334 | BG18: 8.8106667 | BH18: 9.7346 | BI18: 5.7 | BJ18: 6.983 | BK18: 7.0166667 | BL18: 7.9162 | BM18: 7 | BN18: -4.8973333 | BO18: -5.4 | BP18: -4.8973333 | BQ18: 0.77613667 | BR18: -5.8104102 | BS18: 73 | BT18: 50 | BU18: 63 | BV18: 62 | BW18: 2011 | BY18: =(AE18-Standardisation_Parameters!$E$15)/Standardisation_Parameters!$F$15 -> 0.46320559 | BZ18: =VLOOKUP($D18,$CH:$CN,2,FALSE) -> 1.3603508 | CA18: =VLOOKUP($D18,$CH:$CN,3,FALSE) -> 1.0910148 | CB18: =VLOOKUP($D18,$CH:$CN,5,FALSE) -> 1.2241093 | CC18: =VLOOKUP($D18,$CH:$CN,6,FALSE) -> 1.3499454 | CD18: =VLOOKUP($D18,$CH:$CN,4,FALSE) -> 0.93703315 | CF18: GHANA | CG18: MEDIUM HUMAN DEVELOPMENT | CH18: GHA | CI18: 0.60019731 | CJ18: 0.043811429 | CK18: 0.3786541 | CL18: 0.11525244 | CM18: 0.27034397 | CN18: 0.4614 | CP18: GHANA | CQ18: MEDIUM HUMAN DEVELOPMENT | CR18: GHA | CS18: GHA2011 | CT18: 96 | CU18: 0.60019731 | CV18: 0.043811429 | CW18: 0.3786541 | CX18: 0.27034342 | CY18: 51 | CZ18: 49.189582 | DA18: 54.703106 | DB18: 45.403088
B19: FIJI | C19: MEDIUM HUMAN DEVELOPMENT | D19: FJI | E19: 8.3 | F19: 5.8423333 | G19: 6.0126 | H19: -0.8 | I19: 2.262989 | K19: 26.297 | L19: 1.7991665 | M19: 1.8 | N19: 4680 | O19: 0.16846301 | P19: 3 | Q19: 4.0583002 | R19: 3.9969489 | S19: -10.7 | T19: -4.6188453 | U19: 6.3609098 | V19: 10.8 | W19: -23.938043 | X19: 83.7 | Y19: 60.020937 | Z19: 1.5 | AA19: 7 | AB19: 0.688 | AC19: -0.98685051 | AD19: -0.90329832 | AE19: 39.344262 | AG19: 3.25 | AH19: 4 | AI19: 3 | AJ19: 2.4576667 | AK19: -1.2126 | AL19: 7.5 | AM19: 0.62043759 | AN19: -0.15562762 | AO19: 12.174901 | AP19: 11.990847 | AQ19: 3 | AR19: 9.5090796 | AS19: 5.5876609 | AT19: 1140 | AU19: 0.25771098 | AV19: 11.358873 | AW19: -0.96003051 | AX19: 10 | AY19: 0.17243983 | AZ19: 7.6583467 | BA19: 8.7657778 | BB19: 114.3 | BC19: 74.5716 | BD19: 0.11247752 | BE19: 12.046024 | BF19: 9.8549693 | BG19: -0.23333333 | BH19: -0.28 | BI19: 1.4 | BJ19: 0.8955 | BK19: -0.23933333 | BL19: -0.3384 | BM19: 7 | BN19: -10.966667 | BO19: -10.7 | BP19: -10.966667 | BQ19: -0.28267477 | BR19: -48.850343 | BW19: 2011 | BY19: =(AE19-Standardisation_Parameters!$E$15)/Standardisation_Parameters!$F$15 -> -0.16936155 | BZ19: =VLOOKUP($D19,$CH:$CN,2,FALSE) -> #N/A | CA19: =VLOOKUP($D19,$CH:$CN,3,FALSE) -> #N/A | CB19: =VLOOKUP($D19,$CH:$CN,5,FALSE) -> #N/A | CC19: =VLOOKUP($D19,$CH:$CN,6,FALSE) -> #N/A | CD19: =VLOOKUP($D19,$CH:$CN,4,FALSE) -> #N/A | CF19: GUATEMALA | CG19: MEDIUM HUMAN DEVELOPMENT | CH19: GTM | CI19: 0.39918867 | CJ19: 0.97130558 | CK19: 0.8373226 | CL19: 0.8305531 | CM19: 0.63640372 | CN19: 0.5702 | CP19: GUATEMALA | CQ19: MEDIUM HUMAN DEVELOPMENT | CR19: GTM | CS19: GTM2011 | CT19: 102 | CU19: 0.39918867 | CV19: 0.97130558 | CW19: 0.8373226 | CX19: 0.63639982 | CY19: 58.666667 | CZ19: 55.308232 | DA19: 51.343236 | DB19: 60.906199
B20: GABON | C20: MEDIUM HUMAN DEVELOPMENT | D20: GAB | E20: 1.9 | F20: 1.7493333 | G20: 3.1084 | H20: 13.1 | I20: 1.8711149 | J20: 81.052 | K20: 29.6 | L20: 3.1726048 | M20: 5.7 | N20: 10700 | O20: 17.115684 | P20: 5 | Q20: 5.7 | R20: 6.8990099 | S20: 21.5 | T20: 24.732722 | U20: 14.030581 | V20: 3.4 | W20: -27.884499 | X20: -4 | Y20: 10.190077 | Z20: 4.25 | AA20: 6 | AB20: 0.674 | AC20: -0.92350225 | AD20: -0.51296412 | AE20: 87.431694 | AG20: 3.75 | AH20: 2.5 | AI20: 3 | AJ20: 0.15066667 | AK20: 0.1916 | AL20: 15 | AM20: 0 | AN20: 1.1388119 | AO20: 17.1 | AP20: 20.69703 | AQ20: 3 | AR20: 18.655015 | AS20: 0 | AT20: 1430 | AU20: 0.73018112 | AV20: -1.5447103 | AW20: -0.9310099 | AX20: 5 | AY20: 26.341653 | AZ20: 16.55256 | BA20: 17.840287 | BB20: 5.2973333 | BC20: 12.3162 | BD20: -0.37672975 | BE20: 16.8 | BF20: 15.5136 | BG20: 3.396 | BH20: 3.613 | BI20: 3.7 | BJ20: 3.632 | BK20: 1.2846667 | BL20: 1.6256 | BM20: 6 | BN20: 18.3 | BO20: 21.5 | BP20: 18.3 | BQ20: -0.20765027 | BR20: 25.751525 | BS20: 65 | BT20: 44 | BU20: 72 | BV20: 60.333333 | BW20: 2011 | BY20: =(AE20-Standardisation_Parameters!$E$15)/Standardisation_Parameters!$F$15 -> 1.5701981 | BZ20: =VLOOKUP($D20,$CH:$CN,2,FALSE) -> 1.0968192 | CA20: =VLOOKUP($D20,$CH:$CN,3,FALSE) -> 0.76362754 | CB20: =VLOOKUP($D20,$CH:$CN,5,FALSE) -> 0.86954809 | CC20: =VLOOKUP($D20,$CH:$CN,6,FALSE) -> 0.99495736 | CD20: =VLOOKUP($D20,$CH:$CN,4,FALSE) -> 0.33876988 | CF20: HONDURAS | CG20: MEDIUM HUMAN DEVELOPMENT | CH20: HND | CI20: 0.60068739 | CJ20: 1.1454363 | CK20: 1.2095753 | CL20: 1.0378536 | CM20: 0.86661349 | CN20: 0.7878 | CP20: HONDURAS | CQ20: MEDIUM HUMAN DEVELOPMENT | CR20: HND | CS20: HND2011 | CT20: 108 | CU20: 0.60068739 | CV20: 1.1454363 | CW20: 1.2095753 | CX20: 0.86660922 | CY20: 64.888889 | CZ20: 59.156194 | DA20: 54.711297 | DB20: 63.816803
B21: GHANA | C21: MEDIUM HUMAN DEVELOPMENT | D21: GHA | E21: 8.7 | F21: 12.886333 | G21: 13.1828 | H21: 11.8 | I21: 4.0163707 | J21: 47.8 | K21: 11.797 | L21: 3.5376887 | M21: 13.6 | N21: 1500 | O21: 0.25542611 | P21: 2 | Q21: 3 | R21: 34.827273 | S21: -7.8 | T21: 0.34875904 | U21: 20.058888 | V21: 1.9 | W21: -8.9130087 | X21: 1.7 | Y21: 28.251692 | Z21: 14 | AA21: 3 | AB21: 0.541 | AC21: 0.49373396 | AD21: -0.07173681 | AE21: 32.786885 | AF21: 3.6491543 | AG21: 3 | AH21: 2.5 | AI21: 2 | AJ21: -4.1863333 | AK21: -4.5828 | AL21: 20.5 | AM21: 5.1422291 | AN21: 2.2726703 | AO21: 9 | AP21: 104.48182 | AQ21: 3 | AR21: 14.969014 | AS21: 74.356633 | AT21: 172.1 | AU21: 2.4053025 | AV21: 61.71123 | AW21: -0.65172727 | AX21: 1 | AY21: 0.23886307 | AZ21: 20.775858 | BA21: 19.52521 | BB21: 2.4 | BC21: 2.42 | BD21: -0.4293872 | BE21: 10.556 | BF21: 9.5052 | BG21: 8.4363333 | BH21: 8.04 | BI21: 12.1 | BJ21: 8.966 | BK21: 6.5953333 | BL21: 6.0426 | BM21: 5 | BN21: -7.4376667 | BO21: -7.8 | BP21: -7.4376667 | BQ21: -0.07515798 | BR21: -4.2733636 | BS21: 58 | BT21: 31 | BU21: 69 | BV21: 52.666667 | BW21: 2011 | BY21: =(AE21-Standardisation_Parameters!$E$15)/Standardisation_Parameters!$F$15 -> -0.40657423 | BZ21: =VLOOKUP($D21,$CH:$CN,2,FALSE) -> 0.60019731 | CA21: =VLOOKUP($D21,$CH:$CN,3,FALSE) -> 0.043811429 | CB21: =VLOOKUP($D21,$CH:$CN,5,FALSE) -> 0.11525244 | CC21: =VLOOKUP($D21,$CH:$CN,6,FALSE) -> 0.27034397 | CD21: =VLOOKUP($D21,$CH:$CN,4,FALSE) -> 0.3786541 | CF21: INDONESIA | CG21: MEDIUM HUMAN DEVELOPMENT | CH21: IDN | CI21: 0.85318037 | CJ21: 0.56645796 | CK21: 0.70437521 | CL21: 0.630096 | CM21: 0.72383989 | CN21: 0.7878 | CP21: INDONESIA | CQ21: MEDIUM HUMAN DEVELOPMENT | CR21: IDN | CS21: IDN2011 | CT21: 114 | CU21: 0.85318037 | CV21: 0.56645796 | CW21: 0.70437521 | CX21: 0.72383785 | CY21: 56.444444 | CZ21: 56.769763 | DA21: 58.93173 | DB21: 54.139151
B22: GUATEMALA | C22: MEDIUM HUMAN DEVELOPMENT | D22: GTM | E22: 6.215 | F22: 3.9783333 | G22: 6.0224 | H22: 7.285 | I22: 3.7447797 | J22: 8.436 | K22: 38.907 | L22: 2.0696709 | M22: 3.8 | N22: 3310 | O22: 0.25480182 | P22: 1 | Q22: 4.2 | R22: 38.663542 | S22: -3.3 | T22: -1.4662186 | U22: 32.113773 | V22: 12.1 | W22: -12.082291 | X22: 8.069 | Y22: 38.496026 | Z22: 5.2 | AA22: 4 | AB22: 0.574 | AC22: -0.35473901 | AD22: -1.0365755 | AE22: 50.819672 | AF22: 3.9971175 | AG22: 3.25 | AH22: 3.5 | AI22: 3.75 | AJ22: 2.2366667 | AK22: -0.6224 | AL22: 13.5 | AM22: 0.36349691 | AN22: 1.6133 | AO22: 12.6 | AP22: 115.99063 | AQ22: 3 | AR22: 22.536084 | AS22: 4.6673003 | AT22: 446.4 | AU22: 0.89339808 | AV22: 1.4601019 | AW22: -0.61336458 | AX22: 3 | AY22: 0.25028829 | AZ22: 34.488182 | BA22: 36.78339 | BB22: 11.666 | BC22: 12.0546 | BD22: -0.034232362 | BE22: 13.799 | BF22: 12.4848 | BG22: 2.37 | BH22: 3.339 | BI22: 1.3 | BJ22: 0.8605 | BK22: -0.064666667 | BL22: 0.8666 | BM22: 4 | BN22: -1.8566667 | BO22: -3.3 | BP22: -1.8566667 | BQ22: 0.62854578 | BR22: -0.43996445 | BS22: 63 | BT22: 44 | BU22: 66 | BV22: 57.666667 | BW22: 2011 | BY22: =(AE22-Standardisation_Parameters!$E$15)/Standardisation_Parameters!$F$15 -> 0.24576064 | BZ22: =VLOOKUP($D22,$CH:$CN,2,FALSE) -> 0.39918867 | CA22: =VLOOKUP($D22,$CH:$CN,3,FALSE) -> 0.97130558 | CB22: =VLOOKUP($D22,$CH:$CN,5,FALSE) -> 0.8305531 | CC22: =VLOOKUP($D22,$CH:$CN,6,FALSE) -> 0.63640372 | CD22: =VLOOKUP($D22,$CH:$CN,4,FALSE) -> 0.8373226 | CF22: INDIA | CG22: MEDIUM HUMAN DEVELOPMENT | CH22: IND | CI22: 0.41669351 | CJ22: 0.20379836 | CK22: 0.4451278 | CL22: 0.19321866 | CM22: 0.23302617 | CN22: 0.7878 | CP22: INDIA | CQ22: MEDIUM HUMAN DEVELOPMENT | CR22: IND | CS22: IND2011 | CT22: 120 | CU22: 0.41669351 | CV22: 0.20379836 | CW22: 0.4451278 | CX22: 0.23302488 | CY22: 52.111111 | CZ22: 48.5658 | DA22: 51.635831 | DB22: 48.077278
B23: HONDURAS | C23: MEDIUM HUMAN DEVELOPMENT | D23: HND | E23: 6.762 | F23: 5.6523333 | G23: 7.0592 | H23: 11.338 | I23: 3.1788656 | J23: 27.117 | K23: 36.541 | L23: 3.109796 | M23: 3.8 | N23: 2190 | O23: 0.010569941 | P23: 2 | Q23: 2.8 | R23: 19.57064 | S23: -6.7 | T23: -0.79327771 | U23: 26.768128 | V23: 3.7 | W23: 3.2873184 | X23: 4.893 | Y23: 52.327532 | Z23: 11 | AA23: 6 | AB23: 0.625 | AC23: -0.479126 | AD23: -0.87080741 | AE23: 71.038251 | AF23: 3.9768608 | AG23: 3.75 | AH23: 3 | AI23: 3.75 | AJ23: 1.1096667 | AK23: -1.8592 | AL23: 18.1 | AM23: 1.0727861 | AN23: 0.95581832 | AO23: 8.4 | AP23: 58.711921 | AQ23: 3 | AR23: 30.752346 | AS23: 17.818977 | AT23: 169 | AU23: 1.8898805 | AV23: 0.12838249 | AW23: -0.8042936 | AX23: 3 | AY23: 0.023973299 | AZ23: 26.582905 | BA23: 26.347511 | BB23: 4.769 | BC23: 4.3434 | BD23: 0.11291911 | BE23: 9.095 | BF23: 8.8332 | BG23: 1.481 | BH23: 2.9724 | BI23: 1.441 | BJ23: 1.037 | BK23: -0.72166667 | BL23: 0.7124 | BM23: 6 | BN23: -5.5123333 | BO23: -6.7 | BP23: -5.5123333 | BQ23: 0.09070569 | BR23: -7.0098269 | BS23: 68 | BT23: 44 | BU23: 78 | BV23: 63.333333 | BW23: 2011 | BY23: =(AE23-Standardisation_Parameters!$E$15)/Standardisation_Parameters!$F$15 -> 0.9771664 | BZ23: =VLOOKUP($D23,$CH:$CN,2,FALSE) -> 0.60068739 | CA23: =VLOOKUP($D23,$CH:$CN,3,FALSE) -> 1.1454363 | CB23: =VLOOKUP($D23,$CH:$CN,5,FALSE) -> 1.0378536 | CC23: =VLOOKUP($D23,$CH:$CN,6,FALSE) -> 0.86661349 | CD23: =VLOOKUP($D23,$CH:$CN,4,FALSE) -> 1.2095753 | CF23: IRAQ | CG23: MEDIUM HUMAN DEVELOPMENT | CH23: IRQ | CI23: 0.83426535 | CJ23: 1.3985318 | CK23: 1.8676649 | CL23: 1.3210653 | CM23: 1.1611937 | CN23: 1.0054 | CP23: IRAQ | CQ23: MEDIUM HUMAN DEVELOPMENT | CR23: IRQ | CS23: IRQ2011 | CT23: 126 | CU23: 0.83426535 | CV23: 1.3985318 | CW23: 1.8676649 | CX23: 1.1611889 | CY23: 75.888889 | CZ23: 64.080107 | DA23: 58.615564 | DB23: 68.047306
B24: INDIA | C24: MEDIUM HUMAN DEVELOPMENT | D24: IND | E24: 8.866 | F24: 10.581 | G24: 9.2938 | H24: 0.734 | I24: 3.4309996 | J24: 27.038 | K24: 11.599 | L24: 2.3921244 | M24: 7.2 | N24: 1570 | O24: 2.7565793 | P24: 1 | Q24: 6.9 | R24: 26.479643 | S24: -2.2 | T24: -1.6523248 | U24: 15.713296 | V24: 11.1 | W24: -15.447562 | X24: 14.8 | Y24: 71.109006 | Z24: 8.5 | AA24: 2 | AB24: 0.547 | AC24: 0.42402758 | AD24: -0.057769364 | AE24: 75.956284 | AF24: 4.3049784 | AG24: 3 | AH24: 2.5 | AI24: 3.5 | AJ24: -1.715 | AK24: -1.1938 | AL24: 9.6 | AM24: 1.699035 | AN24: 3.2341963 | AO24: 20.7 | AP24: 79.43893 | AQ24: 3 | AR24: 22.922508 | AS24: 22.185999 | AT24: 160 | AU24: 1.4603622 | AV24: 12.870914 | AW24: -0.73520357 | AX24: 1 | AY24: 3.3223777 | AZ24: 17.215777 | BA24: 17.272621 | BB24: 7.039 | BC24: 8.615 | BE24: 25.062 | BF24: 26.9178 | BG24: 8.3303333 | BH24: 7.7366 | BI24: 5.3 | BJ24: 6.6 | BK24: 6.6 | BL24: 6.0274 | BM24: 5 | BN24: -2.408 | BO24: -2.2 | BP24: -2.408 | BQ24: -0.37250831 | BR24: 0.77006064 | BS24: 60 | BT24: 81 | BU24: 56 | BV24: 65.666667 | BW24: 2011 | BY24: =(AE24-Standardisation_Parameters!$E$15)/Standardisation_Parameters!$F$15 -> 1.1550759 | BZ24: =VLOOKUP($D24,$CH:$CN,2,FALSE) -> 0.41669351 | CA24: =VLOOKUP($D24,$CH:$CN,3,FALSE) -> 0.20379836 | CB24: =VLOOKUP($D24,$CH:$CN,5,FALSE) -> 0.19321866 | CC24: =VLOOKUP($D24,$CH:$CN,6,FALSE) -> 0.23302617 | CD24: =VLOOKUP($D24,$CH:$CN,4,FALSE) -> 0.4451278 | CF24: JORDAN | CG24: MEDIUM HUMAN DEVELOPMENT | CH24: JOR | CI24: 0.24015599 | CJ24: -0.00061593764 | CK24: -0.1464881 | CL24: -0.031822578 | CM24: 0.0032828881 | CN24: 0.5702 | CP24: JORDAN | CQ24: MEDIUM HUMAN DEVELOPMENT | CR24: JOR | CS24: JOR2011 | CT24: 132 | CU24: 0.24015599 | CV24: -0.00061593764 | CW24: -0.1464881 | CX24: 0.0032820929 | CY24: 42.222222 | CZ24: 44.725638 | DA24: 48.684997 | DB24: 44.660483
B25: INDONESIA | C25: MEDIUM HUMAN DEVELOPMENT | D25: IDN | E25: 5.362 | F25: 5.112 | G25: 6.3048 | H25: 6.838 | I25: 2.1937038 | J25: 6.592 | K25: 16.337 | L25: 0.74625753 | M25: 6.463 | N25: 3450 | O25: 637.76442 | P25: 2 | Q25: 7 | R25: 15.974644 | S25: 0.3 | T25: 1.5010215 | U25: 18.77381 | V25: 10.9 | W25: -35.698987 | X25: 14.895 | Y25: 36.530561 | Z25: 5.6 | AA25: 5 | AB25: 0.617 | AC25: -0.055267442 | AD25: -0.6300547 | AE25: 68.852459 | AF25: 4.3768297 | AG25: 3 | AH25: 3.25 | AI25: 2.75 | AJ25: 0.25 | AK25: -1.1048 | AL25: 12.2 | AM25: 0.84949044 | AN25: 7.9471225 | AO25: 21 | AP25: 47.923932 | AQ25: 3 | AR25: 16.555882 | AS25: 11.775636 | AT25: 536.1 | AU25: 0.96212101 | AV25: -4.0538964 | AW25: -0.84025356 | AX25: 5 | AY25: 789.13726 | AZ25: 23.244925 | BA25: 25.880928 | BB25: 14.2 | BC25: 14.5216 | BD25: 0.0011684785 | BE25: 21.629 | BF25: 19.2828 | BG25: 5.7636667 | BH25: 5.9306 | BI25: 5.3 | BJ25: 5.1585 | BK25: 4.5813333 | BL25: 4.7086 | BM25: 6 | BN25: 1.0223333 | BO25: 0.3 | BP25: 1.0223333 | BQ25: -0.48614281 | BR25: 0.48739409 | BS25: 73 | BT25: 44 | BU25: 72 | BV25: 63 | BW25: 2011 | BY25: =(AE25-Standardisation_Parameters!$E$15)/Standardisation_Parameters!$F$15 -> 0.8980955 | BZ25: =VLOOKUP($D25,$CH:$CN,2,FALSE) -> 0.85318037 | CA25: =VLOOKUP($D25,$CH:$CN,3,FALSE) -> 0.56645796 | CB25: =VLOOKUP($D25,$CH:$CN,5,FALSE) -> 0.630096 | CC25: =VLOOKUP($D25,$CH:$CN,6,FALSE) -> 0.72383989 | CD25: =VLOOKUP($D25,$CH:$CN,4,FALSE) -> 0.70437521 | CF25: KENYA | CG25: LOW HUMAN DEVELOPMENT | CH25: KEN | CI25: 0.66765653 | CJ25: 1.1300231 | CK25: 1.3491701 | CL25: 1.0453842 | CM25: 0.90347962 | CN25: 0.679 | CP25: KENYA | CQ25: LOW HUMAN DEVELOPMENT | CR25: KEN | CS25: KEN2011 | CT25: 138 | CU25: 0.66765653 | CV25: 1.1300231 | CW25: 1.3491701 | CX25: 0.90347547 | CY25: 67.222222 | CZ25: 59.772415 | DA25: 55.83069 | DB25: 63.55917
B26: IRAQ | C26: MEDIUM HUMAN DEVELOPMENT | D26: IRQ | E26: 5.611 | F26: 1.7603333 | G26: 8.1344 | H26: 0.389 | I26: 9.6772227 | J26: 98.2 | K26: 24.605 | L26: 2.7193749 | M26: 8.2 | N26: 4880 | O26: 36.814399 | P26: 4 | Q26: 13.1 | R26: 3.3815558 | S26: 13.8 | T26: 15.996767 | U26: 32.328961 | V26: 5.3 | W26: -47.257844 | Y26: -2.1016031 | AA26: 6 | AB26: 0.573 | AC26: -1.0533541 | AD26: -1.6183871 | AE26: 86.885246 | AG26: 3.75 | AH26: 4 | AI26: 4 | AJ26: 3.8506667 | AK26: -2.6344 | AL26: 6 | AM26: 6.3796552 | AN26: 2.0225236 | AO26: 39.3 | AP26: 10.144667 | AQ26: 3 | AR26: -120.79109 | AS26: 127.5931 | AT26: 210 | AV26: -6.7729084 | AW26: -96.618444 | AX26: 2 | AY26: 35.896745 | AZ26: 43.134053 | BA26: 61.477711 | BB26: 6 | BC26: 9.4 | BD26: 0.24414108 | BE26: 39.746 | BF26: 49.2342 | BG26: 6.0666667 | BH26: 5.5 | BI26: 5.8 | BJ26: 4.6 | BK26: 3.9 | BL26: 3.34 | BM26: 5 | BN26: 4.4656667 | BO26: 13.8 | BP26: 4.4656667 | BQ26: 2.7709189 | BR26: 0.89802641 | BS26: 80 | BT26: 69 | BU26: 97 | BV26: 82 | BW26: 2011 | BY26: =(AE26-Standardisation_Parameters!$E$15)/Standardisation_Parameters!$F$15 -> 1.5504304 | BZ26: =VLOOKUP($D26,$CH:$CN,2,FALSE) -> 0.83426535 | CA26: =VLOOKUP($D26,$CH:$CN,3,FALSE) -> 1.3985318 | CB26: =VLOOKUP($D26,$CH:$CN,5,FALSE) -> 1.3210653 | CC26: =VLOOKUP($D26,$CH:$CN,6,FALSE) -> 1.1611937 | CD26: =VLOOKUP($D26,$CH:$CN,4,FALSE) -> 1.8676649 | CF26: KYRGYZSTAN | CG26: MEDIUM HUMAN DEVELOPMENT | CH26: KGZ | CI26: 1.3932766 | CJ26: 1.3178153 | CK26: 1.3358753 | CL26: 1.4240699 | CM26: 1.4948611 | CN26: 0.4614 | CP26: KYRGYZSTAN | CQ26: MEDIUM HUMAN DEVELOPMENT | CR26: KGZ | CS26: KGZ2011 | CT26: 144 | CU26: 1.3932766 | CV26: 1.3178153 | CW26: 1.3358753 | CX26: 1.4948571 | CY26: 67 | CZ26: 69.657388 | DA26: 67.959465 | DB26: 66.698126
B27: JORDAN | C27: MEDIUM HUMAN DEVELOPMENT | D27: JOR | E27: 4.417 | F27: 2.9193333 | G27: 5.8146 | H27: 4.483 | I27: 5.7078154 | J27: 25.567 | K27: 13.143 | L27: 2.0866015 | M27: 2.6 | N27: 4480 | O27: 0 | P27: 2 | Q27: 7.4 | R27: 13.105433 | S27: -12.2 | T27: -6.6624886 | U27: 23.804329 | V27: 5.1 | W27: -15.543228 | X27: -0.1 | Y27: 96.003789 | Z27: 2.5 | AA27: 5 | AB27: 0.698 | AC27: -0.8326618 | AD27: 0.21938102 | AE27: 51.912568 | AF27: 4.1869537 | AG27: 2.25 | AH27: 2.5 | AI27: 2.75 | AJ27: 1.4976667 | AK27: -2.2146 | AL27: 8.9 | AM27: 0.20815859 | AN27: 1.9891676 | AO27: 22.2 | AP27: 39.316299 | AQ27: 3 | AR27: 18.795836 | AS27: 1.8068166 | AT27: 223 | AU27: 0.42951831 | AV27: 0 | AW27: -0.86894567 | AX27: 2 | AY27: 2.2781296e-16 | AZ27: 25.816068 | BA27: 31.127212 | BB27: 4.6666667 | BC27: 7.1656 | BE27: 25.377 | BF27: 22.2018 | BG27: 2.6666667 | BH27: 4.1506 | BI27: 0.3 | BJ27: 0.4 | BK27: 0.033333333 | BL27: 1.28 | BM27: 4 | BN27: -7.2676667 | BO27: -12.2 | BP27: -7.2676667 | BQ27: 1.0286658 | BR27: -2.7986047 | BS27: 53 | BT27: 19 | BU27: 47 | BV27: 39.666667 | BW27: 2011 | BY27: =(AE27-Standardisation_Parameters!$E$15)/Standardisation_Parameters!$F$15 -> 0.28529608 | BZ27: =VLOOKUP($D27,$CH:$CN,2,FALSE) -> 0.24015599 | CA27: =VLOOKUP($D27,$CH:$CN,3,FALSE) -> -0.00061593764 | CB27: =VLOOKUP($D27,$CH:$CN,5,FALSE) -> -0.031822578 | CC27: =VLOOKUP($D27,$CH:$CN,6,FALSE) -> 0.0032828881 | CD27: =VLOOKUP($D27,$CH:$CN,4,FALSE) -> -0.1464881 | CF27: CAMBODIA | CG27: MEDIUM HUMAN DEVELOPMENT | CH27: KHM | CI27: 0.79299413 | CJ27: 1.0008626 | CK27: 1.0433911 | CL27: 0.9754801 | CM27: 0.91821124 | CN27: 0.7878 | CP27: CAMBODIA | CQ27: MEDIUM HUMAN DEVELOPMENT | CR27: KHM | CS27: KHM2011 | CT27: 150 | CU27: 0.79299413 | CV27: 1.0008626 | CW27: 1.0433911 | CX27: 0.91820766 | CY27: 62.111111 | CZ27: 60.018664 | DA27: 57.925714 | DB27: 61.400245
B28: KENYA | C28: LOW HUMAN DEVELOPMENT | D28: KEN | E28: 13.976 | F28: 9.0486667 | G28: 10.641 | H28: 1.824 | I28: 4.682836 | J28: 22.2 | K28: 9.989 | L28: 2.2059402 | M28: 4.2 | N28: 845 | O28: 8.6261969 | P28: 3 | Q28: 4 | R28: 21.179402 | S28: -10.5 | T28: -9.2443382 | U28: 25.454933 | V28: 4.9 | W28: -4.861953 | X28: -7.505 | Y28: 51.034712 | Z28: 4 | AA28: 6 | AB28: 0.509 | AC28: -0.23110592 | AD28: -1.0113717 | AE28: 57.923497 | AF28: 3.8215291 | AG28: 4 | AH28: 3.25 | AI28: 3.75 | AJ28: 4.9273333 | AK28: -1.041 | AL28: 15.8 | AM28: 0.91748569 | AN28: 1.9084833 | AO28: 12 | AP28: 63.538206 | AQ28: 3 | AR28: 16.769236 | AS28: 12.239259 | AT28: 50.2 | AU28: 0.68722929 | AV28: 31.928054 | AW28: -0.78820598 | AX28: 0 | AY28: 8.689894 | AZ28: 26.100153 | BA28: 26.086317 | BB28: 4.4763333 | BC28: 4.5952 | BD28: -0.07317995 | BE28: 11.916 | BF28: 11.202 | BG28: 4.0873333 | BH28: 4.21 | BI28: 1.625 | BJ28: 2.323 | BK28: 1.5866667 | BL28: 1.6072 | BM28: 5 | BN28: -7.9413333 | BO28: -10.5 | BP28: -7.9413333 | BQ28: 0.33974144 | BR28: -5.3107067 | BS28: 75 | BT28: 50 | BU28: 91 | BV28: 72 | BW28: 2011 | BY28: =(AE28-Standardisation_Parameters!$E$15)/Standardisation_Parameters!$F$15 -> 0.50274104 | BZ28: =VLOOKUP($D28,$CH:$CN,2,FALSE) -> 0.66765653 | CA28: =VLOOKUP($D28,$CH:$CN,3,FALSE) -> 1.1300231 | CB28: =VLOOKUP($D28,$CH:$CN,5,FALSE) -> 1.0453842 | CC28: =VLOOKUP($D28,$CH:$CN,6,FALSE) -> 0.90347962 | CD28: =VLOOKUP($D28,$CH:$CN,4,FALSE) -> 1.3491701 | CF28: SRI LANKA | CG28: MEDIUM HUMAN DEVELOPMENT | CH28: LKA | CI28: 0.57223503 | CJ28: 0.28164626 | CK28: 0.2257646 | CL28: 0.30587151 | CM28: 0.3801294 | CN28: 0.5702 | CP28: SRI LANKA | CQ28: MEDIUM HUMAN DEVELOPMENT | CR28: LKA | CS28: LKA2011 | CT28: 156 | CU28: 0.57223503 | CV28: 0.28164626 | CW28: 0.2257646 | CX28: 0.38012801 | CY28: 48.444444 | CZ28: 51.024636 | DA28: 54.235715 | DB28: 49.378509
B29: KOREA, DEMOCRATIC PEOPLE'S REP OF | C29: LOW HUMAN DEVELOPMENT | D29: PRK | L29: 1.9411337 | M29: 2.5 | O29: 1.2617448 | P29: 6 | Q29: 0.68491477 | R29: 6039.3739 | U29: 56.114255 | W29: -1.343594 | AA29: 7 | AC29: -2.2078247 | AD29: -1.2974518 | AG29: 4 | AH29: 4.5 | AI29: 2.75 | AN29: 0.43273681 | AO29: 2.0547443 | AP29: 18118.122 | AQ29: 3 | AV29: 0.71942446 | AW29: 5939.3739 | AX29: 0 | AZ29: 56.745529 | BA29: 51.345292 | BD29: 0.18055853 | BE29: 2.2813445 | BF29: 2.36741 | BG29: 0.76666667 | BH29: 0.84 | BI29: 1.4 | BJ29: 0.8 | BK29: -0.83333333 | BL29: -0.3 | BM29: 9 | BS29: 95 | BT29: 44 | BU29: 75 | BV29: 71.333333 | BW29: 2011 | BY29: =(AE29-Standardisation_Parameters!$E$15)/Standardisation_Parameters!$F$15 -> -1.5926376 | BZ29: =VLOOKUP($D29,$CH:$CN,2,FALSE) -> #N/A | CA29: =VLOOKUP($D29,$CH:$CN,3,FALSE) -> #N/A | CB29: =VLOOKUP($D29,$CH:$CN,5,FALSE) -> #N/A | CC29: =VLOOKUP($D29,$CH:$CN,6,FALSE) -> #N/A | CD29: =VLOOKUP($D29,$CH:$CN,4,FALSE) -> #N/A | CF29: LESOTHO | CG29: LOW HUMAN DEVELOPMENT | CH29: LSO | CI29: 0.80750976 | CJ29: 0.28028689 | CK29: 0.15264353 | CL29: 0.37653183 | CM29: 0.53820421 | CN29: 0.8966 | CP29: LESOTHO | CQ29: LOW HUMAN DEVELOPMENT | CR29: LSO | CS29: LSO2011 | CT29: 162 | CU29: 0.80750976 | CV29: 0.28028689 | CW29: 0.15264353 | CX29: 0.53820308 | CY29: 47.222222 | CZ29: 53.666869 | DA29: 58.168343 | DB29: 49.355787
B30: KYRGYZSTAN | C30: MEDIUM HUMAN DEVELOPMENT | D30: KGZ | E30: 16.582 | F30: 10.475 | G30: 13.2248 | H30: 17.218 | I30: 8.6123404 | J30: 33.124 | K30: 17.348 | L30: 4.2320685 | M30: 5.7 | N30: 1040 | O30: 4.6053373 | P30: 4 | Q30: 4.4 | R30: 18.103453 | S30: -8 | T30: -1.5459272 | U30: 62.44714 | V30: 40 | W30: -28.283852 | X30: 6.8 | Z30: 8.3 | AA30: 6 | AB30: 0.615 | AC30: -0.95688195 | AD30: -1.2917066 | AE30: 36.612022 | AF30: 3.4472698 | AG30: 3.75 | AH30: 3 | AI30: 4 | AJ30: 6.107 | AK30: -9.2248 | AL30: 33.8 | AM30: 4.9747178 | AN30: 1.1171842 | AO30: 13.2 | AP30: 54.31036 | AQ30: 3 | AR30: 124.23301 | AS30: 122.37806 | AT30: 197.3 | AU30: 1.4260008 | AV30: 23.656268 | AW30: -0.81896547 | AX30: 0 | AY30: 4.3754626 | AZ30: 78.611895 | BA30: 75.227084 | BB30: 20.607333 | BC30: 15.415 | BD30: -0.51642906 | BE30: 14.853 | BF30: 13.4022 | BG30: 2.2326667 | BH30: 4.728 | BI30: 4.6 | BJ30: 1.55 | BK30: 1.557 | BL30: 3.7474 | BM30: 7 | BN30: -8.224 | BO30: -8 | BP30: -8.224 | BQ30: -0.25717412 | BR30: -13.549757 | BS30: 85 | BT30: 50 | BU30: 78 | BV30: 71 | BW30: 2011 | BY30: =(AE30-Standardisation_Parameters!$E$15)/Standardisation_Parameters!$F$15 -> -0.26820017 | BZ30: =VLOOKUP($D30,$CH:$CN,2,FALSE) -> 1.3932766 | CA30: =VLOOKUP($D30,$CH:$CN,3,FALSE) -> 1.3178153 | CB30: =VLOOKUP($D30,$CH:$CN,5,FALSE) -> 1.4240699 | CC30: =VLOOKUP($D30,$CH:$CN,6,FALSE) -> 1.4948611 | CD30: =VLOOKUP($D30,$CH:$CN,4,FALSE) -> 1.3358753 | CF30: MOROCCO | CG30: MEDIUM HUMAN DEVELOPMENT | CH30: MAR | CI30: 0.55962767 | CJ30: 0.48719568 | CK30: 0.39194884 | CL30: 0.47414207 | CM30: 0.48281415 | CN30: 0.679 | CP30: MOROCCO | CQ30: MEDIUM HUMAN DEVELOPMENT | CR30: MAR | CS30: MAR2011 | CT30: 168 | CU30: 0.55962767 | CV30: 0.48719568 | CW30: 0.39194884 | CX30: 0.48281206 | CY30: 51.222222 | CZ30: 52.741005 | DA30: 54.024982 | DB30: 52.814278
B31: LESOTHO | C31: LOW HUMAN DEVELOPMENT | D31: LSO | E31: 4.8 | F31: 5.1793333 | G31: 6.8578 | H31: 8.2 | I31: 1.2058618 | L31: 0.6589198 | M31: 4 | N31: 1000 | O31: 0.63168888 | P31: 4 | Q31: 4.6 | R31: 0.10895224 | S31: -25 | U31: 33.147139 | V31: 1.8 | W31: -18.640977 | Y31: -6.2725802 | Z31: 8 | AA31: 4 | AB31: 0.45 | AC31: -0.17813554 | AD31: -0.29865157 | AE31: 77.595628 | AF31: 3.2634153 | AG31: 2.75 | AH31: 2.5 | AI31: 2.25 | AJ31: -0.37933333 | AK31: -3.3578 | AL31: 13 | AM31: 1.8237166 | AN31: 5.9345614 | AO31: 13.8 | AP31: 0.32685673 | AQ31: 3 | AR31: 7.358169 | AS31: 25.772763 | AT31: 17 | AU31: 1.3744586 | AV31: 3.0179543 | AW31: -0.99891048 | AX31: 3 | AY31: 0.9173838 | AZ31: 35.623605 | BA31: 38.553272 | BB31: 1.9 | BC31: 2.4248 | BD31: 0.00012247452 | BE31: 15 | BF31: 16.02 | BG31: 3.4923333 | BH31: 3.9104 | BI31: 4.7 | BJ31: 4.6 | BK31: 3.6666667 | BL31: 3.82 | BM31: 6 | BN31: -14.962333 | BO31: -25 | BP31: -14.962333 | BQ31: 0.35101477 | BR31: -68.091883 | BS31: 60 | BT31: 19 | BU31: 44 | BV31: 41 | BW31: 2011 | BY31: =(AE31-Standardisation_Parameters!$E$15)/Standardisation_Parameters!$F$15 -> 1.2143791 | BZ31: =VLOOKUP($D31,$CH:$CN,2,FALSE) -> 0.80750976 | CA31: =VLOOKUP($D31,$CH:$CN,3,FALSE) -> 0.28028689 | CB31: =VLOOKUP($D31,$CH:$CN,5,FALSE) -> 0.37653183 | CC31: =VLOOKUP($D31,$CH:$CN,6,FALSE) -> 0.53820421 | CD31: =VLOOKUP($D31,$CH:$CN,4,FALSE) -> 0.15264353 | CF31: MADAGASCAR | CG31: LOW HUMAN DEVELOPMENT | CH31: MDG | CI31: 1.1300797 | CJ31: 0.96592907 | CK31: 1.1763385 | CL31: 1.0490965 | CM31: 1.1268459 | CN31: 0.8966 | CP31: MADAGASCAR | CQ31: LOW HUMAN DEVELOPMENT | CR31: MDG | CS31: MDG2011 | CT31: 174 | CU31: 1.1300797 | CV31: 0.96592907 | CW31: 1.1763385 | CX31: 1.1268428 | CY31: 64.333333 | CZ31: 63.506011 | DA31: 63.560116 | DB31: 60.81633
B32: MADAGASCAR | C32: LOW HUMAN DEVELOPMENT | D32: MDG | E32: 9.481 | F32: 9.2283333 | G32: 9.442 | H32: 29.519 | I32: 3.3549589 | J32: 48 | K32: 23.764 | L32: 4.4754317 | M32: 0.7 | N32: 462 | O32: 147.97375 | P32: 6 | Q32: 3.1 | R32: 20.769598 | S32: -25.1 | T32: -22.546451 | U32: 23.58209 | V32: 1.6 | W32: -8.9005036 | X32: 7.2 | Y32: 10.489162 | Z32: 9.6 | AA32: 6 | AB32: 0.48 | AC32: -0.7977237 | AD32: -0.8425329 | AE32: 78.688525 | AF32: 3.3633945 | AG32: 3.5 | AH32: 3 | AI32: 3.75 | AJ32: 0.25266667 | AK32: -0.942 | AL32: 39 | AM32: 2.991437 | AN32: 0.48741667 | AO32: 9.3 | AP32: 62.308795 | AQ32: 3 | AR32: 100.56154 | AS32: 120.48013 | AT32: 40 | AU32: 1.6493503 | AV32: 8.0710132 | AW32: -0.79230402 | AX32: 4 | AY32: 150.59331 | AZ32: 24.985494 | BA32: 24.073207 | BB32: 2.0726667 | BC32: 1.7484 | BD32: -0.22669721 | BE32: 9.234 | BF32: 9.1482 | BG32: -0.82066667 | BH32: 2.1814 | BI32: -2.1 | BJ32: -2.25 | BK32: -3.6333333 | BL32: -0.76 | BM32: 7 | BN32: -27.533333 | BO32: -25.1 | BP32: -27.533333 | BQ32: -0.11622276 | BR32: -59.367352 | BS32: 68 | BT32: 44 | BU32: 66 | BV32: 59.333333 | BW32: 2011 | BY32: =(AE32-Standardisation_Parameters!$E$15)/Standardisation_Parameters!$F$15 -> 1.2539145 | BZ32: =VLOOKUP($D32,$CH:$CN,2,FALSE) -> 1.1300797 | CA32: =VLOOKUP($D32,$CH:$CN,3,FALSE) -> 0.96592907 | CB32: =VLOOKUP($D32,$CH:$CN,5,FALSE) -> 1.0490965 | CC32: =VLOOKUP($D32,$CH:$CN,6,FALSE) -> 1.1268459 | CD32: =VLOOKUP($D32,$CH:$CN,4,FALSE) -> 1.1763385 | CF32: MALI | CG32: LOW HUMAN DEVELOPMENT | CH32: MLI | CI32: 0.51854447 | CJ32: 0.72814371 | CK32: 0.49830675 | CL32: 0.66336389 | CM32: 0.58542709 | CN32: 0.8966 | CP32: MALI | CQ32: LOW HUMAN DEVELOPMENT | CR32: MLI | CS32: MLI2011 | CT32: 177 | CU32: 0.51854447 | CV32: 0.72814371 | CW32: 0.49830675 | CX32: 0.58542414 | CY32: 53 | CZ32: 54.456171 | DA32: 53.338274 | DB32: 56.841736
B33: MALAWI | C33: LOW HUMAN DEVELOPMENT | D33: MWI | E33: 7.6 | F33: 7.801 | G33: 8.0114 | H33: 16.3 | I33: 1.3950371 | J33: 43.158 | K33: 10.882 | L33: 2.7417148 | M33: 5.3 | N33: 369 | O33: 7.4695697 | P33: 5 | Q33: 1.6 | R33: 31.666667 | S33: -12.3 | T33: -10.78461 | U33: 22.298387 | V33: 6.5 | W33: 6.3394885 | X33: -2.964 | Y33: 28.393015 | Z33: 7.5 | AA33: 5 | AB33: 0.4 | AC33: -0.15753089 | AD33: -0.13905781 | AE33: 77.04918 | AF33: 3.580455 | AG33: 3.5 | AH33: 3 | AI33: 2.25 | AJ33: -0.201 | AK33: 3.4886 | AL33: 23.9 | AM33: 1.4281423 | AN33: 3.2169648 | AO33: 4.8 | AP33: 95 | AQ33: 3 | AR33: 27.595229 | AS33: 39.583819 | AT33: 24.5 | AU33: 1.2885549 | AV33: 12.077026 | AW33: -0.68333333 | AX33: 5 | AY33: 7.3817713 | AZ33: 22.064902 | BA33: 22.110688 | BB33: 3.6 | BC33: 3.5 | BD33: 0.27712204 | BE33: 4.532 | BF33: 4.548 | BG33: 7.1333333 | BH33: 8.82 | BI33: 1.4 | BJ33: 3.15 | BK33: 5.0333333 | BL33: 4.92 | BM33: 5 | BN33: -10.593667 | BO33: -12.3 | BP33: -10.593667 | BQ33: 0.37758409 | BR33: -145.47857 | BS33: 63 | BT33: 44 | BU33: 72 | BV33: 59.666667 | BW33: 2011 | BY33: =(AE33-Standardisation_Parameters!$E$15)/Standardisation_Parameters!$F$15 -> 1.1946114 | BZ33: =VLOOKUP($D33,$CH:$CN,2,FALSE) -> 0.89283756 | CA33: =VLOOKUP($D33,$CH:$CN,3,FALSE) -> 0.20067696 | CB33: =VLOOKUP($D33,$CH:$CN,5,FALSE) -> 0.33590943 | CC33: =VLOOKUP($D33,$CH:$CN,6,FALSE) -> 0.55273433 | CD33: =VLOOKUP($D33,$CH:$CN,4,FALSE) -> 0.73096469 | CF33: MONGOLIA | CG33: MEDIUM HUMAN DEVELOPMENT | CH33: MNG | CI33: 0.5208178 | CJ33: 0.33991617 | CK33: 1.0832753 | CL33: 0.33897318 | CM33: 0.37694471 | CN33: 0.5702 | CP33: MONGOLIA | CQ33: MEDIUM HUMAN DEVELOPMENT | CR33: MNG | CS33: MNG2011 | CT33: 180 | CU33: 0.5208178 | CV33: 0.33991617 | CW33: 1.0832753 | CX33: 0.37694307 | CY33: 62.777778 | CZ33: 50.9714 | DA33: 53.376273 | DB33: 50.352494
B34: MALI | C34: LOW HUMAN DEVELOPMENT | D34: MLI | E34: 2.9 | F34: 2.0693333 | G34: 3.3582 | H34: 6.1 | I34: 3.2319781 | J34: 13.3 | K34: 28.402 | L34: 0.66558245 | M34: 5.4 | N34: 707 | O34: 17.115318 | P34: 3 | Q34: 6.443 | R34: 2.0154094 | S34: -7.451 | T34: -5.4286607 | U34: 28.49933 | V34: 3.2 | W34: -3.8677869 | X34: -3.4 | Y34: 12.485436 | Z34: 3.3 | AA34: 5 | AB34: 0.359 | AC34: 0.15258479 | AD34: -0.46066321 | AE34: 80.874317 | AF34: 3.3870861 | AG34: 3.5 | AH34: 3.5 | AI34: 3.5 | AJ34: 0.83066667 | AK34: 0.6418 | AL34: 9 | AM34: 0.21213203 | AN34: 7.4220707 | AO34: 19.329 | AP34: 6.0462281 | AQ34: 3 | AR34: 25.493844 | AS34: 1.9728279 | AT34: 105 | AU34: 0.56696416 | AV34: -1.5440256 | AW34: -0.97984591 | AX34: 7 | AY34: 26.341653 | AZ34: 29.679163 | BA34: 28.25428 | BB34: 3.5666667 | BC34: 3.36 | BD34: -0.033008933 | BE34: 18.427 | BF34: 16.0926 | BG34: 5.1666667 | BH34: 4.94 | BI34: 2.3 | BJ34: 2.45 | BK34: 2.0173333 | BL34: 1.7768 | BM34: 6 | BN34: -7.49 | BO34: -7.451 | BP34: -7.49 | BQ34: -0.038451268 | BR34: -11.88039 | BS34: 63 | BT34: 44 | BU34: 81 | BV34: 62.666667 | BW34: 2011 | BY34: =(AE34-Standardisation_Parameters!$E$15)/Standardisation_Parameters!$F$15 -> 1.3329854 | BZ34: =VLOOKUP($D34,$CH:$CN,2,FALSE) -> 0.51854447 | CA34: =VLOOKUP($D34,$CH:$CN,3,FALSE) -> 0.72814371 | CB34: =VLOOKUP($D34,$CH:$CN,5,FALSE) -> 0.66336389 | CC34: =VLOOKUP($D34,$CH:$CN,6,FALSE) -> 0.58542709 | CD34: =VLOOKUP($D34,$CH:$CN,4,FALSE) -> 0.49830675 | CF34: MOZAMBIQUE | CG34: LOW HUMAN DEVELOPMENT | CH34: MOZ | CI34: 0.46900275 | CJ34: 0.56957936 | CK34: 0.3121804 | CL34: 0.51547055 | CM34: 0.46620898 | CN34: 0.7878 | CP34: MOZAMBIQUE | CQ34: LOW HUMAN DEVELOPMENT | CR34: MOZ | CS34: MOZ2011 | CT34: 186 | CU34: 0.46900275 | CV34: 0.56957936 | CW34: 0.3121804 | CX34: 0.4662065 | CY34: 49.888889 | CZ34: 52.463443 | DA34: 52.510182 | DB34: 54.191325
B35: MONGOLIA | C35: MEDIUM HUMAN DEVELOPMENT | D35: MNG | E35: 9.2 | F35: 8.543 | G35: 11.9462 | H35: 6.3 | I35: 7.2172353 | L35: 6.7340316 | M35: 17.3 | N35: 2250 | O35: 118.42536 | P35: 2 | Q35: 4.4923378 | R35: 10.021495 | S35: -30.412 | T35: 13.472843 | U35: 33.924046 | V35: 1.6145412 | W35: -27.428607 | Y35: 29.91407 | Z35: 14.3 | AA35: 5 | AB35: 0.653 | AC35: 0.0034235453 | AD35: -0.42555826 | AE35: 48.63388 | AF35: 3.8590679 | AG35: 3.5 | AH35: 3 | AI35: 1.5 | AJ35: 0.657 | AK35: 0.9538 | AL35: 15.5 | AM35: 2.2034065 | AN35: 1.2272589 | AO35: 13.477013 | AP35: 30.064484 | AQ35: 3 | AR35: 78.343089 | AS35: 43.847788 | AT35: -3 | AU35: 2.4568447 | AV35: 8.126703 | AW35: -89.978505 | AX35: 1 | AY35: 113.6236 | AZ35: 40.283077 | BA35: 40.22735 | BB35: 3.7890513 | BC35: 3.2331094 | BD35: 0.014210795 | BE35: 17.207334 | BF35: 13.729574 | BG35: 7.3903333 | BH35: 8.2644 | BI35: 15.6 | BJ35: 9.9085 | BK35: 5.697 | BL35: 6.503 | BM35: 4 | BN35: -17.480667 | BP35: -11.015 | BS35: 73 | BT35: 69 | BU35: 94 | BV35: 78.666667 | BW35: 2011 | BY35: =(AE35-Standardisation_Parameters!$E$15)/Standardisation_Parameters!$F$15 -> 0.16668974 | BZ35: =VLOOKUP($D35,$CH:$CN,2,FALSE) -> 0.5208178 | CA35: =VLOOKUP($D35,$CH:$CN,3,FALSE) -> 0.33991617 | CB35: =VLOOKUP($D35,$CH:$CN,5,FALSE) -> 0.33897318 | CC35: =VLOOKUP($D35,$CH:$CN,6,FALSE) -> 0.37694471 | CD35: =VLOOKUP($D35,$CH:$CN,4,FALSE) -> 1.0832753 | CF35: MALAWI | CG35: LOW HUMAN DEVELOPMENT | CH35: MWI | CI35: 0.89283756 | CJ35: 0.20067696 | CK35: 0.73096469 | CL35: 0.33590943 | CM35: 0.55273433 | CN35: 0.8966 | CP35: MALAWI | CQ35: LOW HUMAN DEVELOPMENT | CR35: MWI | CS35: MWI2011 | CT35: 192 | CU35: 0.89283756 | CV35: 0.20067696 | CW35: 0.73096469 | CX35: 0.55273356 | CY35: 56.888889 | CZ35: 53.909747 | DA35: 59.594602 | DB35: 48.025103
B36: MOROCCO | C36: MEDIUM HUMAN DEVELOPMENT | D36: MAR | E36: 1.4 | F36: 1.1273333 | G36: 1.8262 | H36: 5.1 | I36: 1.1192353 | J36: 11.896 | K36: 25.06 | L36: 1.0896656 | M36: 4.3 | N36: 3020 | O36: 0.2420675 | P36: 3 | Q36: 5.2 | R36: 11.85159 | S36: -8.8 | T36: -8.1524725 | U36: 28.362052 | V36: 9.1 | W36: 9.1088244 | X36: -5.6 | Y36: 105.96807 | Z36: 3.294 | AA36: 6 | AB36: 0.582 | AC36: -0.76807488 | AD36: -0.18523994 | AE36: 62.84153 | AF36: 4.1648434 | AG36: 2.25 | AH36: 2.5 | AI36: 2.75 | AJ36: 0.27266667 | AK36: -0.7262 | AL36: 6.5 | AM36: 0.5804804 | AN36: 3.8597161 | AO36: 15.6 | AP36: 35.554769 | AQ36: 3 | AR36: 6.2710755 | AS36: 4.4377727 | AT36: 215.7 | AU36: 0.56593332 | AV36: -1.5463667 | AW36: -0.8814841 | AX36: 10 | AY36: 0.3736928 | AZ36: 27.870601 | BA36: 26.870448 | BB36: 9.4863333 | BC36: 10.0078 | BD36: -0.011186918 | BE36: 19.854 | BF36: 20.5518 | BG36: 4.2453333 | BH36: 4.2058 | BI36: 3.8 | BJ36: 3.0975 | BK36: 3.2363333 | BL36: 3.0964 | BM36: 6 | BN36: -6.4343333 | BO36: -8.8 | BP36: -6.4343333 | BQ36: 0.64730871 | BR36: -0.94164124 | BS36: 50 | BT36: 38 | BU36: 56 | BV36: 48 | BW36: 2011 | BY36: =(AE36-Standardisation_Parameters!$E$15)/Standardisation_Parameters!$F$15 -> 0.68065055 | BZ36: =VLOOKUP($D36,$CH:$CN,2,FALSE) -> 0.55962767 | CA36: =VLOOKUP($D36,$CH:$CN,3,FALSE) -> 0.48719568 | CB36: =VLOOKUP($D36,$CH:$CN,5,FALSE) -> 0.47414207 | CC36: =VLOOKUP($D36,$CH:$CN,6,FALSE) -> 0.48281415 | CD36: =VLOOKUP($D36,$CH:$CN,4,FALSE) -> 0.39194884 | CF36: NAMIBIA | CG36: MEDIUM HUMAN DEVELOPMENT | CH36: NAM | CI36: 0.44171025 | CJ36: -0.23900037 | CK36: -0.2993776 | CL36: -0.16992694 | CM36: 0.010374551 | CN36: 0.4614 | CP36: NAMIBIA | CQ36: MEDIUM HUMAN DEVELOPMENT | CR36: NAM | CS36: NAM2011 | CT36: 198 | CU36: 0.44171025 | CV36: -0.23900037 | CW36: -0.2993776 | CX36: 0.010374779 | CY36: 39.666667 | CZ36: 44.844193 | DA36: 52.053987 | DB36: 40.675875
B37: MOZAMBIQUE | C37: LOW HUMAN DEVELOPMENT | D37: MOZ | E37: 11.7 | F37: 9.2253333 | G37: 9.2334 | H37: 4.3 | I37: 4.1484704 | J37: 38.029 | K37: 36.936 | L37: 0.35380475 | M37: 7.2 | N37: 496 | O37: 3.7155147 | P37: 3 | Q37: 6 | R37: 24.917857 | S37: -12 | T37: -3.5467565 | U37: 42.609099 | V37: 3.8 | W37: -0.0043112488 | X37: -36.3 | Y37: 24.06576 | Z37: 9 | AA37: 3 | AB37: 0.322 | AC37: -0.1187054 | AD37: -0.50045857 | AE37: 72.131148 | AF37: 3.3110222 | AG37: 3.5 | AH37: 3.25 | AI37: 3.75 | AJ37: 2.4746667 | AK37: -2.2334 | AL37: 16 | AM37: 1.6768443 | AN37: 19.760617 | AO37: 18 | AP37: 74.753571 | AQ37: 3 | AR37: 47.110029 | AS37: 32.730323 | AT37: 86 | AU37: 1.5462659 | AV37: 12.512091 | AW37: -0.75082143 | AX37: 0 | AY37: 3.7325829 | AZ37: 43.996943 | BA37: 40.756344 | BB37: 3.3723333 | BC37: 2.8594 | BD37: -0.041951575 | BE37: 17.406 | BF37: 15.7452 | BG37: 6.947 | BH37: 6.9914 | BI37: 4.7 | BJ37: 4.55 | BK37: 4.3303333 | BL37: 4.409 | BM37: 4 | BN37: -11.467 | BO37: -12 | BP37: -11.467 | BQ37: 0.034185053 | BR37: -12.109607 | BS37: 65 | BT37: 38 | BU37: 63 | BV37: 55.333333 | BW37: 2011 | BY37: =(AE37-Standardisation_Parameters!$E$15)/Standardisation_Parameters!$F$15 -> 1.0167018 | BZ37: =VLOOKUP($D37,$CH:$CN,2,FALSE) -> 0.46900275 | CA37: =VLOOKUP($D37,$CH:$CN,3,FALSE) -> 0.56957936 | CB37: =VLOOKUP($D37,$CH:$CN,5,FALSE) -> 0.51547055 | CC37: =VLOOKUP($D37,$CH:$CN,6,FALSE) -> 0.46620898 | CD37: =VLOOKUP($D37,$CH:$CN,4,FALSE) -> 0.3121804 | CF37: NIGERIA | CG37: LOW HUMAN DEVELOPMENT | CH37: NGA | CI37: 0.67076433 | CJ37: 1.3814198 | CK37: 1.455528 | CL37: 1.256841 | CM37: 1.0415738 | CN37: 0.7878 | CP37: NIGERIA | CQ37: LOW HUMAN DEVELOPMENT | CR37: NGA | CS37: NGA2011 | CT37: 204 | CU37: 0.67076433 | CV37: 1.3814198 | CW37: 1.455528 | CX37: 1.0415688 | CY37: 69 | CZ37: 62.080651 | DA37: 55.882637 | DB37: 67.761278
B38: NAMIBIA | C38: MEDIUM HUMAN DEVELOPMENT | D38: NAM | E38: 5 | F38: 6.084 | G38: 7.0646 | H38: 3.8 | I38: 1.5184794 | J38: 17.4 | L38: 2.6727606 | M38: 4.2 | N38: 5850 | O38: 0.63168888 | P38: 3 | Q38: 3.5 | R38: 46.962457 | S38: -0.8 | T38: 5.8245587 | U38: 34.370881 | V38: 7.7 | W38: 40.432602 | X38: 16.3 | Y38: 48.429313 | Z38: 4.6 | AA38: 3 | AB38: 0.625 | AC38: 0.33474917 | AD38: 0.22973382 | AE38: 40.437158 | AF38: 3.9982167 | AG38: 2.5 | AH38: 2 | AI38: 1.5 | AJ38: -1.084 | AK38: -1.6646 | AL38: 8.8 | AM38: 2.0746855 | AN38: 1.4303563 | AO38: 10.5 | AP38: 140.88737 | AQ38: 3 | AR38: 9.3492779 | AS38: 26.721949 | AT38: 808.3 | AU38: 0.79031368 | AV38: 3.0179543 | AW38: -0.53037543 | AX38: 3 | AY38: 0.89246641 | AZ38: 28.89176 | BA38: 26.257334 | BB38: 7.0296667 | BC38: 8.0186 | BD38: 0.022310835 | BE38: 11.013 | BF38: 10.4976 | BG38: 3.4556667 | BH38: 3.823 | BI38: 3 | BJ38: 3.8005 | BK38: 1.5626667 | BL38: 1.8962 | BM38: 4 | BN38: -1.8033333 | BO38: -0.8 | BP38: -1.8033333 | BQ38: -1.1195933 | BR38: 0.043686007 | BS38: 43 | BT38: 38 | BU38: 38 | BV38: 39.666667 | BW38: 2011 | BY38: =(AE38-Standardisation_Parameters!$E$15)/Standardisation_Parameters!$F$15 -> -0.1298261 | BZ38: =VLOOKUP($D38,$CH:$CN,2,FALSE) -> 0.44171025 | CA38: =VLOOKUP($D38,$CH:$CN,3,FALSE) -> -0.23900037 | CB38: =VLOOKUP($D38,$CH:$CN,5,FALSE) -> -0.16992694 | CC38: =VLOOKUP($D38,$CH:$CN,6,FALSE) -> 0.010374551 | CD38: =VLOOKUP($D38,$CH:$CN,4,FALSE) -> -0.2993776 | CF38: NICARAGUA | CG38: MEDIUM HUMAN DEVELOPMENT | CH38: NIC | CI38: 1.0112186 | CJ38: 0.86954658 | CK38: 0.71766995 | CL38: 0.93211731 | CM38: 0.99447537 | CN38: 0.7878 | CP38: NICARAGUA | CQ38: MEDIUM HUMAN DEVELOPMENT | CR38: NIC | CS38: NIC2011 | CT38: 210 | CU38: 1.0112186 | CV38: 0.86954658 | CW38: 0.71766995 | CX38: 0.99447248 | CY38: 56.666667 | CZ38: 61.293435 | DA38: 61.573347 | DB38: 59.205292
B39: NICARAGUA | C39: MEDIUM HUMAN DEVELOPMENT | D39: NIC | E39: 8.08 | F39: 5.7406667 | G39: 9.635 | H39: 1.92 | I39: 6.5819817 | J39: 30.913 | K39: 61.098 | L39: 2.481738 | M39: 4.6 | N39: 1020 | O39: 1.571686 | P39: 4 | Q39: 3.4 | R39: 37.145877 | S39: -18 | T39: -7.0582227 | U39: 74.743908 | V39: 11.6 | W39: -0.58996273 | X39: -2.059 | Y39: 63.477821 | Z39: 4.5 | AA39: 6 | AB39: 0.589 | AC39: -0.47879647 | AD39: -0.82778531 | AE39: 66.666667 | AF39: 3.6115661 | AG39: 3.5 | AH39: 3.75 | AI39: 3 | AJ39: 2.3393333 | AK39: -1.335 | AL39: 10 | AM39: 1.5656883 | AN39: 1.1292087 | AO39: 10.2 | AP39: 111.43763 | AQ39: 3 | AR39: 12.591331 | AS39: 20.416576 | AT39: 39 | AU39: 0.77313295 | AV39: 21.550804 | AW39: -0.62854123 | AX39: 3 | AY39: 1.4704126 | AZ39: 74.722538 | BA39: 71.125908 | BB39: 12.660333 | BC39: 12.3878 | BD39: 0.053418265 | BE39: 11.463 | BF39: 10.092 | BG39: 2.537 | BH39: 2.8024 | BI39: 2 | BJ39: 1.9 | BK39: -0.066666667 | BL39: 0.18 | BM39: 7 | BN39: -15.421667 | BO39: -18 | BP39: -15.421667 | BQ39: 0.19835729 | BR39: -27.42685 | BS39: 73 | BT39: 50 | BU39: 69 | BV39: 64 | BW39: 2011 | BY39: =(AE39-Standardisation_Parameters!$E$15)/Standardisation_Parameters!$F$15 -> 0.81902461 | BZ39: =VLOOKUP($D39,$CH:$CN,2,FALSE) -> 1.0112186 | CA39: =VLOOKUP($D39,$CH:$CN,3,FALSE) -> 0.86954658 | CB39: =VLOOKUP($D39,$CH:$CN,5,FALSE) -> 0.93211731 | CC39: =VLOOKUP($D39,$CH:$CN,6,FALSE) -> 0.99447537 | CD39: =VLOOKUP($D39,$CH:$CN,4,FALSE) -> 0.71766995 | CF39: PAKISTAN | CG39: LOW HUMAN DEVELOPMENT | CH39: PAK | CI39: 1.4405128 | CJ39: 1.0910148 | CK39: 1.2694016 | CL39: 1.2485723 | CM39: 1.4040547 | CN39: 0.5702 | CP39: PAKISTAN | CQ39: LOW HUMAN DEVELOPMENT | CR39: PAK | CS39: PAK2011 | CT39: 216 | CU39: 1.4405128 | CV39: 1.0910148 | CW39: 1.2694016 | CX39: 1.4040515 | CY39: 65.888889 | CZ39: 68.139568 | DA39: 68.74902 | DB39: 62.907144
B40: NIGERIA | C40: LOW HUMAN DEVELOPMENT | D40: NGA | E40: 10.9 | F40: 12.052667 | G40: 10.6236 | H40: 5.6 | I40: 3.1649626 | J40: 88.3 | K40: 36.085 | L40: 0.73900352 | M40: 7.4 | N40: 1570 | O40: 16.1165 | P40: 2 | Q40: 4.3 | R40: 18.105683 | S40: 5.3 | T40: 7.8074302 | U40: 5.0068555 | V40: 0.4 | W40: 8.1143828 | X40: 4.471 | Y40: 34.696847 | Z40: 8.5 | AA40: 6 | AB40: 0.459 | AC40: -0.82320984 | AD40: -1.2057694 | AE40: 72.677596 | AF40: 3.4455741 | AG40: 4.25 | AH40: 4.25 | AI40: 4.25 | AJ40: -1.1526667 | AK40: 1.6764 | AL40: 16.5 | AM40: 1.090619 | AN40: 9.3745156 | AO40: 12.9 | AP40: 54.31705 | AQ40: 3 | AR40: 36.577473 | AS40: 18.473994 | AT40: 280 | AU40: 1.4603622 | AV40: 22.33142 | AW40: -0.81894317 | AX40: 0 | AY40: 14.893687 | AZ40: 4.768453 | BA40: 5.0040782 | BB40: 0.53333333 | BC40: 0.76 | BE40: 20.687 | BF40: 26.28 | BG40: 7.402 | BH40: 6.9278 | BI40: -2.9 | BJ40: -1.4 | BK40: -4.4666667 | BL40: -2.4 | BM40: 6 | BN40: 4.7753333 | BO40: 5.3 | BP40: 4.7753333 | BQ40: 0.84559542 | BR40: 1.0037717 | BS40: 83 | BT40: 44 | BU40: 88 | BV40: 71.666667 | BW40: 2011 | BY40: =(AE40-Standardisation_Parameters!$E$15)/Standardisation_Parameters!$F$15 -> 1.0364696 | BZ40: =VLOOKUP($D40,$CH:$CN,2,FALSE) -> 0.67076433 | CA40: =VLOOKUP($D40,$CH:$CN,3,FALSE) -> 1.3814198 | CB40: =VLOOKUP($D40,$CH:$CN,5,FALSE) -> 1.256841 | CC40: =VLOOKUP($D40,$CH:$CN,6,FALSE) -> 1.0415738 | CD40: =VLOOKUP($D40,$CH:$CN,4,FALSE) -> 1.455528 | CF40: PHILIPPINES | CG40: MEDIUM HUMAN DEVELOPMENT | CH40: PHL | CI40: 0.54127194 | CJ40: 0.79470677 | CK40: 0.57142782 | CL40: 0.72603655 | CM40: 0.63677629 | CN40: 0.7878 | CP40: PHILIPPINES | CQ40: MEDIUM HUMAN DEVELOPMENT | CR40: PHL | CS40: PHL2011 | CT40: 222 | CU40: 0.54127194 | CV40: 0.79470677 | CW40: 0.57142782 | CX40: 0.63677314 | CY40: 54.222222 | CZ40: 55.314472 | DA40: 53.718165 | DB40: 57.954341
B41: PAKISTAN | C41: LOW HUMAN DEVELOPMENT | D41: PAK | E41: 11.916 | F41: 12.333 | G41: 12.8724 | H41: 2.199 | I41: 4.1136786 | J41: 10.632 | K41: 15.829 | L41: 1.5904237 | M41: 2.357 | N41: 1120 | O41: 11.004435 | P41: 5 | Q41: 4.8 | R41: 19.77124 | S41: -0.7 | T41: -0.15172904 | U41: 27.744671 | V41: 10.3 | W41: -17.753886 | X41: 6.9 | Y41: 46.276453 | Z41: 12.473 | AA41: 7 | AB41: 0.504 | AC41: -0.81606361 | AD41: -0.78557066 | AE41: 52.459016 | AF41: 3.5788048 | AG41: 4 | AH41: 3.75 | AI41: 4.5 | AJ41: -0.417 | AK41: -4.8724 | AL41: 14.115 | AM41: 1.4736316 | AN41: 2.1849524 | AO41: 14.4 | AP41: 59.313719 | AQ41: 3 | AR41: 12.361604 | AS41: 15.624916 | AT41: 163.4 | AU41: 2.1429527 | AV41: 42.149325 | AW41: -0.8022876 | AX41: 0 | AY41: 10.654911 | AZ41: 31.196585 | BA41: 30.489733 | BB41: 10.666667 | BC41: 9.9834 | BD41: 0.15446577 | BE41: 14.666 | BF41: 13.1424 | BG41: 3.3653333 | BH41: 3.475 | BI41: 1.117 | BJ41: 1.408 | BK41: 1.5196667 | BL41: 1.6274 | BM41: 8 | BN41: -1.3366667 | BO41: -0.7 | BP41: -1.3366667 | BQ41: -0.10698254 | BR41: 0.45083956 | BS41: 60 | BT41: 56 | BU41: 78 | BV41: 64.666667 | BW41: 2011 | BY41: =(AE41-Standardisation_Parameters!$E$15)/Standardisation_Parameters!$F$15 -> 0.30506381 | BZ41: =VLOOKUP($D41,$CH:$CN,2,FALSE) -> 1.4405128 | CA41: =VLOOKUP($D41,$CH:$CN,3,FALSE) -> 1.0910148 | CB41: =VLOOKUP($D41,$CH:$CN,5,FALSE) -> 1.2485723 | CC41: =VLOOKUP($D41,$CH:$CN,6,FALSE) -> 1.4040547 | CD41: =VLOOKUP($D41,$CH:$CN,4,FALSE) -> 1.2694016 | CF41: PAPUA NEW GUINEA | CG41: LOW HUMAN DEVELOPMENT | CH41: PNG | CI41: 0.61320825 | CJ41: 1.0428236 | CK41: 0.77084891 | CL41: 0.95575125 | CM41: 0.81955532 | CN41: 0.5702 | CP41: PAPUA NEW GUINEA | CQ41: LOW HUMAN DEVELOPMENT | CR41: PNG | CS41: PNG2011 | CT41: 228 | CU41: 0.61320825 | CV41: 1.0428236 | CW41: 0.77084891 | CX41: 0.8195514 | CY41: 57.555556 | CZ41: 58.36962 | DA41: 54.920584 | DB41: 62.101625
B42: PALESTINIAN TERRITORY, OCCUPIED | C42: MEDIUM HUMAN DEVELOPMENT | D42: PSE | E42: 5 | F42: 4.5 | G42: 5.1914 | H42: 2.3 | I42: 3.2353164 | L42: 1.219553 | M42: 4 | N42: 2380 | O42: 0 | Q42: 2.0791327 | U42: 38.453954 | W42: -26.923178 | Z42: 4.8 | AC42: -0.8531581 | AD42: -0.20494924 | AE42: 69.945355 | AG42: 4.5 | AH42: 4.25 | AI42: 4 | AJ42: 0.5 | AL42: 7.3 | AM42: 0.31943575 | AN42: 2.661631 | AO42: 6.237398 | AQ42: 3 | AR42: 17.496591 | AS42: 2.5484584 | AT42: 160 | AU42: 0.82467515 | AV42: 0 | AX42: 0 | AZ42: 44.64172 | BA42: 47.671133 | BE42: 6.6192985 | BF42: 6.1611978 | BG42: 3 | BH42: 3.246 | BI42: 7.7 | BJ42: 7 | BK42: 6.2333333 | BL42: 4.9232 | BS42: 35 | BT42: 19 | BU42: 88 | BV42: 47.333333 | BW42: 2011 | BY42: =(AE42-Standardisation_Parameters!$E$15)/Standardisation_Parameters!$F$15 -> 0.93763095 | BZ42: =VLOOKUP($D42,$CH:$CN,2,FALSE) -> #N/A | CA42: =VLOOKUP($D42,$CH:$CN,3,FALSE) -> #N/A | CB42: =VLOOKUP($D42,$CH:$CN,5,FALSE) -> #N/A | CC42: =VLOOKUP($D42,$CH:$CN,6,FALSE) -> #N/A | CD42: =VLOOKUP($D42,$CH:$CN,4,FALSE) -> #N/A | CF42: RWANDA | CG42: LOW HUMAN DEVELOPMENT | CH42: RWA | CI42: 0.59768133 | CJ42: 0.53268116 | CK42: 0.63125414 | CL42: 0.52384238 | CM42: 0.5331063 | CN42: 0.4614 | CP42: RWANDA | CQ42: LOW HUMAN DEVELOPMENT | CR42: RWA | CS42: RWA2011 | CT42: 234 | CU42: 0.59768133 | CV42: 0.53268116 | CW42: 0.63125414 | CX42: 0.53310409 | CY42: 55.222222 | CZ42: 53.581639 | DA42: 54.661051 | DB42: 53.57457
B43: PAPUA NEW GUINEA | C43: LOW HUMAN DEVELOPMENT | D43: PNG | E43: 8.7 | F43: 7.219 | G43: 6.6562 | H43: 2.2 | I43: 3.7813628 | J43: 40.843 | K43: 46.184 | L43: 1.344247 | M43: 9.2 | N43: 1910 | O43: 0.21796272 | P43: 2 | Q43: 5 | R43: 5.637154 | S43: -35.6 | T43: -32.533304 | U43: 27.507401 | V43: 13.7 | W43: 51.868236 | X43: 16.5 | Y43: 35.684395 | Z43: 6.4 | AA43: 7 | AB43: 0.466 | AC43: 0.072118584 | AD43: -0.93236536 | AE43: 53.005464 | AG43: 3.5 | AH43: 2.75 | AI43: 3.75 | AJ43: 1.481 | AK43: -0.0562 | AL43: 10.9 | AM43: 0.64686165 | AN43: 5.2966456 | AO43: 15 | AP43: 16.911462 | AQ43: 3 | AR43: 33.65791 | AS43: 6.326307 | AT43: 480 | AU43: 1.0995669 | AV43: -20.444231 | AW43: -0.94362846 | AX43: 3 | AY43: 0.21860464 | AZ43: 28.646943 | BA43: 25.403138 | BB43: 12.9 | BC43: 14.7066 | BD43: -0.065533809 | BE43: 17.599 | BF43: 16.7142 | BG43: 7.2666667 | BH43: 7.12 | BI43: 8.6 | BJ43: 6.85 | BK43: 5.6 | BL43: 5.14 | BM43: 5 | BN43: -18.233333 | BO43: -35.6 | BP43: -18.233333 | BQ43: 1.4478976 | BR43: -24.264653 | BS43: 48 | BT43: 44 | BU43: 81 | BV43: 57.666667 | BW43: 2011 | BY43: =(AE43-Standardisation_Parameters!$E$15)/Standardisation_Parameters!$F$15 -> 0.32483153 | BZ43: =VLOOKUP($D43,$CH:$CN,2,FALSE) -> 0.61320825 | CA43: =VLOOKUP($D43,$CH:$CN,3,FALSE) -> 1.0428236 | CB43: =VLOOKUP($D43,$CH:$CN,5,FALSE) -> 0.95575125 | CC43: =VLOOKUP($D43,$CH:$CN,6,FALSE) -> 0.81955532 | CD43: =VLOOKUP($D43,$CH:$CN,4,FALSE) -> 0.77084891 | CF43: SUDAN | CG43: LOW HUMAN DEVELOPMENT | CH43: SDN | CI43: 1.4573081 | CJ43: 1.3814198 | CK43: 1.6416543 | CL43: 1.4968699 | CM43: 1.57249 | CN43: 0.7878 | CP43: SUDAN | CQ43: LOW HUMAN DEVELOPMENT | CR43: SDN | CS43: SDN2011 | CT43: 240 | CU43: 1.4573081 | CV43: 1.3814198 | CW43: 1.6416543 | CX43: 1.5724858 | CY43: 72.111111 | CZ43: 70.954956 | DA43: 69.029755 | DB43: 67.761278
B44: PHILIPPINES | C44: MEDIUM HUMAN DEVELOPMENT | D44: PHL | E44: 4.768 | F44: 4.0373333 | G44: 4.836 | H44: 2.032 | I44: 2.615743 | J44: 60.427 | K44: 15.219 | L44: 2.5564128 | M44: 3.718 | N44: 2210 | O44: 1.6822154 | P44: 2 | Q44: 12 | R44: 8.688555 | S44: 2.1 | T44: 2.4351947 | U44: 32.275017 | V44: 11.9 | W44: -13.922857 | X44: 11 | Y44: 49.231661 | Z44: 1.348 | AA44: 6 | AB44: 0.644 | AC44: -0.092479687 | AD44: -0.54157661 | AE44: 73.224044 | AF44: 4.082931 | AG44: 2.5 | AH44: 2.25 | AI44: 3.75 | AJ44: 0.73066667 | AK44: -1.136 | AL44: 6.8 | AM44: 0.84594545 | AN44: 1.8203633 | AO44: 36 | AP44: 26.065665 | AQ44: 3 | AR44: 15.47212 | AS44: 7.3521119 | AT44: 210 | AU44: 0.23159627 | AV44: -6.1437494 | AW44: -0.91311445 | AX44: 10 | AY44: 2.2532048 | AZ44: 35.337807 | BA44: 37.507832 | BB44: 13.044333 | BC44: 13.2914 | BD44: 0.34854462 | BE44: 31.826 | BF44: 26.6892 | BG44: 4.166 | BH44: 4.6536 | BI44: 1.9 | BJ44: 3.75 | BK44: 2.2333333 | BL44: 2.66 | BM44: 5 | BN44: 4.0433333 | BO44: 2.1 | BP44: 4.0433333 | BQ44: -0.58639736 | BR44: 0.35428172 | BS44: 58 | BT44: 38 | BU44: 63 | BV44: 53 | BW44: 2011 | BY44: =(AE44-Standardisation_Parameters!$E$15)/Standardisation_Parameters!$F$15 -> 1.0562373 | BZ44: =VLOOKUP($D44,$CH:$CN,2,FALSE) -> 0.54127194 | CA44: =VLOOKUP($D44,$CH:$CN,3,FALSE) -> 0.79470677 | CB44: =VLOOKUP($D44,$CH:$CN,5,FALSE) -> 0.72603655 | CC44: =VLOOKUP($D44,$CH:$CN,6,FALSE) -> 0.63677629 | CD44: =VLOOKUP($D44,$CH:$CN,4,FALSE) -> 0.57142782 | CF44: SENEGAL | CG44: LOW HUMAN DEVELOPMENT | CH44: SEN | CI44: 0.71871702 | CJ44: 0.67995247 | CK44: 0.50495412 | CL44: 0.68409717 | CM44: 0.69447365 | CN44: 1.0054 | CP44: SENEGAL | CQ44: LOW HUMAN DEVELOPMENT | CR44: SEN | CS44: SEN2011 | CT44: 246 | CU44: 0.71871702 | CV44: 0.67995247 | CW44: 0.50495412 | CX44: 0.69447107 | CY44: 53.111111 | CZ44: 56.278896 | DA44: 56.684168 | DB44: 56.036217
B45: RWANDA | C45: LOW HUMAN DEVELOPMENT | D45: RWA | E45: 3.9 | F45: 5.5253333 | G45: 8.22 | H45: 12.4 | I45: 5.4293269 | J45: 22 | K45: 34.49 | L45: 2.7802609 | M45: 8.8 | N45: 546 | O45: 22.700968 | Q45: 5.7 | R45: 1.8120972 | S45: -11.9 | T45: -10.682968 | U45: 16.346124 | W45: 14.155902 | X45: -6.1 | Z45: 7.5 | AB45: 0.429 | AC45: -1.3349287 | AD45: -0.31210192 | AE45: 27.322404 | AF45: 4.1881739 | AG45: 3.75 | AH45: 4 | AI45: 3.75 | AJ45: -1.6253333 | AK45: -1.72 | AL45: 16.3 | AM45: 0.26953794 | AN45: 2.6688143 | AO45: 17.1 | AP45: 5.4362916 | AQ45: 3 | AR45: 37.560084 | AS45: 4.3123375 | AT45: 25 | AU45: 1.2885549 | AV45: 9.6883469 | AW45: -98.187903 | AX45: 2 | AY45: 21.531034 | AZ45: 14.927472 | BA45: 14.76061 | BB45: 4.068 | BC45: 4.1226667 | BE45: 17.665 | BF45: 18.042 | BG45: 6.8 | BH45: 7.42 | BI45: 5.4 | BJ45: 4.8665 | BK45: 3.5776667 | BL45: 4.2486 | BN45: -8.9473333 | BO45: -11.9 | BP45: -8.9473333 | BQ45: 0.48059012 | BR45: -40.513819 | BS45: 65 | BT45: 44 | BU45: 78 | BV45: 62.333333 | BW45: 2011 | BY45: =(AE45-Standardisation_Parameters!$E$15)/Standardisation_Parameters!$F$15 -> -0.60425146 | BZ45: =VLOOKUP($D45,$CH:$CN,2,FALSE) -> 0.59768133 | CA45: =VLOOKUP($D45,$CH:$CN,3,FALSE) -> 0.53268116 | CB45: =VLOOKUP($D45,$CH:$CN,5,FALSE) -> 0.52384238 | CC45: =VLOOKUP($D45,$CH:$CN,6,FALSE) -> 0.5331063 | CD45: =VLOOKUP($D45,$CH:$CN,4,FALSE) -> 0.63125414 | CF45: SIERRA LEONE | CG45: LOW HUMAN DEVELOPMENT | CH45: SLE | CI45: 1.1590526 | CJ45: 1.12354 | CK45: 0.85726471 | CL45: 1.1899145 | CM45: 1.2316643 | CN45: 0.8966 | CP45: SIERRA LEONE | CQ45: LOW HUMAN DEVELOPMENT | CR45: SLE | CS45: SLE2011 | CT45: 249 | CU45: 1.1590526 | CV45: 1.12354 | CW45: 0.85726471 | CX45: 1.2316607 | CY45: 59 | CZ45: 65.258048 | DA45: 64.0444 | DB45: 63.450805
B46: SENEGAL | C46: LOW HUMAN DEVELOPMENT | D46: SEN | E46: 3.439 | F46: 1.206 | G46: 3.0482 | H46: 11.061 | I46: 2.7527493 | J46: 11.917 | K46: 25.176 | L46: 2.1330931 | M46: -0.5 | N46: 978 | O46: 17.022231 | P46: 3 | Q46: 4.7 | R46: 1.637827 | S46: -13.1 | T46: -10.422055 | U46: 34.262371 | V46: 8.3 | W46: 15.122115 | X46: -5.9 | Y46: 29.014121 | Z46: 3.285 | AA46: 5 | AB46: 0.459 | AC46: -0.31493892 | AD46: -0.40512907 | AE46: 85.79235 | AF46: 3.6969522 | AG46: 2.5 | AH46: 2.5 | AI46: 3 | AJ46: 2.233 | AK46: -0.5482 | AL46: 14.5 | AM46: 0.27386128 | AN46: 1.3393696 | AO46: 14.1 | AP46: 4.9134809 | AQ46: 3 | AR46: 25.179398 | AS46: 4.1079192 | AT46: 56.2 | AU46: 0.56438705 | AV46: -1.4388489 | AW46: -0.98362173 | AX46: 2 | AY46: 26.341653 | AZ46: 32.22801 | BA46: 28.283681 | BB46: 5.8043333 | BC46: 5.0266 | BD46: -0.17939532 | BE46: 13.929 | BF46: 12.213 | BG46: 1.9083333 | BH46: 2.857 | BI46: -0.1 | BJ46: 0.681 | BK46: 0.282 | BL46: 0.791 | BM46: 7 | BN46: -10.782667 | BO46: -13.1 | BP46: -10.782667 | BQ46: 0.11128972 | BR46: -15.765755 | BS46: 73 | BT46: 44 | BU46: 75 | BV46: 64 | BW46: 2011 | BY46: =(AE46-Standardisation_Parameters!$E$15)/Standardisation_Parameters!$F$15 -> 1.5108949 | BZ46: =VLOOKUP($D46,$CH:$CN,2,FALSE) -> 0.71871702 | CA46: =VLOOKUP($D46,$CH:$CN,3,FALSE) -> 0.67995247 | CB46: =VLOOKUP($D46,$CH:$CN,5,FALSE) -> 0.68409717 | CC46: =VLOOKUP($D46,$CH:$CN,6,FALSE) -> 0.69447365 | CD46: =VLOOKUP($D46,$CH:$CN,4,FALSE) -> 0.50495412 | CF46: EL SALVADOR | CG46: MEDIUM HUMAN DEVELOPMENT | CH46: SLV | CI46: 0.20464658 | CJ46: 0.80721152 | CK46: 0.29223829 | CL46: 0.63377979 | CM46: 0.41631915 | CN46: 0.679 | CP46: EL SALVADOR | CQ46: MEDIUM HUMAN DEVELOPMENT | CR46: SLV | CS46: SLV2011 | CT46: 255 | CU46: 0.20464658 | CV46: 0.80721152 | CW46: 0.29223829 | CX46: 0.41631559 | CY46: 49.555556 | CZ46: 51.629514 | DA46: 48.091456 | DB46: 58.163358
B47: SIERRA LEONE | C47: LOW HUMAN DEVELOPMENT | D47: SLE | E47: 18 | F47: 14.629 | G47: 14.0756 | H47: 3 | I47: 4.7293329 | J47: 32.433 | K47: 25.071 | L47: 1.2121602 | M47: 5.6 | N47: 326 | O47: 606.02629 | P47: 4 | Q47: 5.2 | R47: 0.61394892 | S47: -48.3 | T47: -43.084016 | U47: 27.843238 | V47: 25 | W47: 17.222476 | X47: -2 | Y47: 18.404146 | Z47: 24.05 | AA47: 7 | AB47: 0.336 | AC47: -0.17574297 | AD47: -0.94036377 | AE47: 81.967213 | AG47: 3.75 | AH47: 4 | AI47: 4 | AJ47: 3.371 | AK47: -5.5756 | AL47: 21 | AM47: 1.8552709 | AN47: 4.2448185 | AO47: 15.6 | AP47: 1.8418468 | AQ47: 3 | AR47: 63.108218 | AS47: 46.381772 | AT47: 1 | AU47: 4.1319661 | AV47: 45.254741 | AW47: -0.99386051 | AX47: 0 | AY47: 577.05377 | AZ47: 25.766658 | BA47: 23.288837 | BB47: 13.166667 | BC47: 8.4 | BD47: -0.27004567 | BE47: 18.441 | BF47: 16.8828 | BG47: 4.5826667 | BH47: 5.1454 | BI47: 3 | BJ47: 2.8 | BK47: 2.172 | BL47: 2.6082 | BM47: 7 | BN47: -29.716667 | BO47: -48.3 | BP47: -29.716667 | BQ47: 0.77444756 | BR47: -355.82638 | BS47: 70 | BT47: 38 | BU47: 88 | BV47: 65.333333 | BW47: 2011 | BY47: =(AE47-Standardisation_Parameters!$E$15)/Standardisation_Parameters!$F$15 -> 1.3725209 | BZ47: =VLOOKUP($D47,$CH:$CN,2,FALSE) -> 1.1590526 | CA47: =VLOOKUP($D47,$CH:$CN,3,FALSE) -> 1.12354 | CB47: =VLOOKUP($D47,$CH:$CN,5,FALSE) -> 1.1899145 | CC47: =VLOOKUP($D47,$CH:$CN,6,FALSE) -> 1.2316643 | CD47: =VLOOKUP($D47,$CH:$CN,4,FALSE) -> 0.85726471 | CF47: SWAZILAND | CG47: MEDIUM HUMAN DEVELOPMENT | CH47: SWZ | CI47: 0.99171521 | CJ47: 0.57950336 | CK47: 0.79743839 | CL47: 0.6832962 | CM47: 0.82440784 | CN47: 0.7878 | CP47: SWAZILAND | CQ47: MEDIUM HUMAN DEVELOPMENT | CR47: SWZ | CS47: SWZ2011 | CT47: 261 | CU47: 0.99171521 | CV47: 0.57950336 | CW47: 0.79743839 | CX47: 0.82440591 | CY47: 58 | CZ47: 58.450763 | DA47: 61.247347 | DB47: 54.357205
B48: SOUTH AFRICA | C48: MEDIUM HUMAN DEVELOPMENT | D48: ZAF | E48: 5.039 | F48: 5.4456667 | G48: 6.5196 | H48: 3.961 | I48: 1.1783418 | J48: 11.445 | K48: 12.698 | L48: 2.6029336 | M48: 3.1 | N48: 8270 | O48: 0.63168888 | P48: 1 | Q48: 5.1 | R48: 39.845052 | S48: -4.2 | T48: -2.9253634 | U48: 11.645622 | V48: 5.7 | W48: -21.24897 | X48: 8.629 | Y48: 182.24237 | Z48: 5.287 | AA48: 3 | AB48: 0.619 | AC48: 0.52635949 | AD48: 0.097393132 | AE48: 19.672131 | AF48: 4.3420593 | AG48: 2.25 | AH48: 2 | AI48: 3.25 | AJ48: -0.40666667 | AK48: -1.2196 | AL48: 9 | AM48: 2.4817478 | AN48: 1.0465115 | AO48: 15.3 | AP48: 119.53516 | AQ48: 3 | AR48: 8.2283611 | AS48: 32.677174 | AT48: 860 | AU48: 0.90834531 | AV48: 3.0179543 | AW48: -0.60154948 | AX48: 3 | AY48: 0.89246641 | AZ48: 12.969888 | BA48: 13.892558 | BB48: 5.3346667 | BC48: 5.1372 | BD48: 0.20094104 | BE48: 16.234 | BF48: 14.4402 | BG48: 1.4843333 | BH48: 2.724 | BI48: 3.3 | BJ48: 3.05 | BK48: 1.3403333 | BL48: 2.2682 | BM48: 4 | BN48: -3.6533333 | BO48: -4.2 | BP48: -3.6533333 | BQ48: 0.38841241 | BR48: 0.8995422 | BS48: 40 | BT48: 31 | BU48: 63 | BV48: 44.666667 | BW48: 2011 | BY48: =(AE48-Standardisation_Parameters!$E$15)/Standardisation_Parameters!$F$15 -> -0.88099958 | BZ48: =VLOOKUP($D48,$CH:$CN,2,FALSE) -> 0.22652597 | CA48: =VLOOKUP($D48,$CH:$CN,3,FALSE) -> -0.14316747 | CB48: =VLOOKUP($D48,$CH:$CN,5,FALSE) -> -0.15534834 | CC48: =VLOOKUP($D48,$CH:$CN,6,FALSE) -> -0.083032511 | CD48: =VLOOKUP($D48,$CH:$CN,4,FALSE) -> 0.052932988 | CF48: TOGO | CG48: LOW HUMAN DEVELOPMENT | CH48: TGO | CI48: 0.74444912 | CJ48: 0.98304109 | CK48: 0.8373226 | CL48: 0.94574273 | CM48: 0.87580263 | CN48: 1.0054 | CP48: TOGO | CQ48: LOW HUMAN DEVELOPMENT | CR48: TGO | CS48: TGO2011 | CT48: 266 | CU48: 0.74444912 | CV48: 0.98304109 | CW48: 0.8373226 | CX48: 0.87579906 | CY48: 58.666667 | CZ48: 59.309803 | DA48: 57.114282 | DB48: 61.102358
B49: SRI LANKA | C49: MEDIUM HUMAN DEVELOPMENT | D49: LKA | E49: 7.008 | F49: 5.4556667 | G49: 10.9548 | H49: 2.292 | I49: 5.8095364 | J49: 42.166 | K49: 20.731 | L49: 1.8495343 | M49: 8 | N49: 2880 | O49: 2.5485512 | P49: 2 | Q49: 4.2 | R49: 58.667688 | S49: -7.1 | T49: -5.4757494 | U49: 38.405524 | V49: 10.4 | W49: -6.1418702 | X49: 10.413 | Y49: 40.490482 | Z49: 8 | AA49: 5 | AB49: 0.691 | AC49: -0.50845292 | AD49: -0.087576306 | AE49: 53.551913 | AF49: 4.327236 | AG49: 3.25 | AH49: 2.75 | AI49: 3 | AJ49: 1.5523333 | AK49: -5.8548 | AL49: 9.3 | AM49: 4.2513727 | AN49: 3.4924466 | AO49: 12.6 | AP49: 176.00306 | AQ49: 3 | AR49: 7.1863966 | AS49: 72.613446 | AT49: 453.5 | AU49: 1.3744586 | AV49: -0.052245012 | AW49: -0.41332312 | AX49: 3 | AY49: 2.5530319 | AZ49: 40.19994 | BA49: 40.67365 | BB49: 10.646667 | BC49: 9.6328 | BD49: 0.46551776 | BE49: 15.343 | BF49: 12.3594 | BG49: 6.5166667 | BH49: 6.4594 | BI49: 7.3 | BJ49: 7.18 | BK49: 5.6593333 | BL49: 5.5614 | BM49: 5 | BN49: -3.5876667 | BO49: -7.1 | BP49: -3.5876667 | BQ49: 1.1508873 | BR49: -1.5018377 | BS49: 45 | BT49: 31 | BU49: 53 | BV49: 43 | BW49: 2011 | BY49: =(AE49-Standardisation_Parameters!$E$15)/Standardisation_Parameters!$F$15 -> 0.34459925 | BZ49: =VLOOKUP($D49,$CH:$CN,2,FALSE) -> 0.57223503 | CA49: =VLOOKUP($D49,$CH:$CN,3,FALSE) -> 0.28164626 | CB49: =VLOOKUP($D49,$CH:$CN,5,FALSE) -> 0.30587151 | CC49: =VLOOKUP($D49,$CH:$CN,6,FALSE) -> 0.3801294 | CD49: =VLOOKUP($D49,$CH:$CN,4,FALSE) -> 0.2257646 | CF49: THAILAND | CG49: MEDIUM HUMAN DEVELOPMENT | CH49: THA | CI49: 0.0074684449 | CJ49: 0.56816498 | CK49: 0.29223829 | CL49: 0.37344017 | CM49: 0.1539087 | CN49: 0.4614 | CP49: THAILAND | CQ49: MEDIUM HUMAN DEVELOPMENT | CR49: THA | CS49: THA2011 | CT49: 272 | CU49: 0.0074684449 | CV49: 0.56816498 | CW49: 0.29223829 | CX49: 0.15390573 | CY49: 49.555556 | CZ49: 47.24332 | DA49: 44.795613 | DB49: 54.167684
B50: SUDAN | C50: LOW HUMAN DEVELOPMENT | D50: SDN | E50: 18 | F50: 14.078667 | G50: 12.9036 | H50: -8 | I50: 4.3062799 | J50: 90.4 | K50: 68.365 | L50: 4.6147917 | M50: -2.4 | N50: 1500 | O50: 0.24169581 | P50: 6 | Q50: 0.3 | R50: 7904.5424 | S50: 0.2 | T50: 2.78193 | U50: 58.138901 | V50: 10.9 | W50: -10.925956 | X50: 9.9 | Y50: 20.517187 | AA50: 6 | AB50: 0.408 | AC50: -1.7054229 | AD50: -1.3199608 | AE50: 73.770492 | AG50: 4.5 | AH50: 4.5 | AI50: 4.25 | AJ50: 3.9213333 | AK50: 5.6964 | AL50: 10 | AM50: 0.92797834 | AN50: 0.9980082 | AO50: 0.9 | AP50: 23713.627 | AQ50: 3 | AR50: 16.28635 | AS50: 10.911169 | AT50: -48.5 | AV50: 30.651832 | AW50: 78.045424 | AX50: 0 | AY50: 0.23864835 | AZ50: 59.854491 | BA50: 60.955919 | BB50: 12.5 | BC50: 14.56 | BD50: -0.1922418 | BE50: 2.238 | BF50: 3.2016 | BG50: 2.0153333 | BH50: 4.6056 | BI50: 0.4 | BJ50: 1.3265 | BK50: 1.4526667 | BL50: 3.313 | BM50: 9 | BN50: -1.6826667 | BO50: 0.2 | BP50: -1.6826667 | BQ50: 0.020800317 | BR50: 239.17017 | BS50: 73 | BT50: 38 | BU50: 78 | BV50: 63 | BW50: 2011 | BY50: =(AE50-Standardisation_Parameters!$E$15)/Standardisation_Parameters!$F$15 -> 1.076005 | BZ50: =VLOOKUP($D50,$CH:$CN,2,FALSE) -> 1.4573081 | CA50: =VLOOKUP($D50,$CH:$CN,3,FALSE) -> 1.3814198 | CB50: =VLOOKUP($D50,$CH:$CN,5,FALSE) -> 1.4968699 | CC50: =VLOOKUP($D50,$CH:$CN,6,FALSE) -> 1.57249 | CD50: =VLOOKUP($D50,$CH:$CN,4,FALSE) -> 1.6416543 | CF50: TAJIKISTAN | CG50: MEDIUM HUMAN DEVELOPMENT | CH50: TJK | CI50: 1.393271 | CJ50: 1.4908395 | CK50: 1.6881859 | CL50: 1.5689509 | CM50: 1.588457 | CN50: 0.8966 | CP50: TAJIKISTAN | CQ50: MEDIUM HUMAN DEVELOPMENT | CR50: TJK | CS50: TJK2011 | CT50: 278 | CU50: 1.393271 | CV50: 1.4908395 | CW50: 1.6881859 | CX50: 1.5884524 | CY50: 72.888889 | CZ50: 71.221839 | DA50: 67.959372 | DB50: 69.590233
B51: SWAZILAND | C51: MEDIUM HUMAN DEVELOPMENT | D51: SWZ | E51: 5.9 | F51: 5.9523333 | G51: 7.718 | H51: 3.3 | I51: 1.2785365 | L51: 1.5766304 | M51: -0.5 | N51: 3210 | O51: 0.63168888 | P51: 5 | Q51: 2.8 | R51: 8.8203039 | S51: -10.8 | T51: -8.1952356 | U51: 16.74262 | V51: 1.7 | W51: 18.364476 | Y51: 17.241823 | Z51: 5 | AA51: 7 | AB51: 0.522 | AC51: -1.2679663 | AD51: -0.49580704 | AE51: 67.213115 | AF51: 3.3005615 | AG51: 2.5 | AH51: 3.25 | AI51: 2.5 | AJ51: -0.052333333 | AK51: -2.118 | AL51: 9.2 | AM51: 2.3515834 | AN51: 0.87249366 | AO51: 8.4 | AP51: 26.460912 | AQ51: 3 | AR51: 6.5090292 | AS51: 30.963299 | AT51: 133.7 | AU51: 0.85903661 | AV51: 3.0179543 | AW51: -0.91179696 | AX51: 3 | AY51: 0.89246641 | AZ51: 14.587125 | BA51: 14.100337 | BB51: 2.1333333 | BC51: 2.2648 | BD51: 0.086055441 | BE51: 11.168 | BF51: 11.3394 | BG51: 0.33366667 | BH51: 1.3756 | BI51: -1.6 | BJ51: -0.575 | BK51: -0.48833333 | BL51: 0.3012 | BM51: 7 | BN51: -13.651333 | BO51: -10.8 | BP51: -13.651333 | BQ51: -0.38824046 | BR51: -50.495222 | BS51: 55 | BT51: 31 | BU51: 63 | BV51: 49.666667 | BW51: 2011 | BY51: =(AE51-Standardisation_Parameters!$E$15)/Standardisation_Parameters!$F$15 -> 0.83879233 | BZ51: =VLOOKUP($D51,$CH:$CN,2,FALSE) -> 0.99171521 | CA51: =VLOOKUP($D51,$CH:$CN,3,FALSE) -> 0.57950336 | CB51: =VLOOKUP($D51,$CH:$CN,5,FALSE) -> 0.6832962 | CC51: =VLOOKUP($D51,$CH:$CN,6,FALSE) -> 0.82440784 | CD51: =VLOOKUP($D51,$CH:$CN,4,FALSE) -> 0.79743839 | CF51: TANZANIA, UNITED REPUBLIC OF | CG51: LOW HUMAN DEVELOPMENT | CH51: TZA | CI51: 0.59701155 | CJ51: 0.47319686 | CK51: 0.55148571 | CL51: 0.47382848 | CM51: 0.50047538 | CN51: 0.7878 | CP51: TANZANIA, UNITED REPUBLIC OF | CQ51: LOW HUMAN DEVELOPMENT | CR51: TZA | CS51: TZA2011 | CT51: 284 | CU51: 0.59701155 | CV51: 0.47319686 | CW51: 0.55148571 | CX51: 0.50047337 | CY51: 53.888889 | CZ51: 53.036215 | DA51: 54.649856 | DB51: 52.580287
B52: TANZANIA, UNITED REPUBLIC OF | C52: LOW HUMAN DEVELOPMENT | D52: TZA | E52: 12.661 | F52: 10.673333 | G52: 9.8648 | H52: 4.039 | I52: 2.5230184 | J52: 34.1 | K52: 15.077 | L52: 0.57709341 | M52: 6.4 | N52: 553 | O52: 148.62763 | P52: 3 | Q52: 4 | R52: 45.797061 | S52: -9 | T52: -6.8645626 | U52: 35.878994 | V52: 3 | W52: 4.6676389 | X52: -7.971 | Y52: 21.052029 | Z52: 6.2 | AA52: 3 | AB52: 0.466 | AC52: -0.09658169 | AD52: -0.51170462 | AE52: 68.306011 | AF52: 3.5632456 | AG52: 3.75 | AH52: 3.5 | AI52: 3 | AJ52: 1.9876667 | AK52: 2.3352 | AL52: 16.7 | AM52: 0.88782318 | AN52: 11.785614 | AO52: 12 | AP52: 137.39118 | AQ52: 3 | AR52: 22.818178 | AS52: 14.267319 | AT52: 22 | AU52: 1.0652054 | AV52: 26.27024 | AW52: -0.54202939 | AX52: 0 | AY52: 144.22579 | AZ52: 34.958161 | BA52: 32.672374 | BB52: 3.8333333 | BC52: 3.821 | BD52: -0.36945941 | BE52: 13.974 | BF52: 14.0454 | BG52: 6.474 | BH52: 6.8014 | BI52: 3.2 | BJ52: 3.5 | BK52: 3.32 | BL52: 3.702 | BM52: 5 | BN52: -8.783 | BO52: -9 | BP52: -8.783 | BQ52: 0.079699419 | BR52: -6.1838209 | BS52: 73 | BT52: 38 | BU52: 69 | BV52: 60 | BW52: 2011 | BY52: =(AE52-Standardisation_Parameters!$E$15)/Standardisation_Parameters!$F$15 -> 0.87832778 | BZ52: =VLOOKUP($D52,$CH:$CN,2,FALSE) -> 0.59701155 | CA52: =VLOOKUP($D52,$CH:$CN,3,FALSE) -> 0.47319686 | CB52: =VLOOKUP($D52,$CH:$CN,5,FALSE) -> 0.47382848 | CC52: =VLOOKUP($D52,$CH:$CN,6,FALSE) -> 0.50047538 | CD52: =VLOOKUP($D52,$CH:$CN,4,FALSE) -> 0.55148571 | CF52: UGANDA | CG52: LOW HUMAN DEVELOPMENT | CH52: UGA | CI52: 0.69872652 | CJ52: 0.4999031 | CK52: 0.67778573 | CL52: 0.52723137 | CM52: 0.58357997 | CN52: 0.679 | CP52: UGANDA | CQ52: LOW HUMAN DEVELOPMENT | CR52: UGA | CS52: UGA2011 | CT52: 290 | CU52: 0.69872652 | CV52: 0.4999031 | CW52: 0.67778573 | CX52: 0.58357798 | CY52: 56 | CZ52: 54.425313 | DA52: 56.350026 | DB52: 53.026683
B53: THAILAND | C53: MEDIUM HUMAN DEVELOPMENT | D53: THA | E53: 3.807 | F53: 2.075 | G53: 2.778 | H53: 3.107 | I53: 2.0475593 | J53: 13.963 | K53: 10.994 | L53: 3.9904147 | M53: 0.1 | N53: 5110 | O53: 1.7302823 | P53: 1 | Q53: 8.5 | R53: 24.607889 | S53: 3.8 | T53: 2.9496528 | U53: 23.871672 | V53: 4 | W53: 8.751099 | X53: 6.425 | Y53: 135.48373 | Z53: 2.795 | AA53: 6 | AB53: 0.682 | AC53: -0.55781899 | AD53: -0.19570797 | AE53: 8.7431694 | AF53: 4.5185917 | AG53: 2.75 | AH53: 2.5 | AI53: 3.5 | AJ53: 1.732 | AK53: 0.222 | AL53: 6.914 | AM53: 0.57935542 | AN53: 0.65702445 | AO53: 25.5 | AP53: 73.823668 | AQ53: 3 | AR53: 9.8835689 | AS53: 4.0844557 | AT53: 390 | AU53: 0.48020147 | AV53: -11.664701 | AW53: -0.75392111 | AX53: 2 | AY53: 1.8014264 | AZ53: 22.722708 | BA53: 20.959237 | BB53: 5.1343333 | BC53: 7.0086 | BD53: 0.77098168 | BE53: 29.228 | BF53: 25.3314 | BG53: 1.8603333 | BH53: 2.6218 | BI53: -0.8 | BJ53: 3.05 | BK53: 0.93333333 | BL53: 1.7394 | BM53: 4 | BN53: 5.4026667 | BO53: 3.8 | BP53: 5.4026667 | BQ53: -0.056823791 | BR53: 0.80634152 | BS53: 58 | BT53: 31 | BU53: 59 | BV53: 49.333333 | BW53: 2011 | BY53: =(AE53-Standardisation_Parameters!$E$15)/Standardisation_Parameters!$F$15 -> -1.276354 | BZ53: =VLOOKUP($D53,$CH:$CN,2,FALSE) -> 0.0074684449 | CA53: =VLOOKUP($D53,$CH:$CN,3,FALSE) -> 0.56816498 | CB53: =VLOOKUP($D53,$CH:$CN,5,FALSE) -> 0.37344017 | CC53: =VLOOKUP($D53,$CH:$CN,6,FALSE) -> 0.1539087 | CD53: =VLOOKUP($D53,$CH:$CN,4,FALSE) -> 0.29223829 | CF53: UZBEKISTAN | CG53: MEDIUM HUMAN DEVELOPMENT | CH53: UZB | CI53: 1.0947723 | CJ53: 1.3985318 | CK53: 1.761307 | CL53: 1.400564 | CM53: 1.3370357 | CN53: 1.0054 | CP53: UZBEKISTAN | CQ53: MEDIUM HUMAN DEVELOPMENT | CR53: UZB | CS53: UZB2011 | CT53: 295 | CU53: 1.0947723 | CV53: 1.3985318 | CW53: 1.761307 | CX53: 1.3370311 | CY53: 74.111111 | CZ53: 67.019319 | DA53: 62.969952 | DB53: 68.047306
B54: TOGO | C54: LOW HUMAN DEVELOPMENT | D54: TGO | E54: 4.1 | F54: 2.6296667 | G54: 3.5062 | K54: 26.962 | L54: 0.99247166 | M54: 3.9 | N54: 586 | O54: 17.115318 | P54: 6 | Q54: 4.8 | R54: 8.1772312 | S54: -8.1 | T54: -5.7642164 | U54: 56.493087 | V54: 5.1 | W54: 12.414284 | X54: -2.1 | Y54: 31.856441 | Z54: 3.5 | AA54: 6 | AB54: 0.435 | AC54: -0.96546774 | AD54: -0.92217763 | AE54: 86.338798 | AG54: 3 | AH54: 3.75 | AI54: 3.25 | AJ54: 1.4703333 | AK54: -1.0062 | AN54: 2.9219978 | AO54: 14.4 | AP54: 24.531694 | AQ54: 3 | AT54: 56 | AU54: 0.60132563 | AV54: -1.5440256 | AW54: -91.822769 | AX54: 8 | AY54: 26.341653 | AZ54: 55.760703 | BA54: 58.823785 | BB54: 5.2333333 | BC54: 4.88 | BD54: -0.010456491 | BE54: 14.593 | BF54: 13.5588 | BG54: 3.6 | BH54: 2.9 | BI54: 1.8 | BJ54: 1.65 | BK54: 1.4333333 | BL54: 0.7166 | BN54: -6.9666667 | BO54: -8.1 | BP54: -6.9666667 | BQ54: 0.10047847 | BR54: -33.077101 | BS54: 68 | BT54: 56 | BU54: 75 | BV54: 66.333333 | BW54: 2011 | BY54: =(AE54-Standardisation_Parameters!$E$15)/Standardisation_Parameters!$F$15 -> 1.5306626 | BZ54: =VLOOKUP($D54,$CH:$CN,2,FALSE) -> 0.74444912 | CA54: =VLOOKUP($D54,$CH:$CN,3,FALSE) -> 0.98304109 | CB54: =VLOOKUP($D54,$CH:$CN,5,FALSE) -> 0.94574273 | CC54: =VLOOKUP($D54,$CH:$CN,6,FALSE) -> 0.87580263 | CD54: =VLOOKUP($D54,$CH:$CN,4,FALSE) -> 0.8373226 | CF54: VIETNAM | CG54: MEDIUM HUMAN DEVELOPMENT | CH54: VNM | CI54: 0.67076433 | CJ54: 0.42781105 | CK54: 0.81738049 | CL54: 0.4583315 | CM54: 0.52570636 | CN54: 0.5702 | CP54: VIETNAM | CQ54: MEDIUM HUMAN DEVELOPMENT | CR54: VNM | CS54: VNM2011 | CT54: 301 | CU54: 0.67076433 | CV54: 0.42781105 | CW54: 0.81738049 | CX54: 0.52570459 | CY54: 58.333333 | CZ54: 53.457956 | DA54: 55.882637 | DB54: 51.821661
B55: UGANDA | C55: LOW HUMAN DEVELOPMENT | D55: UGA | E55: 18.687 | F55: 11.893667 | G55: 10.7742 | H55: 5.313 | I55: 4.3533997 | J55: 13.119 | K55: 15.499 | L55: 2.4723357 | M55: 6.6 | N55: 529 | O55: 337.06384 | P55: 3 | Q55: 4.6 | R55: 13.855833 | S55: -10.4 | T55: -4.2185047 | U55: 19.020627 | V55: 1.6 | W55: 27.472382 | X55: -3.983 | Y55: 17.118284 | Z55: 14.5 | AA55: 5 | AB55: 0.446 | AC55: -0.4773887 | AD55: -0.40333844 | AE55: 65.027322 | AF55: 3.5591894 | AG55: 3 | AH55: 3 | AI55: 3.25 | AJ55: 6.7933333 | AK55: 0.7258 | AL55: 24 | AM55: 1.8402364 | AN55: 2.800995 | AO55: 13.8 | AP55: 41.5675 | AQ55: 3 | AR55: 56.467948 | AS55: 35.166918 | AT55: 25.5 | AU55: 2.4912062 | AV55: 46.387466 | AW55: -0.86144167 | AX55: 0 | AY55: 328.10606 | AZ55: 17.16052 | BA55: 15.34456 | BB55: 1.642 | BC55: 1.8118 | BD55: 0.22174311 | BE55: 17.08 | BF55: 18.057 | BG55: 5.378 | BH55: 6.925 | BI55: 2.544 | BJ55: 2.686 | BK55: 2.0536667 | BL55: 3.5204 | BM55: 5 | BN55: -9.0213333 | BO55: -10.4 | BP55: -9.0213333 | BQ55: 0.01962016 | BR55: -10.801294 | BS55: 63 | BT55: 44 | BU55: 69 | BV55: 58.666667 | BW55: 2011 | BY55: =(AE55-Standardisation_Parameters!$E$15)/Standardisation_Parameters!$F$15 -> 0.75972144 | BZ55: =VLOOKUP($D55,$CH:$CN,2,FALSE) -> 0.69872652 | CA55: =VLOOKUP($D55,$CH:$CN,3,FALSE) -> 0.4999031 | CB55: =VLOOKUP($D55,$CH:$CN,5,FALSE) -> 0.52723137 | CC55: =VLOOKUP($D55,$CH:$CN,6,FALSE) -> 0.58357997 | CD55: =VLOOKUP($D55,$CH:$CN,4,FALSE) -> 0.67778573 | CF55: YEMEN | CG55: LOW HUMAN DEVELOPMENT | CH55: YEM | CI55: 1.3743461 | CJ55: 1.4583143 | CK55: 1.8144859 | CL55: 1.5359405 | CM55: 1.5580878 | CN55: 0.5702 | CP55: YEMEN | CQ55: LOW HUMAN DEVELOPMENT | CR55: YEM | CS55: YEM2011 | CT55: 307 | CU55: 1.3743461 | CV55: 1.4583143 | CW55: 1.8144859 | CX55: 1.5580833 | CY55: 75 | CZ55: 70.714217 | DA55: 67.643041 | DB55: 69.046573
